Workbook
Name UPDATE: 'Data Sheet'!$E$1

Sheet One Page View
B2: ='Data Sheet'!B1 & " - One Page View" -> EICHER MOTORS LTD - One Page View
C4: =data!C23 -> Eicher Motors Limited is an Indian multinational automotive company that manufactures motorcycles and commercial vehicles, headquartered in New Delhi. Eicher is the parent company of Royal Enfield, a manufacturer of middleweight motorcycles. It also manufactures Eicher branded trucks and buses, under a joint venture with Volvo Group.
B6: Key Financial Metrics | C6: =IFERROR('Data Sheet'!G16,0) -> 44286 | D6: =IFERROR('Data Sheet'!H16,0) -> 44651 | E6: =IFERROR('Data Sheet'!I16,0) -> 45016 | F6: =IFERROR('Data Sheet'!J16,0) -> 45382 | G6: =IFERROR('Data Sheet'!K16,0) -> 45747 | I6: Share Price - 5Y
B8: Total sales | C8: =IFERROR('Data Sheet'!G17,0) -> 8720.35 | D8: =IFERROR('Data Sheet'!H17,0) -> 10297.83 | E8: =IFERROR('Data Sheet'!I17,0) -> 14442.18 | F8: =IFERROR('Data Sheet'!J17,0) -> 16535.78 | G8: =IFERROR('Data Sheet'!K17,0) -> 18870.35
B9: Sales Growth Y-O-Y | C9: =IFERROR('Profit & Loss'!G4/'Profit & Loss'!F4-1,0) -> -0.047329023 | D9: =IFERROR('Profit & Loss'!H4/'Profit & Loss'!G4-1,0) -> 0.18089641 | E9: =IFERROR('Profit & Loss'!I4/'Profit & Loss'!H4-1,0) -> 0.40244887 | F9: =IFERROR('Profit & Loss'!J4/'Profit & Loss'!I4-1,0) -> 0.14496426 | G9: =IFERROR('Profit & Loss'!K4/'Profit & Loss'!J4-1,0) -> 0.14118294
B10: Gross Profit Margin(%) | C10: =IFERROR('Data Sheet'!G36,0) -> 0.23480021 | D10: =IFERROR('Data Sheet'!H36,0) -> 0.27508223 | E10: =IFERROR('Data Sheet'!I36,0) -> 0.32029652 | F10: =IFERROR('Data Sheet'!J36,0) -> 0.32902833 | G10: =IFERROR('Data Sheet'!K36,0) -> 0.33397473
B11: EBIDTA Margin(%) | C11: =IFERROR('Profit & Loss'!G28,0) -> 0.20449065 | D11: =IFERROR('Profit & Loss'!H28,0) -> 0.21145911 | E11: =IFERROR('Profit & Loss'!I28,0) -> 0.23858725 | F11: =IFERROR('Profit & Loss'!J28,0) -> 0.26181831 | G11: =IFERROR('Profit & Loss'!K28,0) -> 0.25026404
B12: EBIT Margin(%) | C12: =IFERROR('Profit & Loss'!G29,0) -> 0.1528035 | D12: =IFERROR('Profit & Loss'!H29,0) -> 0.16757317 | E12: =IFERROR('Profit & Loss'!I29,0) -> 0.20215161 | F12: =IFERROR('Profit & Loss'!J29,0) -> 0.2256785 | G12: =IFERROR('Profit & Loss'!K29,0) -> 0.21161452
B13: Net Profit Margin (%) | C13: =IFERROR('Profit & Loss'!G12/'Profit & Loss'!G4,0) -> 0.15445366 | D13: =IFERROR('Profit & Loss'!H12/'Profit & Loss'!H4,0) -> 0.162811 | E13: =IFERROR('Profit & Loss'!I12/'Profit & Loss'!I4,0) -> 0.20176594 | F13: =IFERROR('Profit & Loss'!J12/'Profit & Loss'!J4,0) -> 0.24196077 | G13: =IFERROR('Profit & Loss'!K12/'Profit & Loss'!K4,0) -> 0.25089307
B14: Earnig Per Share (In rs) | C14: =IFERROR('Profit & Loss'!G13,0) -> 49.282473 | D14: =IFERROR('Profit & Loss'!H13,0) -> 61.324067 | E14: =IFERROR('Profit & Loss'!I13,0) -> 106.5426 | F14: =IFERROR('Profit & Loss'!J13,0) -> 146.12893 | G14: =IFERROR('Profit & Loss'!K13,0) -> 172.66375
B15: Eps Growth Margin Y-o-Y | C15: =IFERROR('Profit & Loss'!G13/'Profit & Loss'!F13-1,0) -> -0.26350285 | D15: =IFERROR('Profit & Loss'!H13/'Profit & Loss'!G13-1,0) -> 0.24433826 | E15: =IFERROR('Profit & Loss'!I13/'Profit & Loss'!H13-1,0) -> 0.73737002 | F15: =IFERROR('Profit & Loss'!J13/'Profit & Loss'!I13-1,0) -> 0.37155402 | G15: =IFERROR('Profit & Loss'!K13/'Profit & Loss'!J13-1,0) -> 0.18158501
B16: Dividend per Share | C16: =IFERROR('Profit & Loss'!G32,0) -> 17 | D16: =IFERROR('Profit & Loss'!H32,0) -> 21 | E16: =IFERROR('Profit & Loss'!I32,0) -> 37 | F16: =IFERROR('Profit & Loss'!J32,0) -> 51 | G16: =IFERROR('Profit & Loss'!K32,0) -> 70
B17: Divident Growth Margin Y-o-Y | C17: =IFERROR('Profit & Loss'!G33,0) -> 0.36049817 | D17: =IFERROR('Profit & Loss'!H33,0) -> 0.23529412 | E17: =IFERROR('Profit & Loss'!I33,0) -> 0.76190476 | F17: =IFERROR('Profit & Loss'!J33,0) -> 0.37837838 | G17: =IFERROR('Profit & Loss'!K33,0) -> 0.37254902
B19: Key Financial Ratio | C19: 44286 | D19: 44651 | E19: 45016 | F19: 45382 | G19: 45747 | I19: Volume - 5Y
B21: Price to Earnings | C21: =IFERROR('Profit & Loss'!G14,0) -> 52.837242 | D21: =IFERROR('Profit & Loss'!H14,0) -> 40.068282 | E21: =IFERROR('Profit & Loss'!I14,0) -> 27.677662 | F21: =IFERROR('Profit & Loss'!J14,0) -> 27.505163 | G21: =IFERROR('Profit & Loss'!K14,0) -> 30.971759
B22: EV/EBIDTA | C22: =IFERROR('Profit & Loss'!G40,0) -> 36.761855 | D22: =IFERROR('Profit & Loss'!H40,0) -> 29.649435 | E22: =IFERROR('Profit & Loss'!I40,0) -> 23.26767 | F22: =IFERROR('Profit & Loss'!J40,0) -> 25.482129 | G22: =IFERROR('Profit & Loss'!K40,0) -> 31.090922
B23: EV/Sales | C23: =IFERROR('Profit & Loss'!G41,0) -> 7.5174555 | D23: =IFERROR('Profit & Loss'!H41,0) -> 6.2696433 | E23: =IFERROR('Profit & Loss'!I41,0) -> 5.5513695 | F23: =IFERROR('Profit & Loss'!J41,0) -> 6.6716879 | G23: =IFERROR('Profit & Loss'!K41,0) -> 7.7809396
B24: Price to Book | C24: =IFERROR('Profit & Loss'!G42,0) -> 6.2218444 | D24: =IFERROR('Profit & Loss'!H42,0) -> 5.3282425 | E24: =IFERROR('Profit & Loss'!I42,0) -> 5.3802229 | F24: =IFERROR('Profit & Loss'!J42,0) -> 6.0983764 | G24: =IFERROR('Profit & Loss'!K42,0) -> 6.8853569
B25: Retrun on Equity(%) | C25: =IFERROR('Profit & Loss'!G15/'Data Sheet'!G74,0) -> 0.17885979 | D25: =IFERROR('Profit & Loss'!H15/'Data Sheet'!H74,0) -> 0.15224138 | E25: =IFERROR('Profit & Loss'!I15/'Data Sheet'!I74,0) -> 0.15360482 | F25: =IFERROR('Profit & Loss'!J15/'Data Sheet'!J74,0) -> 0.17388178 | G25: =IFERROR('Profit & Loss'!K15/'Data Sheet'!K74,0) -> 0.19679176
B26: Retrun on Capital(%) | C26: =IFERROR('Data Sheet'!G30/('Data Sheet'!G74-'Data Sheet'!G59),0) -> 0.093929576 | D26: =IFERROR('Data Sheet'!H30/('Data Sheet'!H74-'Data Sheet'!H59),0) -> 0.10457756 | E26: =IFERROR('Data Sheet'!I30/('Data Sheet'!I74-'Data Sheet'!I59),0) -> 0.15410146 | F26: =IFERROR('Data Sheet'!J30/('Data Sheet'!J74-'Data Sheet'!J59),0) -> 0.17628942 | G26: =IFERROR('Data Sheet'!K30/('Data Sheet'!K74-'Data Sheet'!K59),0) -> 0.1772118
B28: Top 10 Share Holders | C28: =data!J25 -> No of Shares (in Cr) | D28: =data!K25 -> Shareholding (%) | F28: =data!L25 -> Market value(in Cr) | I28: Share Holding Pattern
B30: =data!I26 -> THE SIMRAN SIDDHARTHA TARA BENEFIT TRUST (Name of trustees are mentioned in Note-4) | C30: =data!J26 -> 12.030648 | D30: =data!K26 -> 0.4386 | G30: =data!L26 -> 96509.858
B31: =data!I27 -> Sbi Nifty 50 Etf | C31: =data!J27 -> 0.8167427 | D31: =data!K27 -> 0.0298 | G31: =data!L27 -> 6551.9099
B32: =data!I28 -> Hdfc Trustee Company Limited-Hdfc Flexi Cap Fund | C32: =data!J28 -> 0.6861231 | D32: =data!K28 -> 0.025 | G32: =data!L28 -> 5504.0795
B33: =data!I29 -> THE BRINDA LAL TRUST (Mrs Anita Lal Mr. Vikram Lal & Mr. Ravi Prakash) | C33: =data!J29 -> 0.485707 | D33: =data!K29 -> 0.0177 | G33: =data!L29 -> 3896.3416
B34: =data!I30 -> New World Fund Inc | C34: =data!J30 -> 0.421887 | D34: =data!K30 -> 0.0154 | G34: =data!L30 -> 3384.3775
B35: =data!I31 -> Uti Nifty 50 Etf | C35: =data!J31 -> 0.3671085 | D35: =data!K31 -> 0.0134 | G35: =data!L31 -> 2944.9444
B36: =data!I32 -> Government Of Singapore | C36: =data!J32 -> 0.3233263 | D36: =data!K32 -> 0.0118 | G36: =data!L32 -> 2593.7236
B37: =data!I33 -> Simran Lal | C37: =data!J33 -> 0.315241 | D37: =data!K33 -> 0.0115 | G37: =data!L33 -> 2528.8633
B38: =data!I34 -> TARA LAL | C38: =data!J34 -> 0.314994 | D38: =data!K34 -> 0.0115 | G38: =data!L34 -> 2526.8819
B39: =data!I35 -> Nps Trust- A/C Sbi Pension Fund Scheme - State Govt | C39: =data!J35 -> 0.3089972 | D39: =data!K35 -> 0.0113 | G39: =data!L35 -> 2478.7755
B41: Mangerial Remuneration | C41: Designation | D41: Remuneration | F41: x of Median Salary | I41: Capital Strucutre
B43: Mr. Siddhartha Lal | C43: CMD | D43: 32.72 | F43: 358.4 | I43: Share Price as 18-02-2026 | L43: 8022
B44: Mr. S Sandilya | C44: CNID | D44: 73.03 | F44: 9.1 | I44: Number of Shares o/s | L44: ='Data Sheet'!B6 -> 27.429924
B45: Mr. Govindarajan Balakrishnan | C45: MD | D45: 19.4 | F45: 211.8 | I45: Market Captialziation | L45: =L43*L44 -> 220042.85
B46: Mr. Atul Sharma | C46: CS | I46: Less: Cash & Equlivant | L46: ='Data Sheet'!K69*-1 -> -263.01
B47: Ms. Vidhya Srinivasan | C47: CFO | I47: Add:Total Debt | L47: ='Data Sheet'!K59 -> 458.13
I48: Entrpise Value | L48: =SUM(L45:L47) -> 220237.97
B50: Recent updates
B52: Eicher Motors Ltd Hits New 52-Week High of Rs.8140 on 19 Feb 2026
B53: Eicher Motors Q3 earnings: Net profit rises 21% to ?1,421 crore, board approves capacity expansion for Royal Enfield
B54: Eicher Motors Q3 Results: Cons PAT jumps 21% YoY to Rs 1,420 crore, revenue surges 23%
B55: Top gainers and losers on February 11: Eicher Motors rise 6.45%, Apollo Hospitals, Max Healthcare gain over 3%; check full list
B57: Souces
B58: Company annual report
B59: yaho finnaces
B60: Screner
B61: Investpedia
B62: Euitymaster

Sheet Historical IFS
D2: =data!C23 -> Eicher Motors Limited is an Indian multinational automotive company that manufactures motorcycles and commercial vehicles, headquartered in New Delhi. Eicher is the parent company of Royal Enfield, a manufacturer of middleweight motorcycles. It also manufactures Eicher branded trucks and buses, under a joint venture with Volvo Group.
B9: ="Historical Finanical Statement - "&'Balance Sheet'!A1 -> Historical Finanical Statement - EICHER MOTORS LTD
B10: Years | C10: ='Balance Sheet'!B3 -> 42460 | D10: ='Balance Sheet'!C3 -> 42825 | E10: ='Balance Sheet'!D3 -> 43190 | F10: ='Balance Sheet'!E3 -> 43555 | G10: ='Balance Sheet'!F3 -> 43921 | H10: ='Balance Sheet'!G3 -> 44286 | I10: ='Balance Sheet'!H3 -> 44651 | J10: ='Balance Sheet'!I3 -> 45016 | ... L10: ='Balance Sheet'!K3 -> 45747 | M10: LTM
A11: # | B11: Income Statement
B12: Sales | C12: =IFERROR('Profit & Loss'!B4,'Profit & Loss'!B40) -> 6173.46 | D12: =IFERROR('Profit & Loss'!C4,'Profit & Loss'!C40) -> 7033.36 | E12: =IFERROR('Profit & Loss'!D4,'Profit & Loss'!D40) -> 8964.96 | F12: =IFERROR('Profit & Loss'!E4,'Profit & Loss'!E40) -> 9797.06 | G12: =IFERROR('Profit & Loss'!F4,'Profit & Loss'!F40) -> 9153.58 | H12: =IFERROR('Profit & Loss'!G4,'Profit & Loss'!G40) -> 8720.35 | I12: =IFERROR('Profit & Loss'!H4,'Profit & Loss'!H40) -> 10297.83 | J12: =IFERROR('Profit & Loss'!I4,'Profit & Loss'!I40) -> 14442.18 | ... L12: =IFERROR('Profit & Loss'!K4,'Profit & Loss'!K40) -> 18870.35 | M12: =IFERROR(SUM(#REF!),0) -> 0
B13: Sales Growth | C13: - | D13: =IFERROR(D12/C12-1,0) -> 0.1392898 | E13: =IFERROR(E12/D12-1,0) -> 0.27463403 | F13: =IFERROR(F12/E12-1,0) -> 0.092816923 | G13: =IFERROR(G12/F12-1,0) -> -0.065680929 | H13: =IFERROR(H12/G12-1,0) -> -0.047329023 | I13: =IFERROR(I12/H12-1,0) -> 0.18089641 | J13: =IFERROR(J12/I12-1,0) -> 0.40244887 | K13: =IFERROR(K12/J12-1,0) -> 0.14496426 | L13: =IFERROR(L12/K12-1,0) -> 0.14118294 | M13: =M12/L12-1 -> -1
B15: COGS | C15: =IFERROR(SUM('Data Sheet'!B18,'Data Sheet'!B20:B22)-1*'Data Sheet'!B190,0) -> 4067.88 | D15: =IFERROR(SUM('Data Sheet'!C18,'Data Sheet'!C20:C22)-1*'Data Sheet'!C190,0) -> 4371.11 | E15: =IFERROR(SUM('Data Sheet'!D18,'Data Sheet'!D20:D22)-1*'Data Sheet'!D190,0) -> 5515.92 | F15: =IFERROR(SUM('Data Sheet'!E18,'Data Sheet'!E20:E22)-1*'Data Sheet'!E190,0) -> 6302.53 | G15: =IFERROR(SUM('Data Sheet'!F18,'Data Sheet'!F20:F22)-1*'Data Sheet'!F190,0) -> 6029.8 | H15: =IFERROR(SUM('Data Sheet'!G18,'Data Sheet'!G20:G22)-1*'Data Sheet'!G190,0) -> 6466.91 | I15: =IFERROR(SUM('Data Sheet'!H18,'Data Sheet'!H20:H22)-1*'Data Sheet'!H190,0) -> 7316.49 | J15: =IFERROR(SUM('Data Sheet'!I18,'Data Sheet'!I20:I22)-1*'Data Sheet'!I190,0) -> 9753.15 | ... L15: =IFERROR(SUM('Data Sheet'!K18,'Data Sheet'!K20:K22)-1*'Data Sheet'!K190,0) -> 12404.62 | M15: =IFERROR(SUM(#REF!),0) -> 0
B16: COGS % Sales | C16: =C15/C12 -> 0.65893032 | D16: =D15/D12 -> 0.62148248 | E16: =E15/E12 -> 0.61527547 | F16: =F15/F12 -> 0.6433083 | G16: =G15/G12 -> 0.6587368 | H16: =H15/H12 -> 0.74158835 | I16: =I15/I12 -> 0.71048852 | J16: =J15/J12 -> 0.67532395 | ... M16: =M15/M12 -> #DIV/0!
B18: Gross Profit | C18: =C12-C15 -> 2105.58 | D18: =D12-D15 -> 2662.25 | E18: =E12-E15 -> 3449.04 | F18: =F12-F15 -> 3494.53 | G18: =G12-G15 -> 3123.78 | H18: =H12-H15 -> 2253.44 | I18: =I12-I15 -> 2981.34 | J18: =J12-J15 -> 4689.03 | ... M18: =M12-M15 -> 0
B19: Gross Profit Margin | C19: =C18/C12 -> 0.34106968 | D19: =D18/D12 -> 0.37851752 | E19: =E18/E12 -> 0.38472453 | F19: =F18/F12 -> 0.3566917 | G19: =G18/G12 -> 0.3412632 | H19: =H18/H12 -> 0.25841165 | I19: =I18/I12 -> 0.28951148 | J19: =J18/J12 -> 0.32467605 | ... M19: =M18/M12 -> #DIV/0!
B21: Selling & Other Expenses | C21: =IFERROR(SUM('Data Sheet'!B23:B24),0) -> 477.9 | D21: =IFERROR(SUM('Data Sheet'!C23:C24),0) -> 507.55 | E21: =IFERROR(SUM('Data Sheet'!D23:D24),0) -> 674.28 | F21: =IFERROR(SUM('Data Sheet'!E23:E24),0) -> 800.45 | G21: =IFERROR(SUM('Data Sheet'!F23:F24),0) -> 856.8 | H21: =IFERROR(SUM('Data Sheet'!G23:G24),0) -> 676.11 | I21: =IFERROR(SUM('Data Sheet'!H23:H24),0) -> 952.36 | J21: =IFERROR(SUM('Data Sheet'!I23:I24),0) -> 1306.56 | ... L21: =IFERROR(SUM('Data Sheet'!K23:K24),0) -> 1906.67
B22: S&G % of sales | C22: =C21/C12 -> 0.077412019 | D22: =D21/D12 -> 0.072163234 | E22: =E21/E12 -> 0.075212829 | F22: =F21/F12 -> 0.081703082 | G22: =G21/G12 -> 0.093602722 | H22: =H21/H12 -> 0.077532438 | I22: =I21/I12 -> 0.09248162 | J22: =J21/J12 -> 0.090468336 | ... M22: =M21/M12 -> #DIV/0!
B24: EBITDA | C24: =C18-C21 -> 1627.68 | D24: =D18-D21 -> 2154.7 | E24: =E18-E21 -> 2774.76 | F24: =F18-F21 -> 2694.08 | G24: =G18-G21 -> 2266.98 | H24: =H18-H21 -> 1577.33 | I24: =I18-I21 -> 2028.98 | J24: =J18-J21 -> 3382.47 | ... L24: =L18-L21 -> 4559.06 | M24: =IFERROR(SUM('Data Sheet'!H44:K46),0) -> 3010.92
B25: EBITA Margin | C25: =C24/C12 -> 0.26365766 | D25: =D24/D12 -> 0.30635429 | E25: =E24/E12 -> 0.3095117 | F25: =F24/F12 -> 0.27498862 | G25: =G24/G12 -> 0.24766048 | H25: =H24/H12 -> 0.18087921 | I25: =I24/I12 -> 0.19702986 | J25: =J24/J12 -> 0.23420772 | ... M25: =M24/M12 -> #DIV/0!
B27: Intrest | C27: =IFERROR('Data Sheet'!B27,0) -> 2.12 | D27: =IFERROR('Data Sheet'!C27,0) -> 3.56 | E27: =IFERROR('Data Sheet'!D27,0) -> 5.34 | F27: =IFERROR('Data Sheet'!E27,0) -> 7.33 | G27: =IFERROR('Data Sheet'!F27,0) -> 18.88 | H27: =IFERROR('Data Sheet'!G27,0) -> 16.45 | I27: =IFERROR('Data Sheet'!H27,0) -> 18.78 | J27: =IFERROR('Data Sheet'!I27,0) -> 28.02 | ... L27: =IFERROR('Data Sheet'!K27,0) -> 54.34 | M27: =IFERROR(SUM('Data Sheet'!H46:K46),0) -> 62.99
B28: Interst % sales | C28: =C27/C12 -> 0.00034340548 | D28: =D27/D12 -> 0.00050615922 | E28: =E27/E12 -> 0.00059565241 | F28: =F27/F12 -> 0.00074818364 | G28: =G27/G12 -> 0.002062581 | H28: =H27/H12 -> 0.0018863922 | I28: =I27/I12 -> 0.0018236852 | J28: =J27/J12 -> 0.0019401503 | ... M28: =M27/M12 -> #DIV/0!
B30: Depreciation | C30: =IFERROR('Data Sheet'!B26,0) -> 136.6 | D30: =IFERROR('Data Sheet'!C26,0) -> 153.81 | E30: =IFERROR('Data Sheet'!D26,0) -> 223.3 | F30: =IFERROR('Data Sheet'!E26,0) -> 300.28 | G30: =IFERROR('Data Sheet'!F26,0) -> 381.54 | H30: =IFERROR('Data Sheet'!G26,0) -> 450.73 | I30: =IFERROR('Data Sheet'!H26,0) -> 451.93 | J30: =IFERROR('Data Sheet'!I26,0) -> 526.21 | ... L30: =IFERROR('Data Sheet'!K26,0) -> 729.33 | M30: =IFERROR(SUM('Data Sheet'!H45:K45),0) -> 778.26
B31: Depreciation % sales | C31: =C30/C12 -> 0.022126976 | D31: =D30/D12 -> 0.021868637 | E31: =E30/E12 -> 0.024908087 | F31: =F30/F12 -> 0.030650011 | G31: =G30/G12 -> 0.041682052 | H31: =H30/H12 -> 0.051687146 | I31: =I30/I12 -> 0.043885945 | J31: =J30/J12 -> 0.036435635 | ... M31: =M30/M12 -> #DIV/0!
B33: Earnig Before Tax | C33: =IFERROR(C24-SUM(C27:C31),0) -> 1488.9375 | D33: =IFERROR(D24-SUM(D27:D31),0) -> 1997.3076 | E33: =IFERROR(E24-SUM(E27:E31),0) -> 2546.0945 | F33: =IFERROR(F24-SUM(F27:F31),0) -> 2386.4386 | G33: =IFERROR(G24-SUM(G27:G31),0) -> 1866.5163 | H33: =IFERROR(H24-SUM(H27:H31),0) -> 1110.0964 | I33: =IFERROR(I24-SUM(I27:I31),0) -> 1558.2243 | J33: =IFERROR(J24-SUM(J27:J31),0) -> 2828.2016 | ... M33: =IFERROR(M24-SUM(M27:M31),0) -> 0
B34: EBT % sales | C34: =C33/C12 -> 0.24118364 | D34: =D33/D12 -> 0.28397631 | E34: =E33/E12 -> 0.28400512 | F34: =F33/F12 -> 0.24358722 | G34: =G33/G12 -> 0.20391107 | H34: =H33/H12 -> 0.12729953 | I34: =I33/I12 -> 0.15131579 | J34: =J33/J12 -> 0.19582927 | ... M34: =M33/M12 -> #DIV/0!
B36: Tax | C36: =IFERROR('Data Sheet'!B29,0) -> 538.88 | D36: =IFERROR('Data Sheet'!C29,0) -> 720.3 | E36: =IFERROR('Data Sheet'!D29,0) -> 935.93 | F36: =IFERROR('Data Sheet'!E29,0) -> 1077.04 | G36: =IFERROR('Data Sheet'!F29,0) -> 527.45 | H36: =IFERROR('Data Sheet'!G29,0) -> 451.5 | I36: =IFERROR('Data Sheet'!H29,0) -> 525.91 | J36: =IFERROR('Data Sheet'!I29,0) -> 885.69 | ... L36: =IFERROR('Data Sheet'!K29,0) -> 1198.63 | M36: =IFERROR(SUM('Data Sheet'!H48:K48),0) -> 1394.66
B37: effective tax rate | C37: =C36/C24 -> 0.33107245 | D37: =D36/D24 -> 0.33429248 | E37: =E36/E24 -> 0.33730124 | F37: =F36/F24 -> 0.39978026 | G37: =G36/G24 -> 0.23266637 | H37: =H36/H24 -> 0.28624321 | I37: =I36/I24 -> 0.2591992 | J37: =J36/J24 -> 0.26184711 | ... M37: =M36/M24 -> 0.46320062
B39: Net Profit | C39: =IFERROR(C33-C36,0) -> 950.05753 | D39: =IFERROR(D33-D36,0) -> 1277.0076 | E39: =IFERROR(E33-E36,0) -> 1610.1645 | F39: =IFERROR(F33-F36,0) -> 1309.3986 | G39: =IFERROR(G33-G36,0) -> 1339.0663 | H39: =IFERROR(H33-H36,0) -> 658.59643 | I39: =IFERROR(I33-I36,0) -> 1032.3143 | J39: =IFERROR(J33-J36,0) -> 1942.5116 | ... M39: =IFERROR(M33-M36,0) -> -1394.66
B40: Net Margin | C40: =IFERROR(C39/C12,0) -> 0.15389385 | D40: =IFERROR(D39/D12,0) -> 0.18156438 | E40: =IFERROR(E39/E12,0) -> 0.17960643 | F40: =IFERROR(F39/F12,0) -> 0.1336522 | G40: =IFERROR(G39/G12,0) -> 0.1462888 | H40: =IFERROR(H39/H12,0) -> 0.075524082 | I40: =IFERROR(I39/I12,0) -> 0.10024581 | J40: =IFERROR(J39/J12,0) -> 0.13450266 | ... M40: =IFERROR(M39/M12,0) -> 0
B42: No of Equtiy shares | C42: =IFERROR('Data Sheet'!B93,0) -> 27.16 | D42: =IFERROR('Data Sheet'!C93,0) -> 27.21 | E42: =IFERROR('Data Sheet'!D93,0) -> 27.26 | F42: =IFERROR('Data Sheet'!E93,0) -> 27.28 | G42: =IFERROR('Data Sheet'!F93,0) -> 27.31 | H42: =IFERROR('Data Sheet'!G93,0) -> 27.33 | I42: =IFERROR('Data Sheet'!H93,0) -> 27.34 | J42: =IFERROR('Data Sheet'!I93,0) -> 27.35 | ... L42: =IFERROR('Data Sheet'!K93,0) -> 27.42
B44: Earning per Share | C44: =IFERROR(C39/C42,0) -> 34.980027 | D44: =IFERROR(D39/D42,0) -> 46.931556 | E44: =IFERROR(E39/E42,0) -> 59.066929 | F44: =IFERROR(F39/F42,0) -> 47.998482 | G44: =IFERROR(G39/G42,0) -> 49.032086 | H44: =IFERROR(H39/H42,0) -> 24.09793 | I44: =IFERROR(I39/I42,0) -> 37.758387 | J44: =IFERROR(J39/J42,0) -> 71.024191 | ... M44: =IFERROR(M39/M42,0) -> 0
B45: EPS Groth | D45: =IFERROR(D44/C44-1,0) -> 0.34166722 | E45: =IFERROR(E44/D44-1,0) -> 0.258576 | F45: =IFERROR(F44/E44-1,0) -> -0.18738822 | G45: =IFERROR(G44/F44-1,0) -> 0.021534078 | H45: =IFERROR(H44/G44-1,0) -> -0.50852733 | I45: =IFERROR(I44/H44-1,0) -> 0.56687262 | J45: =IFERROR(J44/I44-1,0) -> 0.88101763 | K45: =IFERROR(K44/J44-1,0) -> 0.17389749 | ... M45: =IFERROR(M44/L44-1,0) -> -1
B47: Dividend per Share | C47: =IFERROR('Data Sheet'!B31/'Historical IFS'!C42,0) -> 10 | D47: =IFERROR('Data Sheet'!C31/'Historical IFS'!D42,0) -> 10 | E47: =IFERROR('Data Sheet'!D31/'Historical IFS'!E42,0) -> 11 | F47: =IFERROR('Data Sheet'!E31/'Historical IFS'!F42,0) -> 12.5 | G47: =IFERROR('Data Sheet'!F31/'Historical IFS'!G42,0) -> 12.495423 | H47: =IFERROR('Data Sheet'!G31/'Historical IFS'!H42,0) -> 17 | I47: =IFERROR('Data Sheet'!H31/'Historical IFS'!I42,0) -> 21 | J47: =IFERROR('Data Sheet'!I31/'Historical IFS'!J42,0) -> 37 | ... M47: =IFERROR('Data Sheet'!L31/'Historical IFS'!M42,0) -> 0
B48: dividend payout ratio | C48: =IFERROR(C47/C44,0) -> 0.28587742 | D48: =IFERROR(D47/D44,0) -> 0.21307625 | E48: =IFERROR(E47/E44,0) -> 0.18622942 | F48: =IFERROR(F47/F44,0) -> 0.2604249 | G48: =IFERROR(G47/G44,0) -> 0.25484176 | H48: =IFERROR(H47/H44,0) -> 0.70545478 | I48: =IFERROR(I47/I44,0) -> 0.55616783 | J48: =IFERROR(J47/J44,0) -> 0.52094926 | ... M48: =IFERROR(M47/M44,0) -> 0
B50: Retain Earnings | C50: =IFERROR(IF(C44>C47,1-C48,0),0) -> 0.71412258 | D50: =IFERROR(IF(D44>D47,1-D48,0),0) -> 0.78692375 | E50: =IFERROR(IF(E44>E47,1-E48,0),0) -> 0.81377058 | F50: =IFERROR(IF(F44>F47,1-F48,0),0) -> 0.7395751 | G50: =IFERROR(IF(G44>G47,1-G48,0),0) -> 0.74515824 | H50: =IFERROR(IF(H44>H47,1-H48,0),0) -> 0.29454522 | I50: =IFERROR(IF(I44>I47,1-I48,0),0) -> 0.44383217 | J50: =IFERROR(IF(J44>J47,1-J48,0),0) -> 0.47905074 | ... M50: =IFERROR(IF(M44>M47,1-M48,0),0) -> 0
A52: # | B52: Blancesheet
B53: Equity Share Capital | C53: =IFERROR('Data Sheet'!B57,0) -> 27.16 | D53: =IFERROR('Data Sheet'!C57,0) -> 27.21 | E53: =IFERROR('Data Sheet'!D57,0) -> 27.26 | F53: =IFERROR('Data Sheet'!E57,0) -> 27.28 | G53: =IFERROR('Data Sheet'!F57,0) -> 27.3 | H53: =IFERROR('Data Sheet'!G57,0) -> 27.33 | I53: =IFERROR('Data Sheet'!H57,0) -> 27.34 | J53: =IFERROR('Data Sheet'!I57,0) -> 27.35 | ... M53: =IFERROR('Data Sheet'!L57,0) -> 0
B54: Reserves | C54: =IFERROR('Data Sheet'!B58,0) -> 3625.93 | D54: =IFERROR('Data Sheet'!C58,0) -> 5317.86 | E54: =IFERROR('Data Sheet'!D58,0) -> 7002.81 | F54: =IFERROR('Data Sheet'!E58,0) -> 8891.44 | G54: =IFERROR('Data Sheet'!F58,0) -> 9953.63 | H54: =IFERROR('Data Sheet'!G58,0) -> 11410.75 | I54: =IFERROR('Data Sheet'!H58,0) -> 12580.66 | J54: =IFERROR('Data Sheet'!I58,0) -> 14962.93 | ... M54: =IFERROR('Data Sheet'!L58,0) -> 0
B55: Borrowings | C55: =IFERROR('Data Sheet'!B59,0) -> 22.57 | D55: =IFERROR('Data Sheet'!C59,0) -> 111.85 | E55: =IFERROR('Data Sheet'!D59,0) -> 150.84 | F55: =IFERROR('Data Sheet'!E59,0) -> 186.76 | G55: =IFERROR('Data Sheet'!F59,0) -> 249 | H55: =IFERROR('Data Sheet'!G59,0) -> 219.25 | I55: =IFERROR('Data Sheet'!H59,0) -> 107.71 | J55: =IFERROR('Data Sheet'!I59,0) -> 288.41 | ... M55: =IFERROR('Data Sheet'!L59,0) -> 0
B56: Other Liabilities | C56: =IFERROR('Data Sheet'!B60,0) -> 1263.35 | D56: =IFERROR('Data Sheet'!C60,0) -> 1552.16 | E56: =IFERROR('Data Sheet'!D60,0) -> 2341.32 | F56: =IFERROR('Data Sheet'!E60,0) -> 2281.35 | G56: =IFERROR('Data Sheet'!F60,0) -> 2219.79 | H56: =IFERROR('Data Sheet'!G60,0) -> 2901.28 | I56: =IFERROR('Data Sheet'!H60,0) -> 3424.12 | J56: =IFERROR('Data Sheet'!I60,0) -> 3918.95 | ... M56: =IFERROR('Data Sheet'!L60,0) -> 0
B57: Total Liabilities | C57: =IFERROR('Data Sheet'!B61,0) -> 4939.01 | D57: =IFERROR('Data Sheet'!C61,0) -> 7009.08 | E57: =IFERROR('Data Sheet'!D61,0) -> 9522.23 | F57: =IFERROR('Data Sheet'!E61,0) -> 11386.83 | G57: =IFERROR('Data Sheet'!F61,0) -> 12449.72 | H57: =IFERROR('Data Sheet'!G61,0) -> 14558.61 | I57: =IFERROR('Data Sheet'!H61,0) -> 16139.83 | J57: =IFERROR('Data Sheet'!I61,0) -> 19197.64 | ... M57: =IFERROR('Data Sheet'!L61,0) -> 0
B59: Fix Assest Net Block | C59: =IFERROR('Data Sheet'!B62,0) -> 789.59 | D59: =IFERROR('Data Sheet'!C62,0) -> 872.78 | E59: =IFERROR('Data Sheet'!D62,0) -> 1501.69 | F59: =IFERROR('Data Sheet'!E62,0) -> 1874.58 | G59: =IFERROR('Data Sheet'!F62,0) -> 2377.52 | H59: =IFERROR('Data Sheet'!G62,0) -> 2433.3 | I59: =IFERROR('Data Sheet'!H62,0) -> 2424.28 | J59: =IFERROR('Data Sheet'!I62,0) -> 2689.99 | ... L59: =IFERROR('Data Sheet'!K62,0) -> 3473.47
B60: Capital Work in Progress | C60: =IFERROR('Data Sheet'!B63,0) -> 94.48 | D60: =IFERROR('Data Sheet'!C63,0) -> 373.77 | E60: =IFERROR('Data Sheet'!D63,0) -> 333.21 | F60: =IFERROR('Data Sheet'!E63,0) -> 449.74 | G60: =IFERROR('Data Sheet'!F63,0) -> 312.17 | H60: =IFERROR('Data Sheet'!G63,0) -> 314.29 | I60: =IFERROR('Data Sheet'!H63,0) -> 504.78 | J60: =IFERROR('Data Sheet'!I63,0) -> 472.07 | ... L60: =IFERROR('Data Sheet'!K63,0) -> 491.47 | M60: =IFERROR('Data Sheet'!N63,0) -> 0
B61: Investments | C61: =IFERROR('Data Sheet'!B64,0) -> 3388.24 | D61: =IFERROR('Data Sheet'!C64,0) -> 4987.13 | E61: =IFERROR('Data Sheet'!D64,0) -> 5580.84 | F61: =IFERROR('Data Sheet'!E64,0) -> 4922.52 | G61: =IFERROR('Data Sheet'!F64,0) -> 5748.77 | H61: =IFERROR('Data Sheet'!G64,0) -> 3902.14 | I61: =IFERROR('Data Sheet'!H64,0) -> 7720.58 | J61: =IFERROR('Data Sheet'!I64,0) -> 12320.66 | ... M61: =IFERROR('Data Sheet'!L64,0) -> 0
B62: Other Assets | C62: =IFERROR('Data Sheet'!B65-SUM('Data Sheet'!B67:B69),0) -> 276.5 | D62: =IFERROR('Data Sheet'!C65-SUM('Data Sheet'!C67:C69),0) -> 364.4 | E62: =IFERROR('Data Sheet'!D65-SUM('Data Sheet'!D67:D69),0) -> 431.85 | F62: =IFERROR('Data Sheet'!E65-SUM('Data Sheet'!E67:E69),0) -> 457.03 | G62: =IFERROR('Data Sheet'!F65-SUM('Data Sheet'!F67:F69),0) -> 401.56 | H62: =IFERROR('Data Sheet'!G65-SUM('Data Sheet'!G67:G69),0) -> 1045.76 | I62: =IFERROR('Data Sheet'!H65-SUM('Data Sheet'!H67:H69),0) -> 1333.28 | J62: =IFERROR('Data Sheet'!I65-SUM('Data Sheet'!I67:I69),0) -> 1301.98 | ... L62: =IFERROR('Data Sheet'!K65-SUM('Data Sheet'!K67:K69),0) -> 6042.17 | M62: =IFERROR('Data Sheet'!L65,0) -> 0
B63: Total Non Current Assest | C63: =IFERROR(SUM(C59:C62),0) -> 4548.81 | D63: =IFERROR(SUM(D59:D62),0) -> 6598.08 | E63: =IFERROR(SUM(E59:E62),0) -> 7847.59 | F63: =IFERROR(SUM(F59:F62),0) -> 7703.87 | G63: =IFERROR(SUM(G59:G62),0) -> 8840.02 | H63: =IFERROR(SUM(H59:H62),0) -> 7695.49 | I63: =IFERROR(SUM(I59:I62),0) -> 11982.92 | J63: =IFERROR(SUM(J59:J62),0) -> 16784.7 | ... M63: =IFERROR(SUM(M59:M62),0) -> 0
B65: Receivables | C65: =IFERROR('Data Sheet'!B67,0) -> 32.64 | D65: =IFERROR('Data Sheet'!C67,0) -> 50.04 | E65: =IFERROR('Data Sheet'!D67,0) -> 68 | F65: =IFERROR('Data Sheet'!E67,0) -> 84.29 | G65: =IFERROR('Data Sheet'!F67,0) -> 86.76 | H65: =IFERROR('Data Sheet'!G67,0) -> 158.16 | I65: =IFERROR('Data Sheet'!H67,0) -> 302.04 | J65: =IFERROR('Data Sheet'!I67,0) -> 368.92 | ... L65: =IFERROR('Data Sheet'!K67,0) -> 549.64
B66: Inventory | C66: =IFERROR('Data Sheet'!B68,0) -> 308.39 | D66: =IFERROR('Data Sheet'!C68,0) -> 335.9 | E66: =IFERROR('Data Sheet'!D68,0) -> 394.64 | F66: =IFERROR('Data Sheet'!E68,0) -> 633.38 | G66: =IFERROR('Data Sheet'!F68,0) -> 572.35 | H66: =IFERROR('Data Sheet'!G68,0) -> 874.6 | I66: =IFERROR('Data Sheet'!H68,0) -> 1132.4 | J66: =IFERROR('Data Sheet'!I68,0) -> 1278.44 | ... M66: =IFERROR('Data Sheet'!L68,0) -> 0
B67: Cash & Bank | C67: =IFERROR('Data Sheet'!B69,0) -> 49.17 | D67: =IFERROR('Data Sheet'!C69,0) -> 25.06 | E67: =IFERROR('Data Sheet'!D69,0) -> 1212 | F67: =IFERROR('Data Sheet'!E69,0) -> 2965.29 | G67: =IFERROR('Data Sheet'!F69,0) -> 2950.59 | H67: =IFERROR('Data Sheet'!G69,0) -> 5830.36 | I67: =IFERROR('Data Sheet'!H69,0) -> 2722.47 | J67: =IFERROR('Data Sheet'!I69,0) -> 765.58 | ... L67: =IFERROR('Data Sheet'!K69,0) -> 263.01
B68: Total Current Assest | C68: =IFERROR(SUM(C65:C67),0) -> 390.2 | D68: =IFERROR(SUM(D65:D67),0) -> 411 | E68: =IFERROR(SUM(E65:E67),0) -> 1674.64 | F68: =IFERROR(SUM(F65:F67),0) -> 3682.96 | G68: =IFERROR(SUM(G65:G67),0) -> 3609.7 | H68: =IFERROR(SUM(H65:H67),0) -> 6863.12 | I68: =IFERROR(SUM(I65:I67),0) -> 4156.91 | J68: =IFERROR(SUM(J65:J67),0) -> 2412.94 | ... L68: =IFERROR(SUM(L65:L67),0) -> 2376.4
B70: Total Assest | C70: =IFERROR(SUM(C63,C68),0) -> 4939.01 | D70: =IFERROR(SUM(D63,D68),0) -> 7009.08 | E70: =IFERROR(SUM(E63,E68),0) -> 9522.23 | F70: =IFERROR(SUM(F63,F68),0) -> 11386.83 | G70: =IFERROR(SUM(G63,G68),0) -> 12449.72 | H70: =IFERROR(SUM(H63,H68),0) -> 14558.61 | I70: =IFERROR(SUM(I63,I68),0) -> 16139.83 | J70: =IFERROR(SUM(J63,J68),0) -> 19197.64 | ... M70: =IFERROR(SUM(M63,M68),0) -> 0
B72: Check | C72: =C70=C57 -> TRUE | D72: =D70=D57 -> TRUE | E72: =E70=E57 -> TRUE | F72: =F70=F57 -> TRUE | G72: =G70=G57 -> TRUE | H72: =H70=H57 -> TRUE | I72: =I70=I57 -> TRUE | J72: =J70=J57 -> TRUE | ... L72: =L70=L57 -> TRUE
A74: # | B74: Cash flow Statement
B75: Operting acitivity
B76: Profit from operations | C76: =IFERROR('Forcasting data '!C14,0) -> 1719 | D76: =IFERROR('Forcasting data '!D14,0) -> 2196 | E76: =IFERROR('Forcasting data '!E14,0) -> 2851 | F76: =IFERROR('Forcasting data '!F14,0) -> 2941 | G76: =IFERROR('Forcasting data '!G14,0) -> 2236 | H76: =IFERROR('Forcasting data '!H14,0) -> 1912 | I76: =IFERROR('Forcasting data '!I14,0) -> 2172 | J76: =IFERROR('Forcasting data '!J14,0) -> 3527 | ... M76: =IFERROR('Forcasting data '!M14,0) -> 0
B77: Receivables | C77: =IFERROR('Forcasting data '!C15,0) -> -22 | D77: =IFERROR('Forcasting data '!D15,0) -> -17 | E77: =IFERROR('Forcasting data '!E15,0) -> -18 | F77: =IFERROR('Forcasting data '!F15,0) -> -18 | G77: =IFERROR('Forcasting data '!G15,0) -> 0 | H77: =IFERROR('Forcasting data '!H15,0) -> -73 | I77: =IFERROR('Forcasting data '!I15,0) -> -147 | J77: =IFERROR('Forcasting data '!J15,0) -> -59 | ... M77: =IFERROR('Forcasting data '!M15,0) -> 0
B78: Inventory | C78: =IFERROR('Forcasting data '!C16,0) -> -104 | D78: =IFERROR('Forcasting data '!D16,0) -> -28 | E78: =IFERROR('Forcasting data '!E16,0) -> -59 | F78: =IFERROR('Forcasting data '!F16,0) -> -239 | G78: =IFERROR('Forcasting data '!G16,0) -> 61 | H78: =IFERROR('Forcasting data '!H16,0) -> -302 | I78: =IFERROR('Forcasting data '!I16,0) -> -258 | J78: =IFERROR('Forcasting data '!J16,0) -> -146 | ... M78: =IFERROR('Forcasting data '!M16,0) -> 0
B79: Payables | C79: =IFERROR('Forcasting data '!C17,0) -> 241 | D79: =IFERROR('Forcasting data '!D17,0) -> 110 | E79: =IFERROR('Forcasting data '!E17,0) -> 407 | F79: =IFERROR('Forcasting data '!F17,0) -> 62 | G79: =IFERROR('Forcasting data '!G17,0) -> -235 | H79: =IFERROR('Forcasting data '!H17,0) -> 495 | I79: =IFERROR('Forcasting data '!I17,0) -> 283 | J79: =IFERROR('Forcasting data '!J17,0) -> 22 | ... M79: =IFERROR('Forcasting data '!M17,0) -> 0
B80: Loans Advances | C80: =IFERROR('Forcasting data '!C18,0) -> -12 | D80: =IFERROR('Forcasting data '!D18,0) -> 6 | E80: =IFERROR('Forcasting data '!E18,0) -> 0 | F80: =IFERROR('Forcasting data '!F18,0) -> -1 | G80: =IFERROR('Forcasting data '!G18,0) -> 1 | H80: =IFERROR('Forcasting data '!H18,0) -> 0 | I80: =IFERROR('Forcasting data '!I18,0) -> 0 | J80: =IFERROR('Forcasting data '!J18,0) -> 0 | ... M80: =IFERROR('Forcasting data '!M18,0) -> 0
B81: Other WC items | C81: =IFERROR('Forcasting data '!C19,0) -> 160 | D81: =IFERROR('Forcasting data '!D19,0) -> 92 | E81: =IFERROR('Forcasting data '!E19,0) -> 109 | F81: =IFERROR('Forcasting data '!F19,0) -> -262 | G81: =IFERROR('Forcasting data '!G19,0) -> 259 | H81: =IFERROR('Forcasting data '!H19,0) -> 115 | I81: =IFERROR('Forcasting data '!I19,0) -> -10 | J81: =IFERROR('Forcasting data '!J19,0) -> 249 | ... M81: =IFERROR('Forcasting data '!M19,0) -> 0
B82: Working capital changes | C82: =IFERROR('Forcasting data '!C20,0) -> 263 | D82: =IFERROR('Forcasting data '!D20,0) -> 163 | E82: =IFERROR('Forcasting data '!E20,0) -> 438 | F82: =IFERROR('Forcasting data '!F20,0) -> -457 | G82: =IFERROR('Forcasting data '!G20,0) -> 86 | H82: =IFERROR('Forcasting data '!H20,0) -> 235 | I82: =IFERROR('Forcasting data '!I20,0) -> -131 | J82: =IFERROR('Forcasting data '!J20,0) -> 66 | ... M82: =IFERROR('Forcasting data '!M20,0) -> 0
B83: Direct taxes | C83: =IFERROR('Forcasting data '!C21,0) -> -519 | D83: =IFERROR('Forcasting data '!D21,0) -> -652 | E83: =IFERROR('Forcasting data '!E21,0) -> -807 | F83: =IFERROR('Forcasting data '!F21,0) -> -908 | G83: =IFERROR('Forcasting data '!G21,0) -> -628 | H83: =IFERROR('Forcasting data '!H21,0) -> -457 | I83: =IFERROR('Forcasting data '!I21,0) -> -514 | J83: =IFERROR('Forcasting data '!J21,0) -> -770 | ... M83: =IFERROR('Forcasting data '!M21,0) -> 0
B84: Cash from Operting activity | C84: =IFERROR(SUM(C76:C83),0) -> 1726 | D84: =IFERROR(SUM(D76:D83),0) -> 1870 | E84: =IFERROR(SUM(E76:E83),0) -> 2921 | F84: =IFERROR(SUM(F76:F83),0) -> 1118 | G84: =IFERROR(SUM(G76:G83),0) -> 1780 | H84: =IFERROR(SUM(H76:H83),0) -> 1925 | I84: =IFERROR(SUM(I76:I83),0) -> 1395 | J84: =IFERROR(SUM(J76:J83),0) -> 2889 | ... M84: =IFERROR(SUM(M76:M83),0) -> 0
B86: Investing acitivity
B87: Fixed assets purchased | C87: =IFERROR('Forcasting data '!C23,0) -> -510 | D87: =IFERROR('Forcasting data '!D23,0) -> -548 | E87: =IFERROR('Forcasting data '!E23,0) -> -748 | F87: =IFERROR('Forcasting data '!F23,0) -> -792 | G87: =IFERROR('Forcasting data '!G23,0) -> -546 | H87: =IFERROR('Forcasting data '!H23,0) -> -532 | I87: =IFERROR('Forcasting data '!I23,0) -> -641 | J87: =IFERROR('Forcasting data '!J23,0) -> -682 | ... M87: =IFERROR('Forcasting data '!M23,0) -> 0
B88: Fixed assets sold | C88: =IFERROR('Forcasting data '!C24,0) -> 1 | D88: =IFERROR('Forcasting data '!D24,0) -> 1 | E88: =IFERROR('Forcasting data '!E24,0) -> 3 | F88: =IFERROR('Forcasting data '!F24,0) -> 2 | G88: =IFERROR('Forcasting data '!G24,0) -> 1 | H88: =IFERROR('Forcasting data '!H24,0) -> 17 | I88: =IFERROR('Forcasting data '!I24,0) -> 2 | J88: =IFERROR('Forcasting data '!J24,0) -> 9 | ... M88: =IFERROR('Forcasting data '!M24,0) -> 0
B89: Investments purchased | C89: =IFERROR('Forcasting data '!C25,0) -> -662 | D89: =IFERROR('Forcasting data '!D25,0) -> -4247 | E89: =IFERROR('Forcasting data '!E25,0) -> -6464 | F89: =IFERROR('Forcasting data '!F25,0) -> -7929 | G89: =IFERROR('Forcasting data '!G25,0) -> -8746 | H89: =IFERROR('Forcasting data '!H25,0) -> -3983 | I89: =IFERROR('Forcasting data '!I25,0) -> -7134 | J89: =IFERROR('Forcasting data '!J25,0) -> -9103 | ... M89: =IFERROR('Forcasting data '!M25,0) -> 0
B90: Investments sold | C90: =IFERROR('Forcasting data '!C26,0) -> 158 | D90: =IFERROR('Forcasting data '!D26,0) -> 3051 | E90: =IFERROR('Forcasting data '!E26,0) -> 6124 | F90: =IFERROR('Forcasting data '!F26,0) -> 9051 | G90: =IFERROR('Forcasting data '!G26,0) -> 8176 | H90: =IFERROR('Forcasting data '!H26,0) -> 5971 | I90: =IFERROR('Forcasting data '!I26,0) -> 3500 | J90: =IFERROR('Forcasting data '!J26,0) -> 5080 | ... M90: =IFERROR('Forcasting data '!M26,0) -> 0
B91: Interest received | C91: =IFERROR('Forcasting data '!C27,0) -> 4 | D91: =IFERROR('Forcasting data '!D27,0) -> 3 | E91: =IFERROR('Forcasting data '!E27,0) -> 12 | F91: =IFERROR('Forcasting data '!F27,0) -> 90 | G91: =IFERROR('Forcasting data '!G27,0) -> 204 | H91: =IFERROR('Forcasting data '!H27,0) -> 192 | I91: =IFERROR('Forcasting data '!I27,0) -> 398 | J91: =IFERROR('Forcasting data '!J27,0) -> 204 | ... M91: =IFERROR('Forcasting data '!M27,0) -> 0
B92: Dividends received | C92: =IFERROR('Forcasting data '!C28,0) -> 107 | D92: =IFERROR('Forcasting data '!D28,0) -> 0 | E92: =IFERROR('Forcasting data '!E28,0) -> 52 | F92: =IFERROR('Forcasting data '!F28,0) -> 65 | G92: =IFERROR('Forcasting data '!G28,0) -> 68 | H92: =IFERROR('Forcasting data '!H28,0) -> 0 | I92: =IFERROR('Forcasting data '!I28,0) -> 27 | J92: =IFERROR('Forcasting data '!J28,0) -> 41 | ... M92: =IFERROR('Forcasting data '!M28,0) -> 0
B93: Investment in group cos | C93: =IFERROR('Forcasting data '!C29,0) -> -109 | D93: =IFERROR('Forcasting data '!D29,0) -> -39 | E93: =IFERROR('Forcasting data '!E29,0) -> -16 | F93: =IFERROR('Forcasting data '!F29,0) -> -30 | G93: =IFERROR('Forcasting data '!G29,0) -> -1 | H93: =IFERROR('Forcasting data '!H29,0) -> 0 | I93: =IFERROR('Forcasting data '!I29,0) -> 0 | J93: =IFERROR('Forcasting data '!J29,0) -> 0 | ... M93: =IFERROR('Forcasting data '!M29,0) -> 0
B94: Other investing items | C94: =IFERROR('Forcasting data '!C30,0) -> 9 | D94: =IFERROR('Forcasting data '!D30,0) -> 36 | E94: =IFERROR('Forcasting data '!E30,0) -> -1106 | F94: =IFERROR('Forcasting data '!F30,0) -> -1117 | G94: =IFERROR('Forcasting data '!G30,0) -> -665 | H94: =IFERROR('Forcasting data '!H30,0) -> -3290 | I94: =IFERROR('Forcasting data '!I30,0) -> 2864 | J94: =IFERROR('Forcasting data '!J30,0) -> 2055 | ... M94: =IFERROR('Forcasting data '!M30,0) -> 0
B95: Cash from Investing acitivity | C95: =IFERROR(SUM(C87:C94),0) -> -1002 | D95: =IFERROR(SUM(D87:D94),0) -> -1743 | E95: =IFERROR(SUM(E87:E94),0) -> -2143 | F95: =IFERROR(SUM(F87:F94),0) -> -660 | G95: =IFERROR(SUM(G87:G94),0) -> -1509 | H95: =IFERROR(SUM(H87:H94),0) -> -1625 | I95: =IFERROR(SUM(I87:I94),0) -> -984 | J95: =IFERROR(SUM(J87:J94),0) -> -2396 | ... M95: =IFERROR(SUM(M87:M94),0) -> 0
B97: Financing activity
B98: Proceeds from shares | C98: =IFERROR('Forcasting data '!C32,0) -> 5 | D98: =IFERROR('Forcasting data '!D32,0) -> 6 | E98: =IFERROR('Forcasting data '!E32,0) -> 19 | F98: =IFERROR('Forcasting data '!F32,0) -> 36 | G98: =IFERROR('Forcasting data '!G32,0) -> 29 | H98: =IFERROR('Forcasting data '!H32,0) -> 38 | I98: =IFERROR('Forcasting data '!I32,0) -> 6 | J98: =IFERROR('Forcasting data '!J32,0) -> 11 | ... M98: =IFERROR('Forcasting data '!M32,0) -> 0
B99: Proceeds from borrowings | C99: =IFERROR('Forcasting data '!C33,0) -> 0 | D99: =IFERROR('Forcasting data '!D33,0) -> 389 | E99: =IFERROR('Forcasting data '!E33,0) -> 495 | F99: =IFERROR('Forcasting data '!F33,0) -> 369 | G99: =IFERROR('Forcasting data '!G33,0) -> 267 | H99: =IFERROR('Forcasting data '!H33,0) -> 40 | I99: =IFERROR('Forcasting data '!I33,0) -> 32 | J99: =IFERROR('Forcasting data '!J33,0) -> 202 | ... M99: =IFERROR('Forcasting data '!M33,0) -> 0
B100: Repayment of borrowings | C100: =IFERROR('Forcasting data '!C34,0) -> 0 | D100: =IFERROR('Forcasting data '!D34,0) -> -345 | E100: =IFERROR('Forcasting data '!E34,0) -> -456 | F100: =IFERROR('Forcasting data '!F34,0) -> -344 | G100: =IFERROR('Forcasting data '!G34,0) -> -298 | H100: =IFERROR('Forcasting data '!H34,0) -> -27 | I100: =IFERROR('Forcasting data '!I34,0) -> -137 | J100: =IFERROR('Forcasting data '!J34,0) -> -20 | ... M100: =IFERROR('Forcasting data '!M34,0) -> 0
B101: Interest paid fin | C101: =IFERROR('Forcasting data '!C35,0) -> -2 | D101: =IFERROR('Forcasting data '!D35,0) -> -2 | E101: =IFERROR('Forcasting data '!E35,0) -> -3 | F101: =IFERROR('Forcasting data '!F35,0) -> -5 | G101: =IFERROR('Forcasting data '!G35,0) -> -8 | H101: =IFERROR('Forcasting data '!H35,0) -> -16 | I101: =IFERROR('Forcasting data '!I35,0) -> -19 | J101: =IFERROR('Forcasting data '!J35,0) -> -18 | ... M101: =IFERROR('Forcasting data '!M35,0) -> 0
B102: Dividends paid | C102: =IFERROR('Forcasting data '!C36,0) -> -407 | D102: =IFERROR('Forcasting data '!D36,0) -> 0 | E102: =IFERROR('Forcasting data '!E36,0) -> -272 | F102: =IFERROR('Forcasting data '!F36,0) -> -300 | G102: =IFERROR('Forcasting data '!G36,0) -> -682 | H102: =IFERROR('Forcasting data '!H36,0) -> 0 | I102: =IFERROR('Forcasting data '!I36,0) -> -465 | J102: =IFERROR('Forcasting data '!J36,0) -> -574 | ... M102: =IFERROR('Forcasting data '!M36,0) -> 0
B103: Financial liabilities | C103: =IFERROR('Forcasting data '!C37,0) -> 0 | D103: =IFERROR('Forcasting data '!D37,0) -> 0 | E103: =IFERROR('Forcasting data '!E37,0) -> 0 | F103: =IFERROR('Forcasting data '!F37,0) -> 0 | G103: =IFERROR('Forcasting data '!G37,0) -> -40 | H103: =IFERROR('Forcasting data '!H37,0) -> -39 | I103: =IFERROR('Forcasting data '!I37,0) -> -17 | J103: =IFERROR('Forcasting data '!J37,0) -> -19 | ... M103: =IFERROR('Forcasting data '!M37,0) -> 0
B104: Other financing items | C104: =IFERROR('Forcasting data '!C38,0) -> -61 | D104: =IFERROR('Forcasting data '!D38,0) -> -23 | E104: =IFERROR('Forcasting data '!E38,0) -> -45 | F104: =IFERROR('Forcasting data '!F38,0) -> -48 | G104: =IFERROR('Forcasting data '!G38,0) -> -126 | H104: =IFERROR('Forcasting data '!H38,0) -> -11 | I104: =IFERROR('Forcasting data '!I38,0) -> 5 | J104: =IFERROR('Forcasting data '!J38,0) -> 0 | ... M104: =IFERROR('Forcasting data '!M38,0) -> 0
B105: Cash from Financing activity | C105: =IFERROR(SUM(C98:C104),0) -> -465 | D105: =IFERROR(SUM(D98:D104),0) -> 25 | E105: =IFERROR(SUM(E98:E104),0) -> -262 | F105: =IFERROR(SUM(F98:F104),0) -> -292 | G105: =IFERROR(SUM(G98:G104),0) -> -858 | H105: =IFERROR(SUM(H98:H104),0) -> -15 | I105: =IFERROR(SUM(I98:I104),0) -> -595 | J105: =IFERROR(SUM(J98:J104),0) -> -418 | ... M105: =IFERROR(SUM(M98:M104),0) -> 0
B107: Net Cash Flow | C107: =C105+C95+C84 -> 259 | D107: =D105+D95+D84 -> 152 | E107: =E105+E95+E84 -> 516 | F107: =F105+F95+F84 -> 166 | G107: =G105+G95+G84 -> -587 | H107: =H105+H95+H84 -> 285 | I107: =I105+I95+I84 -> -184 | J107: =J105+J95+J84 -> 75 | ... M107: =M105+M95+M84 -> 0

Sheet Ratio Annalysis
D2: =data!C23 -> Eicher Motors Limited is an Indian multinational automotive company that manufactures motorcycles and commercial vehicles, headquartered in New Delhi. Eicher is the parent company of Royal Enfield, a manufacturer of middleweight motorcycles. It also manufactures Eicher branded trucks and buses, under a joint venture with Volvo Group.
B9: ="Ratio Annalysis - " & 'Data Sheet'!B1 -> Ratio Annalysis - EICHER MOTORS LTD
B10: ='Historical IFS'!B10 -> Years | D10: ='Historical IFS'!D10 -> 42825 | E10: ='Historical IFS'!E10 -> 43190 | F10: ='Historical IFS'!F10 -> 43555 | G10: ='Historical IFS'!G10 -> 43921 | H10: ='Historical IFS'!H10 -> 44286 | I10: ='Historical IFS'!I10 -> 44651 | J10: ='Historical IFS'!J10 -> 45016 | K10: ='Historical IFS'!K10 -> 45382 | L10: ='Historical IFS'!L10 -> 45747 | N10: Mean | O10: Median
B12: Sales Growth | D12: =IFERROR('Historical IFS'!D13,0) -> 0.1392898 | E12: =IFERROR('Historical IFS'!E13,0) -> 0.27463403 | F12: =IFERROR('Historical IFS'!F13,0) -> 0.092816923 | G12: =IFERROR('Historical IFS'!G13,0) -> -0.065680929 | H12: =IFERROR('Historical IFS'!H13,0) -> -0.047329023 | I12: =IFERROR('Historical IFS'!I13,0) -> 0.18089641 | J12: =IFERROR('Historical IFS'!J13,0) -> 0.40244887 | K12: =IFERROR('Historical IFS'!K13,0) -> 0.14496426 | L12: =IFERROR('Historical IFS'!L13,0) -> 0.14118294 | N12: =IFERROR(AVERAGE(D12:L12),0) -> 0.14035814 | O12: =IFERROR(MEDIAN(D12:L12),0) -> 0.14118294
B13: EBIDTA Growth | D13: =IFERROR('Historical IFS'!D24/'Historical IFS'!C24-1,0) -> 0.323786 | E13: =IFERROR('Historical IFS'!E24/'Historical IFS'!D24-1,0) -> 0.28777092 | F13: =IFERROR('Historical IFS'!F24/'Historical IFS'!E24-1,0) -> -0.029076389 | G13: =IFERROR('Historical IFS'!G24/'Historical IFS'!F24-1,0) -> -0.15853278 | H13: =IFERROR('Historical IFS'!H24/'Historical IFS'!G24-1,0) -> -0.3042153 | I13: =IFERROR('Historical IFS'!I24/'Historical IFS'!H24-1,0) -> 0.28633831 | J13: =IFERROR('Historical IFS'!J24/'Historical IFS'!I24-1,0) -> 0.66707902 | K13: =IFERROR('Historical IFS'!K24/'Historical IFS'!J24-1,0) -> 0.22169302 | L13: =IFERROR('Historical IFS'!L24/'Historical IFS'!K24-1,0) -> 0.10326353 | N13: =IFERROR(AVERAGE(D13:L13),0) -> 0.15534515 | O13: =IFERROR(MEDIAN(D13:L13),0) -> 0.22169302
B14: EBIT Growth | D14: =IFERROR('Historical IFS'!D33/'Historical IFS'!C33-1,0) -> 0.34143145 | E14: =IFERROR('Historical IFS'!E33/'Historical IFS'!D33-1,0) -> 0.27476332 | F14: =IFERROR('Historical IFS'!F33/'Historical IFS'!E33-1,0) -> -0.062706194 | G14: =IFERROR('Historical IFS'!G33/'Historical IFS'!F33-1,0) -> -0.21786538 | H14: =IFERROR('Historical IFS'!H33/'Historical IFS'!G33-1,0) -> -0.40525756 | I14: =IFERROR('Historical IFS'!I33/'Historical IFS'!H33-1,0) -> 0.40368373 | J14: =IFERROR('Historical IFS'!J33/'Historical IFS'!I33-1,0) -> 0.81501575 | K14: =IFERROR('Historical IFS'!K33/'Historical IFS'!J33-1,0) -> 0.23181486 | L14: =IFERROR('Historical IFS'!L33/'Historical IFS'!K33-1,0) -> 0.083680449 | N14: =IFERROR(AVERAGE(D14:L14),0) -> 0.16272893 | O14: =IFERROR(MEDIAN(D14:L14),0) -> 0.23181486
B15: Net Profit Growth | D15: =IFERROR('Historical IFS'!D39/'Historical IFS'!C39-1,0) -> 0.34413716 | E15: =IFERROR('Historical IFS'!E39/'Historical IFS'!D39-1,0) -> 0.26088871 | F15: =IFERROR('Historical IFS'!F39/'Historical IFS'!E39-1,0) -> -0.18679203 | G15: =IFERROR('Historical IFS'!G39/'Historical IFS'!F39-1,0) -> 0.022657465 | H15: =IFERROR('Historical IFS'!H39/'Historical IFS'!G39-1,0) -> -0.50816741 | I15: =IFERROR('Historical IFS'!I39/'Historical IFS'!H39-1,0) -> 0.56744593 | J15: =IFERROR('Historical IFS'!J39/'Historical IFS'!I39-1,0) -> 0.88170564 | K15: =IFERROR('Historical IFS'!K39/'Historical IFS'!J39-1,0) -> 0.17518513 | L15: =IFERROR('Historical IFS'!L39/'Historical IFS'!K39-1,0) -> 0.12874816 | N15: =IFERROR(AVERAGE(D15:L15),0) -> 0.18731208 | O15: =IFERROR(MEDIAN(D15:L15),0) -> 0.17518513
B16: Divide Growth | D16: =IFERROR('Historical IFS'!D47/'Historical IFS'!C47-1,0) -> 0 | E16: =IFERROR('Historical IFS'!E47/'Historical IFS'!D47-1,0) -> 0.1 | F16: =IFERROR('Historical IFS'!F47/'Historical IFS'!E47-1,0) -> 0.13636364 | G16: =IFERROR('Historical IFS'!G47/'Historical IFS'!F47-1,0) -> -0.00036616624 | H16: =IFERROR('Historical IFS'!H47/'Historical IFS'!G47-1,0) -> 0.36049817 | I16: =IFERROR('Historical IFS'!I47/'Historical IFS'!H47-1,0) -> 0.23529412 | J16: =IFERROR('Historical IFS'!J47/'Historical IFS'!I47-1,0) -> 0.76190476 | K16: =IFERROR('Historical IFS'!K47/'Historical IFS'!J47-1,0) -> 0.37837838 | L16: =IFERROR('Historical IFS'!L47/'Historical IFS'!K47-1,0) -> 0.37254902 | N16: =IFERROR(AVERAGE(D16:L16),0) -> 0.26051355 | O16: =IFERROR(MEDIAN(D16:L16),0) -> 0.23529412
B18: Gross Margin | D18: =IFERROR('Historical IFS'!C19,0) -> 0.34106968 | E18: =IFERROR('Historical IFS'!D19,0) -> 0.37851752 | F18: =IFERROR('Historical IFS'!E19,0) -> 0.38472453 | G18: =IFERROR('Historical IFS'!F19,0) -> 0.3566917 | H18: =IFERROR('Historical IFS'!G19,0) -> 0.3412632 | I18: =IFERROR('Historical IFS'!H19,0) -> 0.25841165 | J18: =IFERROR('Historical IFS'!I19,0) -> 0.28951148 | K18: =IFERROR('Historical IFS'!J19,0) -> 0.32467605 | L18: =IFERROR('Historical IFS'!K19,0) -> 0.3409437 | N18: =IFERROR(AVERAGE(D18:L18),0) -> 0.33508994 | O18: =IFERROR(MEDIAN(D18:L18),0) -> 0.34106968
B19: EBIDTA Margin | D19: =IFERROR('Historical IFS'!D25,0) -> 0.30635429 | E19: =IFERROR('Historical IFS'!E25,0) -> 0.3095117 | F19: =IFERROR('Historical IFS'!F25,0) -> 0.27498862 | G19: =IFERROR('Historical IFS'!G25,0) -> 0.24766048 | H19: =IFERROR('Historical IFS'!H25,0) -> 0.18087921 | I19: =IFERROR('Historical IFS'!I25,0) -> 0.19702986 | J19: =IFERROR('Historical IFS'!J25,0) -> 0.23420772 | K19: =IFERROR('Historical IFS'!K25,0) -> 0.24990294 | L19: =IFERROR('Historical IFS'!L25,0) -> 0.24159912 | N19: =IFERROR(AVERAGE(D19:L19),0) -> 0.24912599 | O19: =IFERROR(MEDIAN(D19:L19),0) -> 0.24766048
B20: EBIT Margin | D20: =IFERROR(('Historical IFS'!D24-'Historical IFS'!D30)/'Historical IFS'!D12,0) -> 0.28448565 | E20: =IFERROR(('Historical IFS'!E24-'Historical IFS'!E30)/'Historical IFS'!E12,0) -> 0.28460361 | F20: =IFERROR(('Historical IFS'!F24-'Historical IFS'!F30)/'Historical IFS'!F12,0) -> 0.24433861 | G20: =IFERROR(('Historical IFS'!G24-'Historical IFS'!G30)/'Historical IFS'!G12,0) -> 0.20597843 | H20: =IFERROR(('Historical IFS'!H24-'Historical IFS'!H30)/'Historical IFS'!H12,0) -> 0.12919206 | I20: =IFERROR(('Historical IFS'!I24-'Historical IFS'!I30)/'Historical IFS'!I12,0) -> 0.15314391 | J20: =IFERROR(('Historical IFS'!J24-'Historical IFS'!J30)/'Historical IFS'!J12,0) -> 0.19777208 | K20: =IFERROR(('Historical IFS'!K24-'Historical IFS'!K30)/'Historical IFS'!K12,0) -> 0.21376312 | L20: =IFERROR(('Historical IFS'!L24-'Historical IFS'!L30)/'Historical IFS'!L12,0) -> 0.2029496 | N20: =IFERROR(AVERAGE(D20:L20),0) -> 0.21291412 | O20: =IFERROR(MEDIAN(D20:L20),0) -> 0.20597843
B21: EBT Margin | D21: =IFERROR('Historical IFS'!D34,0) -> 0.28397631 | E21: =IFERROR('Historical IFS'!E34,0) -> 0.28400512 | F21: =IFERROR('Historical IFS'!F34,0) -> 0.24358722 | G21: =IFERROR('Historical IFS'!G34,0) -> 0.20391107 | H21: =IFERROR('Historical IFS'!H34,0) -> 0.12729953 | I21: =IFERROR('Historical IFS'!I34,0) -> 0.15131579 | J21: =IFERROR('Historical IFS'!J34,0) -> 0.19582927 | K21: =IFERROR('Historical IFS'!K34,0) -> 0.21068379 | L21: =IFERROR('Historical IFS'!L34,0) -> 0.20006775 | N21: =IFERROR(AVERAGE(D21:L21),0) -> 0.2111862 | O21: =IFERROR(MEDIAN(D21:L21),0) -> 0.20391107
B22: Net Profit Margin | D22: =IFERROR('Historical IFS'!D40,0) -> 0.18156438 | E22: =IFERROR('Historical IFS'!E40,0) -> 0.17960643 | F22: =IFERROR('Historical IFS'!F40,0) -> 0.1336522 | G22: =IFERROR('Historical IFS'!G40,0) -> 0.1462888 | H22: =IFERROR('Historical IFS'!H40,0) -> 0.075524082 | I22: =IFERROR('Historical IFS'!I40,0) -> 0.10024581 | J22: =IFERROR('Historical IFS'!J40,0) -> 0.13450266 | K22: =IFERROR('Historical IFS'!K40,0) -> 0.1380528 | L22: =IFERROR('Historical IFS'!L40,0) -> 0.13654853 | N22: =IFERROR(AVERAGE(D22:L22),0) -> 0.13622063 | O22: =IFERROR(MEDIAN(D22:L22),0) -> 0.13654853
B24: Sales Expnens % Sales | D24: =IFERROR('Historical IFS'!D22,0) -> 0.072163234 | E24: =IFERROR('Historical IFS'!E22,0) -> 0.075212829 | F24: =IFERROR('Historical IFS'!F22,0) -> 0.081703082 | G24: =IFERROR('Historical IFS'!G22,0) -> 0.093602722 | H24: =IFERROR('Historical IFS'!H22,0) -> 0.077532438 | I24: =IFERROR('Historical IFS'!I22,0) -> 0.09248162 | J24: =IFERROR('Historical IFS'!J22,0) -> 0.090468336 | K24: =IFERROR('Historical IFS'!K22,0) -> 0.091040761 | L24: =IFERROR('Historical IFS'!L22,0) -> 0.10104052 | N24: =IFERROR(AVERAGE(D24:L24),0) -> 0.086138394 | O24: =IFERROR(MEDIAN(D24:L24),0) -> 0.090468336
B25: Depn % sales | D25: =IFERROR('Historical IFS'!D31,0) -> 0.021868637 | E25: =IFERROR('Historical IFS'!E31,0) -> 0.024908087 | F25: =IFERROR('Historical IFS'!F31,0) -> 0.030650011 | G25: =IFERROR('Historical IFS'!G31,0) -> 0.041682052 | H25: =IFERROR('Historical IFS'!H31,0) -> 0.051687146 | I25: =IFERROR('Historical IFS'!I31,0) -> 0.043885945 | J25: =IFERROR('Historical IFS'!J31,0) -> 0.036435635 | K25: =IFERROR('Historical IFS'!K31,0) -> 0.036139813 | L25: =IFERROR('Historical IFS'!L31,0) -> 0.038649522 | N25: =IFERROR(AVERAGE(D25:L25),0) -> 0.036211872 | O25: =IFERROR(MEDIAN(D25:L25),0) -> 0.036435635
B26: Operting Income % Sales | D26: =D20 -> 0.28448565 | E26: =E20 -> 0.28460361 | F26: =F20 -> 0.24433861 | G26: =G20 -> 0.20597843 | H26: =H20 -> 0.12919206 | I26: =I20 -> 0.15314391 | J26: =J20 -> 0.19777208 | K26: =K20 -> 0.21376312 | L26: =L20 -> 0.2029496 | N26: =IFERROR(AVERAGE(D26:L26),0) -> 0.21291412 | O26: =IFERROR(MEDIAN(D26:L26),0) -> 0.20597843
N27: =IFERROR(AVERAGE(D27:L27),0) -> 0 | O27: =IFERROR(MEDIAN(D27:L27),0) -> 0
B28: Retrun on Capital Employed | D28: =IFERROR(('Historical IFS'!D24-'Historical IFS'!D30)/SUM('Historical IFS'!D53:D54),0) -> 0.37434309 | E28: =IFERROR(('Historical IFS'!E24-'Historical IFS'!E30)/SUM('Historical IFS'!E53:E54),0) -> 0.36293522 | F28: =IFERROR(('Historical IFS'!F24-'Historical IFS'!F30)/SUM('Historical IFS'!F53:F54),0) -> 0.26840174 | G28: =IFERROR(('Historical IFS'!G24-'Historical IFS'!G30)/SUM('Historical IFS'!G53:G54),0) -> 0.18890424 | H28: =IFERROR(('Historical IFS'!H24-'Historical IFS'!H30)/SUM('Historical IFS'!H53:H54),0) -> 0.098495552 | I28: =IFERROR(('Historical IFS'!I24-'Historical IFS'!I30)/SUM('Historical IFS'!I53:I54),0) -> 0.12508328 | J28: =IFERROR(('Historical IFS'!J24-'Historical IFS'!J30)/SUM('Historical IFS'!J53:J54),0) -> 0.1905408 | K28: =IFERROR(('Historical IFS'!K24-'Historical IFS'!K30)/SUM('Historical IFS'!K53:K54),0) -> 0.19587898 | L28: =IFERROR(('Historical IFS'!L24-'Historical IFS'!L30)/SUM('Historical IFS'!L53:L54),0) -> 0.17982916 | N28: =IFERROR(AVERAGE(D28:L28),0) -> 0.22049023 | O28: =IFERROR(MEDIAN(D28:L28),0) -> 0.1905408
B29: Retained Earnigns% | D29: =IFERROR('Historical IFS'!D50,0) -> 0.78692375 | E29: =IFERROR('Historical IFS'!E50,0) -> 0.81377058 | F29: =IFERROR('Historical IFS'!F50,0) -> 0.7395751 | G29: =IFERROR('Historical IFS'!G50,0) -> 0.74515824 | H29: =IFERROR('Historical IFS'!H50,0) -> 0.29454522 | I29: =IFERROR('Historical IFS'!I50,0) -> 0.44383217 | J29: =IFERROR('Historical IFS'!J50,0) -> 0.47905074 | K29: =IFERROR('Historical IFS'!K50,0) -> 0.38830673 | L29: =IFERROR('Historical IFS'!L50,0) -> 0.25509906 | N29: =IFERROR(AVERAGE(D29:L29),0) -> 0.54958462 | O29: =IFERROR(MEDIAN(D29:L29),0) -> 0.47905074
B30: Retrun on Equity% | D30: =IFERROR('Historical IFS'!D39/SUM('Historical IFS'!D53:D54),0) -> 0.23891317 | E30: =IFERROR('Historical IFS'!E39/SUM('Historical IFS'!E53:E54),0) -> 0.22903961 | F30: =IFERROR('Historical IFS'!F39/SUM('Historical IFS'!F53:F54),0) -> 0.14681463 | G30: =IFERROR('Historical IFS'!G39/SUM('Historical IFS'!G53:G54),0) -> 0.13416247 | H30: =IFERROR('Historical IFS'!H39/SUM('Historical IFS'!H53:H54),0) -> 0.057579281 | I30: =IFERROR('Historical IFS'!I39/SUM('Historical IFS'!I53:I54),0) -> 0.08187772 | J30: =IFERROR('Historical IFS'!J39/SUM('Historical IFS'!J53:J54),0) -> 0.12958475 | K30: =IFERROR('Historical IFS'!K39/SUM('Historical IFS'!K53:K54),0) -> 0.12650284 | L30: =IFERROR('Historical IFS'!L39/SUM('Historical IFS'!L53:L54),0) -> 0.12099264 | N30: =IFERROR(AVERAGE(D30:L30),0) -> 0.14060746 | O30: =IFERROR(MEDIAN(D30:L30),0) -> 0.12958475
B31: Self Sustained Growth Rate | D31: =IFERROR(D29*D30,0) -> 0.18800645 | E31: =IFERROR(E29*E30,0) -> 0.1863857 | F31: =IFERROR(F29*F30,0) -> 0.10858045 | G31: =IFERROR(G29*G30,0) -> 0.099972273 | H31: =IFERROR(H29*H30,0) -> 0.016959702 | I31: =IFERROR(I29*I30,0) -> 0.036339966 | J31: =IFERROR(J29*J30,0) -> 0.062077668 | K31: =IFERROR(K29*K30,0) -> 0.049121903 | L31: =IFERROR(L29*L30,0) -> 0.030865108 | N31: =IFERROR(AVERAGE(D31:L31),0) -> 0.086478801 | O31: =IFERROR(MEDIAN(D31:L31),0) -> 0.062077668
B32: Interest Coverage Ratio | D32: =IFERROR(('Historical IFS'!D24-'Historical IFS'!D30)/'Historical IFS'!D27,0) -> 562.04775 | E32: =IFERROR(('Historical IFS'!E24-'Historical IFS'!E30)/'Historical IFS'!E27,0) -> 477.8015 | F32: =IFERROR(('Historical IFS'!F24-'Historical IFS'!F30)/'Historical IFS'!F27,0) -> 326.57572 | G32: =IFERROR(('Historical IFS'!G24-'Historical IFS'!G30)/'Historical IFS'!G27,0) -> 99.864407 | H32: =IFERROR(('Historical IFS'!H24-'Historical IFS'!H30)/'Historical IFS'!H27,0) -> 68.486322 | I32: =IFERROR(('Historical IFS'!I24-'Historical IFS'!I30)/'Historical IFS'!I27,0) -> 83.974973 | J32: =IFERROR(('Historical IFS'!J24-'Historical IFS'!J30)/'Historical IFS'!J27,0) -> 101.93647 | K32: =IFERROR(('Historical IFS'!K24-'Historical IFS'!K30)/'Historical IFS'!K27,0) -> 69.472091 | L32: =IFERROR(('Historical IFS'!L24-'Historical IFS'!L30)/'Historical IFS'!L27,0) -> 70.477181 | N32: =IFERROR(AVERAGE(D32:L32),0) -> 206.73738 | O32: =IFERROR(MEDIAN(D32:L32),0) -> 99.864407
B34: Debtor Turnover Ratio | D34: =IFERROR('Historical IFS'!D12/'Historical IFS'!D77,0) -> -413.72706 | E34: =IFERROR('Historical IFS'!E12/'Historical IFS'!E77,0) -> -498.05333 | F34: =IFERROR('Historical IFS'!F12/'Historical IFS'!F77,0) -> -544.28111 | G34: =IFERROR('Historical IFS'!G12/'Historical IFS'!G77,0) -> 0 | H34: =IFERROR('Historical IFS'!H12/'Historical IFS'!H77,0) -> -119.45685 | I34: =IFERROR('Historical IFS'!I12/'Historical IFS'!I77,0) -> -70.053265 | J34: =IFERROR('Historical IFS'!J12/'Historical IFS'!J77,0) -> -244.78271 | K34: =IFERROR('Historical IFS'!K12/'Historical IFS'!K77,0) -> -3307.156 | L34: =IFERROR('Historical IFS'!L12/'Historical IFS'!L77,0) -> -107.2179 | N34: =IFERROR(AVERAGE(D34:L34),0) -> -589.41425 | O34: =IFERROR(MEDIAN(D34:L34),0) -> -244.78271
B35: Creditor Turnover Ratio | D35: ='Historical IFS'!D12/'Historical IFS'!D56 -> 4.531337 | E35: ='Historical IFS'!E12/'Historical IFS'!E56 -> 3.8290195 | F35: ='Historical IFS'!F12/'Historical IFS'!F56 -> 4.2944134 | G35: ='Historical IFS'!G12/'Historical IFS'!G56 -> 4.1236243 | H35: ='Historical IFS'!H12/'Historical IFS'!H56 -> 3.0056906 | I35: ='Historical IFS'!I12/'Historical IFS'!I56 -> 3.0074384 | J35: ='Historical IFS'!J12/'Historical IFS'!J56 -> 3.6852167 | K35: ='Historical IFS'!K12/'Historical IFS'!K56 -> 3.5559594 | L35: ='Historical IFS'!L12/'Historical IFS'!L56 -> 3.4817493 | N35: =IFERROR(AVERAGE(D35:L35),0) -> 3.7238276 | O35: =IFERROR(MEDIAN(D35:L35),0) -> 3.6852167
B36: Invenotry Turn over Ratio | D36: ='Historical IFS'!D12/'Historical IFS'!D66 -> 20.938851 | E36: ='Historical IFS'!E12/'Historical IFS'!E66 -> 22.716805 | F36: ='Historical IFS'!F12/'Historical IFS'!F66 -> 15.467902 | G36: ='Historical IFS'!G12/'Historical IFS'!G66 -> 15.992976 | H36: ='Historical IFS'!H12/'Historical IFS'!H66 -> 9.9706723 | I36: ='Historical IFS'!I12/'Historical IFS'!I66 -> 9.0938096 | J36: ='Historical IFS'!J12/'Historical IFS'!J66 -> 11.296721 | K36: ='Historical IFS'!K12/'Historical IFS'!K66 -> 11.730499 | L36: ='Historical IFS'!L12/'Historical IFS'!L66 -> 12.06737 | N36: =IFERROR(AVERAGE(D36:L36),0) -> 14.363956 | O36: =IFERROR(MEDIAN(D36:L36),0) -> 12.06737
B37: Fixed Assest Turnover Ratio | D37: ='Historical IFS'!D12/'Historical IFS'!D59 -> 8.0585715 | E37: ='Historical IFS'!E12/'Historical IFS'!E59 -> 5.9699139 | F37: ='Historical IFS'!F12/'Historical IFS'!F59 -> 5.2262694 | G37: ='Historical IFS'!G12/'Historical IFS'!G59 -> 3.8500538 | H37: ='Historical IFS'!H12/'Historical IFS'!H59 -> 3.5837546 | I37: ='Historical IFS'!I12/'Historical IFS'!I59 -> 4.247789 | J37: ='Historical IFS'!J12/'Historical IFS'!J59 -> 5.3688601 | K37: ='Historical IFS'!K12/'Historical IFS'!K59 -> 5.6738586 | L37: ='Historical IFS'!L12/'Historical IFS'!L59 -> 5.4327085 | N37: =IFERROR(AVERAGE(D37:L37),0) -> 5.2679755 | O37: =IFERROR(MEDIAN(D37:L37),0) -> 5.3688601
B38: Capitla turn over ratio | D38: =IFERROR('Historical IFS'!D12/SUM('Historical IFS'!D53:D54),0) -> 1.3158593 | E38: =IFERROR('Historical IFS'!E12/SUM('Historical IFS'!E53:E54),0) -> 1.2752305 | F38: =IFERROR('Historical IFS'!F12/SUM('Historical IFS'!F53:F54),0) -> 1.0984827 | G38: =IFERROR('Historical IFS'!G12/SUM('Historical IFS'!G53:G54),0) -> 0.91710692 | H38: =IFERROR('Historical IFS'!H12/SUM('Historical IFS'!H53:H54),0) -> 0.76239631 | I38: =IFERROR('Historical IFS'!I12/SUM('Historical IFS'!I53:I54),0) -> 0.81676951 | J38: =IFERROR('Historical IFS'!J12/SUM('Historical IFS'!J53:J54),0) -> 0.96343631 | K38: =IFERROR('Historical IFS'!K12/SUM('Historical IFS'!K53:K54),0) -> 0.91633662 | L38: =IFERROR('Historical IFS'!L12/SUM('Historical IFS'!L53:L54),0) -> 0.88607794 | N38: =IFERROR(AVERAGE(D38:L38),0) -> 0.99463291 | O38: =IFERROR(MEDIAN(D38:L38),0) -> 0.91710692
B41: (In days)
B42: debtor days | D42: =IFERROR(365/D34,0) -> -0.88222414 | E42: =IFERROR(365/E34,0) -> -0.73285324 | F42: =IFERROR(365/F34,0) -> -0.67060935 | G42: =IFERROR(365/G34,0) -> 0 | H42: =IFERROR(365/H34,0) -> -3.0554966 | I42: =IFERROR(365/I34,0) -> -5.210321 | J42: =IFERROR(365/J34,0) -> -1.4911184 | K42: =IFERROR(365/K34,0) -> -0.11036673 | L42: =IFERROR(365/L34,0) -> -3.4042824 | N42: =IFERROR(AVERAGE(D42:L42),0) -> -1.7285858 | O42: =IFERROR(MEDIAN(D42:L42),0) -> -0.88222414
B43: paybales day | D43: =IFERROR(365/D35,0) -> 80.550178 | E43: =IFERROR(365/E35,0) -> 95.324664 | F43: =IFERROR(365/F35,0) -> 84.994146 | G43: =IFERROR(365/G35,0) -> 88.514368 | H43: =IFERROR(365/H35,0) -> 121.43632 | I43: =IFERROR(365/I35,0) -> 121.36574 | J43: =IFERROR(365/J35,0) -> 99.044379 | K43: =IFERROR(365/K35,0) -> 102.64459 | L43: =IFERROR(365/L35,0) -> 104.83236 | N43: =IFERROR(AVERAGE(D43:L43),0) -> 99.856306 | O43: =IFERROR(MEDIAN(D43:L43),0) -> 99.044379
B44: inveontry day | D44: =IFERROR(365/D36,0) -> 17.431711 | E44: =IFERROR(365/E36,0) -> 16.0674 | F44: =IFERROR(365/F36,0) -> 23.597253 | G44: =IFERROR(365/G36,0) -> 22.822519 | H44: =IFERROR(365/H36,0) -> 36.607361 | I44: =IFERROR(365/I36,0) -> 40.137194 | J44: =IFERROR(365/J36,0) -> 32.310261 | K44: =IFERROR(365/K36,0) -> 31.115472 | L44: =IFERROR(365/L36,0) -> 30.246856 | N44: =IFERROR(AVERAGE(D44:L44),0) -> 27.815114 | O44: =IFERROR(MEDIAN(D44:L44),0) -> 30.246856
B45: cash converstion cycle | D45: =SUM(D42,D44)-D43 -> -64.000691 | E45: =SUM(E42,E44)-E43 -> -79.990117 | F45: =SUM(F42,F44)-F43 -> -62.067503 | G45: =SUM(G42,G44)-G43 -> -65.69185 | H45: =SUM(H42,H44)-H43 -> -87.884454 | I45: =SUM(I42,I44)-I43 -> -86.438871 | J45: =SUM(J42,J44)-J43 -> -68.225237 | K45: =SUM(K42,K44)-K43 -> -71.639487 | L45: =SUM(L42,L44)-L43 -> -77.989788 | N45: =IFERROR(AVERAGE(D45:L45),0) -> -73.769778 | O45: =IFERROR(MEDIAN(D45:L45),0) -> -71.639487
B47: CFO/sales | D47: =IFERROR('Historical IFS'!D84/'Historical IFS'!D12,0) -> 0.26587577 | E47: =IFERROR('Historical IFS'!E84/'Historical IFS'!E12,0) -> 0.3258241 | F47: =IFERROR('Historical IFS'!F84/'Historical IFS'!F12,0) -> 0.11411587 | G47: =IFERROR('Historical IFS'!G84/'Historical IFS'!G12,0) -> 0.19445944 | H47: =IFERROR('Historical IFS'!H84/'Historical IFS'!H12,0) -> 0.22074802 | I47: =IFERROR('Historical IFS'!I84/'Historical IFS'!I12,0) -> 0.13546543 | J47: =IFERROR('Historical IFS'!J84/'Historical IFS'!J12,0) -> 0.20003905 | K47: =IFERROR('Historical IFS'!K84/'Historical IFS'!K12,0) -> 0.24867288 | L47: =IFERROR('Historical IFS'!L84/'Historical IFS'!L12,0) -> 0.22209445 | N47: =IFERROR(AVERAGE(D47:L47),0) -> 0.21414389 | O47: =IFERROR(MEDIAN(D47:L47),0) -> 0.22074802
B48: CFO/Total Assest | D48: =IFERROR('Historical IFS'!D84/'Historical IFS'!D70,0) -> 0.26679678 | E48: =IFERROR('Historical IFS'!E84/'Historical IFS'!E70,0) -> 0.30675588 | F48: =IFERROR('Historical IFS'!F84/'Historical IFS'!F70,0) -> 0.098183603 | G48: =IFERROR('Historical IFS'!G84/'Historical IFS'!G70,0) -> 0.1429751 | H48: =IFERROR('Historical IFS'!H84/'Historical IFS'!H70,0) -> 0.13222416 | I48: =IFERROR('Historical IFS'!I84/'Historical IFS'!I70,0) -> 0.086432137 | J48: =IFERROR('Historical IFS'!J84/'Historical IFS'!J70,0) -> 0.15048725 | K48: =IFERROR('Historical IFS'!K84/'Historical IFS'!K70,0) -> 0.17789214 | L48: =IFERROR('Historical IFS'!L84/'Historical IFS'!L70,0) -> 0.15422598 | N48: =IFERROR(AVERAGE(D48:L48),0) -> 0.16844145 | O48: =IFERROR(MEDIAN(D48:L48),0) -> 0.15048725
B49: CFO/Total debt | D49: ='Historical IFS'!D95/'Historical IFS'!D55 -> -15.583371 | E49: ='Historical IFS'!E95/'Historical IFS'!E55 -> -14.207107 | F49: ='Historical IFS'!F95/'Historical IFS'!F55 -> -3.5339473 | G49: ='Historical IFS'!G95/'Historical IFS'!G55 -> -6.060241 | H49: ='Historical IFS'!H95/'Historical IFS'!H55 -> -7.4116306 | I49: ='Historical IFS'!I95/'Historical IFS'!I55 -> -9.135642 | J49: ='Historical IFS'!J95/'Historical IFS'!J55 -> -8.3076176 | K49: ='Historical IFS'!K95/'Historical IFS'!K55 -> -6.759012 | L49: ='Historical IFS'!L95/'Historical IFS'!L55 -> -5.3696549 | N49: =IFERROR(AVERAGE(D49:L49),0) -> -8.4853581 | O49: =IFERROR(MEDIAN(D49:L49),0) -> -7.4116306

Sheet Revenue Forcasting 
D2: =data!C23 -> Eicher Motors Limited is an Indian multinational automotive company that manufactures motorcycles and commercial vehicles, headquartered in New Delhi. Eicher is the parent company of Royal Enfield, a manufacturer of middleweight motorcycles. It also manufactures Eicher branded trucks and buses, under a joint venture with Volvo Group.
B9: ="Revenue Forcasting Sales - " &'Data Sheet'!B1 -> Revenue Forcasting Sales - EICHER MOTORS LTD
B11: year weight | C11: Years | D11: Sales | E11: Sales Growt
B12: 1 | C12: =IFERROR('Data Sheet'!B16,0) -> 42460 | D12: {=TRANSPOSE('Data Sheet'!B17:K17)} -> 6173.46
B13: 2 | C13: =C12+365 -> 42825 | D13: 7033.36 | E13: =D13/D12-1 -> 0.1392898
B14: 3 | C14: =C13+365 -> 43190 | D14: 8964.96 | E14: =D14/D13-1 -> 0.27463403
B15: 4 | C15: =C14+365 -> 43555 | D15: 9797.06 | E15: =D15/D14-1 -> 0.092816923
B16: 5 | C16: =C15+365 -> 43920 | D16: 9153.58 | E16: =D16/D15-1 -> -0.065680929
B17: 6 | C17: =C16+365 -> 44285 | D17: 8720.35 | E17: =D17/D16-1 -> -0.047329023
B18: 7 | C18: =C17+365 -> 44650 | D18: 10297.83 | E18: =D18/D17-1 -> 0.18089641
B19: 8 | C19: =C18+365 -> 45015 | D19: 14442.18 | E19: =D19/D18-1 -> 0.40244887
B20: 9 | C20: =C19+365 -> 45380 | D20: 16535.78 | E20: =D20/D19-1 -> 0.14496426
B21: 10 | C21: =C20+365 -> 45745 | D21: 18870.35 | E21: =D21/D20-1 -> 0.14118294
B22: 11 | C22: =C21+365 -> 46110 | D22: =FORECAST(B22,$D$12:$D$21,$B$12:$B$21) -> 17973.695 | E22: =D22/D21-1 -> -0.047516589
B23: 12 | C23: =C22+365 -> 46475 | D23: =FORECAST(B23,$D$12:$D$21,$B$12:$B$21) -> 19241.842 | E23: =D23/D22-1 -> 0.070555677
B24: 13 | C24: =C23+365 -> 46840 | D24: =FORECAST(B24,$D$12:$D$21,$B$12:$B$21) -> 20509.988 | E24: =D24/D23-1 -> 0.065905659
B25: 14 | C25: =C24+365 -> 47205 | D25: =FORECAST(B25,$D$12:$D$21,$B$12:$B$21) -> 21778.134 | E25: =D25/D24-1 -> 0.061830668
B26: 15 | C26: =C25+365 -> 47570 | D26: =FORECAST(B26,$D$12:$D$21,$B$12:$B$21) -> 23046.28 | E26: =D26/D25-1 -> 0.058230252
B27: 16 | C27: =C26+365 -> 47935 | D27: =FORECAST(B27,$D$12:$D$21,$B$12:$B$21) -> 24314.427 | E27: =D27/D26-1 -> 0.05502607
B29: ="EBITA - "&'Data Sheet'!B1 -> EBITA - EICHER MOTORS LTD
B31: year weight | C31: Years | D31: Sales | E31: Sales Growt
B32: 1 | C32: =IFERROR('Data Sheet'!B16,0) -> 42460 | D32: {=TRANSPOSE('Historical IFS'!C24:M24)} -> 1627.68
B33: 2 | C33: =C32+365 -> 42825 | D33: 2154.7 | E33: =D33/D32-1 -> 0.323786
B34: 3 | C34: =C33+365 -> 43190 | D34: 2774.76 | E34: =D34/D33-1 -> 0.28777092
B35: 4 | C35: =C34+365 -> 43555 | D35: 2694.08 | E35: =D35/D34-1 -> -0.029076389
B36: 5 | C36: =C35+365 -> 43920 | D36: 2266.98 | E36: =D36/D35-1 -> -0.15853278
B37: 6 | C37: =C36+365 -> 44285 | D37: 1577.33 | E37: =D37/D36-1 -> -0.3042153
B38: 7 | C38: =C37+365 -> 44650 | D38: 2028.98 | E38: =D38/D37-1 -> 0.28633831
B39: 8 | C39: =C38+365 -> 45015 | D39: 3382.47 | E39: =D39/D38-1 -> 0.66707902
B40: 9 | C40: =C39+365 -> 45380 | D40: 4132.34 | E40: =D40/D39-1 -> 0.22169302
B41: 10 | C41: =C40+365 -> 45745 | D41: 4559.06 | E41: =D41/D40-1 -> 0.10326353
B42: 11 | C42: =C41+365 -> 46110 | D42: =FORECAST(B42,D32:D41,B32:B41) -> 4072.488 | E42: =D42/D41-1 -> -0.10672639
B43: 12 | C43: =C42+365 -> 46475 | D43: =FORECAST(B43,D33:D42,B33:B42) -> 4322.3059 | E43: =D43/D42-1 -> 0.061342812
B44: 13 | C44: =C43+365 -> 46840 | D44: =FORECAST(B44,D34:D43,B34:B43) -> 4649.6023 | E44: =D44/D43-1 -> 0.075722656
B45: 14 | C45: =C44+365 -> 47205 | D45: =FORECAST(B45,D35:D44,B35:B44) -> 5128.6597 | E45: =D45/D44-1 -> 0.1030319
B46: 15 | C46: =C45+365 -> 47570 | D46: =FORECAST(B46,D36:D45,B36:B45) -> 5652.8358 | E46: =D46/D45-1 -> 0.10220529
B47: 16 | C47: =C46+365 -> 47935 | D47: =FORECAST(B47,D37:D46,B37:B46) -> 6110.4838 | E47: =D47/D46-1 -> 0.080959
B50: ="EPS - "&'Data Sheet'!B1 -> EPS - EICHER MOTORS LTD
B52: year weight | C52: Years | D52: Sales | E52: Sales Growt
B53: 1 | C53: =IFERROR('Data Sheet'!B16,0) -> 42460 | D53: {=TRANSPOSE('Historical IFS'!C44:M44)} -> 34.980027
B54: 2 | C54: =C53+365 -> 42825 | D54: 46.931556 | E54: =D54/D53-1 -> 0.34166722
B55: 3 | C55: =C54+365 -> 43190 | D55: 59.066929 | E55: =D55/D54-1 -> 0.258576
B56: 4 | C56: =C55+365 -> 43555 | D56: 47.998482 | E56: =D56/D55-1 -> -0.18738822
B57: 5 | C57: =C56+365 -> 43920 | D57: 49.032086 | E57: =D57/D56-1 -> 0.021534078
B58: 6 | C58: =C57+365 -> 44285 | D58: 24.09793 | E58: =D58/D57-1 -> -0.50852733
B59: 7 | C59: =C58+365 -> 44650 | D59: 37.758387 | E59: =D59/D58-1 -> 0.56687262
B60: 8 | C60: =C59+365 -> 45015 | D60: 71.024191 | E60: =D60/D59-1 -> 0.88101763
B61: 9 | C61: =C60+365 -> 45380 | D61: 83.37512 | E61: =D61/D60-1 -> 0.17389749
B62: 10 | C62: =C61+365 -> 45745 | D62: 93.972227 | E62: =D62/D61-1 -> 0.12710155
B63: 11 | C63: =C62+365 -> 46110 | D63: =FORECAST(B63,D53:D62,B53:B62) -> 81.162581 | E63: =D63/D62-1 -> -0.13631311
B64: 12 | C64: =C63+365 -> 46475 | D64: =FORECAST(B64,D54:D63,B54:B63) -> 86.406491 | E64: =D64/D63-1 -> 0.064609953
B65: 13 | C65: =C64+365 -> 46840 | D65: =FORECAST(B65,D55:D64,B55:B64) -> 93.856203 | E65: =D65/D64-1 -> 0.086217042
B66: 14 | C66: =C65+365 -> 47205 | D66: =FORECAST(B66,D56:D65,B56:B65) -> 104.89024 | E66: =D66/D65-1 -> 0.11756319
B67: 15 | C67: =C66+365 -> 47570 | D67: =FORECAST(B67,D57:D66,B57:B66) -> 115.06701 | E67: =D67/D66-1 -> 0.097023111
B68: 16 | C68: =C67+365 -> 47935 | D68: =FORECAST(B68,D58:D67,B58:B67) -> 125.79735 | E68: =D68/D67-1 -> 0.093252891

Sheet Common size statement
D2: =data!C23 -> Eicher Motors Limited is an Indian multinational automotive company that manufactures motorcycles and commercial vehicles, headquartered in New Delhi. Eicher is the parent company of Royal Enfield, a manufacturer of middleweight motorcycles. It also manufactures Eicher branded trucks and buses, under a joint venture with Volvo Group.
B9: ="Common size Income statement - "&'Data Sheet'!B1 -> Common size Income statement - EICHER MOTORS LTD
B11: Particulars | C11: =IFERROR('Data Sheet'!B16,0) -> 42460 | D11: =IFERROR('Data Sheet'!C16,0) -> 42825 | E11: =IFERROR('Data Sheet'!D16,0) -> 43190 | F11: =IFERROR('Data Sheet'!E16,0) -> 43555 | G11: =IFERROR('Data Sheet'!F16,0) -> 43921 | H11: =IFERROR('Data Sheet'!G16,0) -> 44286 | I11: =IFERROR('Data Sheet'!H16,0) -> 44651 | J11: =IFERROR('Data Sheet'!I16,0) -> 45016 | ... L11: =IFERROR('Data Sheet'!K16,0) -> 45747
B12: =IFERROR('Data Sheet'!A17,0) -> Sales | C12: ='Data Sheet'!B17/'Data Sheet'!B$17 -> 1 | D12: ='Data Sheet'!C17/'Data Sheet'!C$17 -> 1 | E12: ='Data Sheet'!D17/'Data Sheet'!D$17 -> 1 | F12: ='Data Sheet'!E17/'Data Sheet'!E$17 -> 1 | G12: ='Data Sheet'!F17/'Data Sheet'!F$17 -> 1 | H12: ='Data Sheet'!G17/'Data Sheet'!G$17 -> 1 | I12: ='Data Sheet'!H17/'Data Sheet'!H$17 -> 1 | J12: ='Data Sheet'!I17/'Data Sheet'!I$17 -> 1 | ... L12: ='Data Sheet'!K17/'Data Sheet'!K$17 -> 1
B13: =IFERROR('Data Sheet'!A18,0) -> Raw Material Cost | C13: ='Data Sheet'!B18/'Data Sheet'!B$17 -> 0.56657531 | D13: ='Data Sheet'!C18/'Data Sheet'!C$17 -> 0.52972121 | E13: ='Data Sheet'!D18/'Data Sheet'!D$17 -> 0.52192871 | F13: ='Data Sheet'!E18/'Data Sheet'!E$17 -> 0.53787973 | G13: ='Data Sheet'!F18/'Data Sheet'!F$17 -> 0.5369025 | H13: ='Data Sheet'!G18/'Data Sheet'!G$17 -> 0.61005006 | I13: ='Data Sheet'!H18/'Data Sheet'!H$17 -> 0.59306475 | J13: ='Data Sheet'!I18/'Data Sheet'!I$17 -> 0.57339266 | ... L13: ='Data Sheet'!K18/'Data Sheet'!K$17 -> 0.55484344
B14: =IFERROR('Data Sheet'!A19,0) -> Change in Inventory | C14: ='Data Sheet'!B19/'Data Sheet'!B$17 -> 0.01005109 | D14: ='Data Sheet'!C19/'Data Sheet'!C$17 -> 0.0027881411 | E14: ='Data Sheet'!D19/'Data Sheet'!D$17 -> 0.0037780425 | F14: ='Data Sheet'!E19/'Data Sheet'!E$17 -> 0.021451333 | G14: ='Data Sheet'!F19/'Data Sheet'!F$17 -> -0.0091865696 | H14: ='Data Sheet'!G19/'Data Sheet'!G$17 -> 0.023611438 | I14: ='Data Sheet'!H19/'Data Sheet'!H$17 -> 0.014429254 | J14: ='Data Sheet'!I19/'Data Sheet'!I$17 -> 0.0043795327 | ... L14: ='Data Sheet'!K19/'Data Sheet'!K$17 -> 0.0086649161
B15: =IFERROR('Data Sheet'!A20,0) -> Power and Fuel | C15: ='Data Sheet'!B20/'Data Sheet'!B$17 -> 0.0074804081 | D15: ='Data Sheet'!C20/'Data Sheet'!C$17 -> 0.0065431032 | E15: ='Data Sheet'!D20/'Data Sheet'!D$17 -> 0.0058460941 | F15: ='Data Sheet'!E20/'Data Sheet'!E$17 -> 0.0068347035 | G15: ='Data Sheet'!F20/'Data Sheet'!F$17 -> 0.0068672585 | H15: ='Data Sheet'!G20/'Data Sheet'!G$17 -> 0.0060754442 | I15: ='Data Sheet'!H20/'Data Sheet'!H$17 -> 0.0054166752 | J15: ='Data Sheet'!I20/'Data Sheet'!I$17 -> 0.0050525613 | ... L15: ='Data Sheet'!K20/'Data Sheet'!K$17 -> 0.0047444801
B16: =IFERROR('Data Sheet'!A21,0) -> Other Mfr. Exp | C16: ='Data Sheet'!B21/'Data Sheet'!B$17 -> 0.028146291 | D16: ='Data Sheet'!C21/'Data Sheet'!C$17 -> 0.024609859 | E16: ='Data Sheet'!D21/'Data Sheet'!D$17 -> 0.023509307 | F16: ='Data Sheet'!E21/'Data Sheet'!E$17 -> 0.026894803 | G16: ='Data Sheet'!F21/'Data Sheet'!F$17 -> 0.028030563 | H16: ='Data Sheet'!G21/'Data Sheet'!G$17 -> 0.028766047 | I16: ='Data Sheet'!H21/'Data Sheet'!H$17 -> 0.032279616 | J16: ='Data Sheet'!I21/'Data Sheet'!I$17 -> 0.027503466 | ... L16: ='Data Sheet'!K21/'Data Sheet'!K$17 -> 0.024046719
B17: =IFERROR('Data Sheet'!A22,0) -> Employee Cost | C17: ='Data Sheet'!B22/'Data Sheet'!B$17 -> 0.056728318 | D17: ='Data Sheet'!C22/'Data Sheet'!C$17 -> 0.060608301 | E17: ='Data Sheet'!D22/'Data Sheet'!D$17 -> 0.063991362 | F17: ='Data Sheet'!E22/'Data Sheet'!E$17 -> 0.071699061 | G17: ='Data Sheet'!F22/'Data Sheet'!F$17 -> 0.086936477 | H17: ='Data Sheet'!G22/'Data Sheet'!G$17 -> 0.096696807 | I17: ='Data Sheet'!H22/'Data Sheet'!H$17 -> 0.079727477 | J17: ='Data Sheet'!I22/'Data Sheet'!I$17 -> 0.069375261 | ... L17: ='Data Sheet'!K22/'Data Sheet'!K$17 -> 0.073725713
B18: =IFERROR('Data Sheet'!A23,0) -> Selling and admin | C18: ='Data Sheet'!B23/'Data Sheet'!B$17 -> 0.064372329 | D18: ='Data Sheet'!C23/'Data Sheet'!C$17 -> 0.058613522 | E18: ='Data Sheet'!D23/'Data Sheet'!D$17 -> 0.063096768 | F18: ='Data Sheet'!E23/'Data Sheet'!E$17 -> 0.066838419 | G18: ='Data Sheet'!F23/'Data Sheet'!F$17 -> 0.072885144 | H18: ='Data Sheet'!G23/'Data Sheet'!G$17 -> 0.059919613 | I18: ='Data Sheet'!H23/'Data Sheet'!H$17 -> 0.079192412 | J18: ='Data Sheet'!I23/'Data Sheet'!I$17 -> 0.080637411 | ... L18: ='Data Sheet'!K23/'Data Sheet'!K$17 -> 0.088479016
B19: =IFERROR('Data Sheet'!A24,0) -> Other Expenses | C19: ='Data Sheet'!B24/'Data Sheet'!B$17 -> 0.013039689 | D19: ='Data Sheet'!C24/'Data Sheet'!C$17 -> 0.013549712 | E19: ='Data Sheet'!D24/'Data Sheet'!D$17 -> 0.012116061 | F19: ='Data Sheet'!E24/'Data Sheet'!E$17 -> 0.014864663 | G19: ='Data Sheet'!F24/'Data Sheet'!F$17 -> 0.020717577 | H19: ='Data Sheet'!G24/'Data Sheet'!G$17 -> 0.017612825 | I19: ='Data Sheet'!H24/'Data Sheet'!H$17 -> 0.013289208 | J19: ='Data Sheet'!I24/'Data Sheet'!I$17 -> 0.0098309258 | ... L19: ='Data Sheet'!K24/'Data Sheet'!K$17 -> 0.012561505
B20: =IFERROR('Data Sheet'!A25,0) -> Other Income | C20: ='Data Sheet'!B25/'Data Sheet'!B$17 -> 0.052792113 | D20: ='Data Sheet'!C25/'Data Sheet'!C$17 -> 0.059209254 | E20: ='Data Sheet'!D25/'Data Sheet'!D$17 -> 0.059750406 | F20: ='Data Sheet'!E25/'Data Sheet'!E$17 -> 0.071517374 | G20: ='Data Sheet'!F25/'Data Sheet'!F$17 -> 0.062535096 | H20: ='Data Sheet'!G25/'Data Sheet'!G$17 -> 0.055312 | I20: ='Data Sheet'!H25/'Data Sheet'!H$17 -> 0.0481315 | J20: ='Data Sheet'!I25/'Data Sheet'!I$17 -> 0.062881089 | ... L20: ='Data Sheet'!K25/'Data Sheet'!K$17 -> 0.10567743
B21: =IFERROR('Data Sheet'!A26,0) -> Depreciation | C21: ='Data Sheet'!B26/'Data Sheet'!B$17 -> 0.022126976 | D21: ='Data Sheet'!C26/'Data Sheet'!C$17 -> 0.021868637 | E21: ='Data Sheet'!D26/'Data Sheet'!D$17 -> 0.024908087 | F21: ='Data Sheet'!E26/'Data Sheet'!E$17 -> 0.030650011 | G21: ='Data Sheet'!F26/'Data Sheet'!F$17 -> 0.041682052 | H21: ='Data Sheet'!G26/'Data Sheet'!G$17 -> 0.051687146 | I21: ='Data Sheet'!H26/'Data Sheet'!H$17 -> 0.043885945 | J21: ='Data Sheet'!I26/'Data Sheet'!I$17 -> 0.036435635 | ... L21: ='Data Sheet'!K26/'Data Sheet'!K$17 -> 0.038649522
B22: =IFERROR('Data Sheet'!A27,0) -> Interest | C22: ='Data Sheet'!B27/'Data Sheet'!B$17 -> 0.00034340548 | D22: ='Data Sheet'!C27/'Data Sheet'!C$17 -> 0.00050615922 | E22: ='Data Sheet'!D27/'Data Sheet'!D$17 -> 0.00059565241 | F22: ='Data Sheet'!E27/'Data Sheet'!E$17 -> 0.00074818364 | G22: ='Data Sheet'!F27/'Data Sheet'!F$17 -> 0.002062581 | H22: ='Data Sheet'!G27/'Data Sheet'!G$17 -> 0.0018863922 | I22: ='Data Sheet'!H27/'Data Sheet'!H$17 -> 0.0018236852 | J22: ='Data Sheet'!I27/'Data Sheet'!I$17 -> 0.0019401503 | ... L22: ='Data Sheet'!K27/'Data Sheet'!K$17 -> 0.0028796498
B23: =IFERROR('Data Sheet'!A28,0) -> Profit before tax | C23: ='Data Sheet'!B28/'Data Sheet'!B$17 -> 0.30403048 | D23: ='Data Sheet'!C28/'Data Sheet'!C$17 -> 0.34597689 | E23: ='Data Sheet'!D28/'Data Sheet'!D$17 -> 0.34753641 | F23: ='Data Sheet'!E28/'Data Sheet'!E$17 -> 0.33655913 | G23: ='Data Sheet'!F28/'Data Sheet'!F$17 -> 0.25726437 | H23: ='Data Sheet'!G28/'Data Sheet'!G$17 -> 0.20622911 | I23: ='Data Sheet'!H28/'Data Sheet'!H$17 -> 0.21388098 | J23: ='Data Sheet'!I28/'Data Sheet'!I$17 -> 0.26309255 | ... L23: ='Data Sheet'!K28/'Data Sheet'!K$17 -> 0.31441229
... B26: =IFERROR('Data Sheet'!A31,0) -> Dividend Amount | C26: ='Data Sheet'!B31/'Data Sheet'!B$17 -> 0.043994778 | D26: ='Data Sheet'!C31/'Data Sheet'!C$17 -> 0.038687057 | E26: ='Data Sheet'!D31/'Data Sheet'!D$17 -> 0.033448002 | F26: ='Data Sheet'!E31/'Data Sheet'!E$17 -> 0.03480636 | G26: ='Data Sheet'!F31/'Data Sheet'!F$17 -> 0.037280496 | H26: ='Data Sheet'!G31/'Data Sheet'!G$17 -> 0.053278825 | I26: ='Data Sheet'!H31/'Data Sheet'!H$17 -> 0.055753494 | J26: ='Data Sheet'!I31/'Data Sheet'!I$17 -> 0.070069062 | ... L26: ='Data Sheet'!K31/'Data Sheet'!K$17 -> 0.10171512
B27: EBIDTA | C27: ='Data Sheet'!B32/'Data Sheet'!B$17 -> 0.32650086 | D27: ='Data Sheet'!C32/'Data Sheet'!C$17 -> 0.36181142 | E27: ='Data Sheet'!D32/'Data Sheet'!D$17 -> 0.34849458 | F27: ='Data Sheet'!E32/'Data Sheet'!E$17 -> 0.36616903 | G27: ='Data Sheet'!F32/'Data Sheet'!F$17 -> 0.301009 | H27: ='Data Sheet'!G32/'Data Sheet'!G$17 -> 0.25980265 | I27: ='Data Sheet'!H32/'Data Sheet'!H$17 -> 0.25959061 | J27: ='Data Sheet'!I32/'Data Sheet'!I$17 -> 0.30146834 | ... L27: ='Data Sheet'!K32/'Data Sheet'!K$17 -> 0.35594146
B29: ="Common size Balance sheet statement - "&'Data Sheet'!B1 -> Common size Balance sheet statement - EICHER MOTORS LTD
B31: Particulars | C31: 42460 | D31: 42825 | E31: 43190 | F31: 43555 | G31: 43921 | H31: 44286 | I31: 44651 | J31: 45016 | K31: 45382 | L31: 45747
B32: Total Liabilaty | C32: ='Data Sheet'!B61/'Data Sheet'!B$61 -> 1 | D32: ='Data Sheet'!C61/'Data Sheet'!C$61 -> 1 | E32: ='Data Sheet'!D61/'Data Sheet'!D$61 -> 1 | F32: ='Data Sheet'!E61/'Data Sheet'!E$61 -> 1 | G32: ='Data Sheet'!F61/'Data Sheet'!F$61 -> 1 | H32: ='Data Sheet'!G61/'Data Sheet'!G$61 -> 1 | I32: ='Data Sheet'!H61/'Data Sheet'!H$61 -> 1 | J32: ='Data Sheet'!I61/'Data Sheet'!I$61 -> 1 | ... L32: ='Data Sheet'!K61/'Data Sheet'!K$61 -> 1
B33: ='Data Sheet'!A57 -> Equity Share Capital | C33: ='Data Sheet'!B62/'Data Sheet'!B$61 -> 0.15986807 | D33: ='Data Sheet'!C62/'Data Sheet'!C$61 -> 0.12452134 | E33: ='Data Sheet'!D62/'Data Sheet'!D$61 -> 0.15770361 | F33: ='Data Sheet'!E62/'Data Sheet'!E$61 -> 0.16462703 | G33: ='Data Sheet'!F62/'Data Sheet'!F$61 -> 0.19096976 | H33: ='Data Sheet'!G62/'Data Sheet'!G$61 -> 0.16713821 | I33: ='Data Sheet'!H62/'Data Sheet'!H$61 -> 0.1502048 | J33: ='Data Sheet'!I62/'Data Sheet'!I$61 -> 0.14012087 | ... L33: ='Data Sheet'!K62/'Data Sheet'!K$61 -> 0.12782136
B34: ='Data Sheet'!A58 -> Reserves | C34: ='Data Sheet'!B63/'Data Sheet'!B$61 -> 0.01912934 | D34: ='Data Sheet'!C63/'Data Sheet'!C$61 -> 0.053326542 | E34: ='Data Sheet'!D63/'Data Sheet'!D$61 -> 0.034992854 | F34: ='Data Sheet'!E63/'Data Sheet'!E$61 -> 0.039496506 | G34: ='Data Sheet'!F63/'Data Sheet'!F$61 -> 0.02507446 | H34: ='Data Sheet'!G63/'Data Sheet'!G$61 -> 0.021587913 | I34: ='Data Sheet'!H63/'Data Sheet'!H$61 -> 0.031275422 | J34: ='Data Sheet'!I63/'Data Sheet'!I$61 -> 0.024590002 | ... L34: ='Data Sheet'!K63/'Data Sheet'!K$61 -> 0.018085765
B35: ='Data Sheet'!A59 -> Borrowings | C35: ='Data Sheet'!B64/'Data Sheet'!B$61 -> 0.68601602 | D35: ='Data Sheet'!C64/'Data Sheet'!C$61 -> 0.71152419 | E35: ='Data Sheet'!D64/'Data Sheet'!D$61 -> 0.5860854 | F35: ='Data Sheet'!E64/'Data Sheet'!E$61 -> 0.43229942 | G35: ='Data Sheet'!F64/'Data Sheet'!F$61 -> 0.46175898 | H35: ='Data Sheet'!G64/'Data Sheet'!G$61 -> 0.26802971 | I35: ='Data Sheet'!H64/'Data Sheet'!H$61 -> 0.47835572 | J35: ='Data Sheet'!I64/'Data Sheet'!I$61 -> 0.64177993 | ... L35: ='Data Sheet'!K64/'Data Sheet'!K$61 -> 0.54429517
B36: ='Data Sheet'!A60 -> Other Liabilities | C36: ='Data Sheet'!B65/'Data Sheet'!B$61 -> 0.13498657 | D36: ='Data Sheet'!C65/'Data Sheet'!C$61 -> 0.11062793 | E36: ='Data Sheet'!D65/'Data Sheet'!D$61 -> 0.22121814 | F36: ='Data Sheet'!E65/'Data Sheet'!E$61 -> 0.36357704 | G36: ='Data Sheet'!F65/'Data Sheet'!F$61 -> 0.3221968 | H36: ='Data Sheet'!G65/'Data Sheet'!G$61 -> 0.54324417 | I36: ='Data Sheet'!H65/'Data Sheet'!H$61 -> 0.34016405 | J36: ='Data Sheet'!I65/'Data Sheet'!I$61 -> 0.1935092 | ... L36: ='Data Sheet'!K65/'Data Sheet'!K$61 -> 0.30979771
B38: Total Assest | C38: ='Data Sheet'!B74/'Data Sheet'!B$74 -> 1 | D38: ='Data Sheet'!C74/'Data Sheet'!C$74 -> 1 | E38: ='Data Sheet'!D74/'Data Sheet'!D$74 -> 1 | F38: ='Data Sheet'!E74/'Data Sheet'!E$74 -> 1 | G38: ='Data Sheet'!F74/'Data Sheet'!F$74 -> 1 | H38: ='Data Sheet'!G74/'Data Sheet'!G$74 -> 1 | I38: ='Data Sheet'!H74/'Data Sheet'!H$74 -> 1 | J38: ='Data Sheet'!I74/'Data Sheet'!I$74 -> 1 | ... L38: ='Data Sheet'!K74/'Data Sheet'!K$74 -> 1
B39: ='Data Sheet'!A62 -> Net Block | C39: ='Data Sheet'!B62/'Data Sheet'!B$74 -> 0.15986807 | D39: ='Data Sheet'!C62/'Data Sheet'!C$74 -> 0.12452134 | E39: ='Data Sheet'!D62/'Data Sheet'!D$74 -> 0.15770361 | F39: ='Data Sheet'!E62/'Data Sheet'!E$74 -> 0.16462703 | G39: ='Data Sheet'!F62/'Data Sheet'!F$74 -> 0.19096976 | H39: ='Data Sheet'!G62/'Data Sheet'!G$74 -> 0.16713821 | I39: ='Data Sheet'!H62/'Data Sheet'!H$74 -> 0.1502048 | J39: ='Data Sheet'!I62/'Data Sheet'!I$74 -> 0.14012087 | ... L39: ='Data Sheet'!K62/'Data Sheet'!K$74 -> 0.12782136
B40: ='Data Sheet'!A63 -> Capital Work in Progress | C40: ='Data Sheet'!B63/'Data Sheet'!B$74 -> 0.01912934 | D40: ='Data Sheet'!C63/'Data Sheet'!C$74 -> 0.053326542 | E40: ='Data Sheet'!D63/'Data Sheet'!D$74 -> 0.034992854 | F40: ='Data Sheet'!E63/'Data Sheet'!E$74 -> 0.039496506 | G40: ='Data Sheet'!F63/'Data Sheet'!F$74 -> 0.02507446 | H40: ='Data Sheet'!G63/'Data Sheet'!G$74 -> 0.021587913 | I40: ='Data Sheet'!H63/'Data Sheet'!H$74 -> 0.031275422 | J40: ='Data Sheet'!I63/'Data Sheet'!I$74 -> 0.024590002 | ... L40: ='Data Sheet'!K63/'Data Sheet'!K$74 -> 0.018085765
B41: ='Data Sheet'!A64 -> Investments | C41: ='Data Sheet'!B64/'Data Sheet'!B$74 -> 0.68601602 | D41: ='Data Sheet'!C64/'Data Sheet'!C$74 -> 0.71152419 | E41: ='Data Sheet'!D64/'Data Sheet'!D$74 -> 0.5860854 | F41: ='Data Sheet'!E64/'Data Sheet'!E$74 -> 0.43229942 | G41: ='Data Sheet'!F64/'Data Sheet'!F$74 -> 0.46175898 | H41: ='Data Sheet'!G64/'Data Sheet'!G$74 -> 0.26802971 | I41: ='Data Sheet'!H64/'Data Sheet'!H$74 -> 0.47835572 | J41: ='Data Sheet'!I64/'Data Sheet'!I$74 -> 0.64177993 | ... L41: ='Data Sheet'!K64/'Data Sheet'!K$74 -> 0.54429517
B42: ='Data Sheet'!A65 -> Other Assets | C42: ='Data Sheet'!B73/'Data Sheet'!B$74 -> 0.055982879 | D42: ='Data Sheet'!C73/'Data Sheet'!C$74 -> 0.051989705 | E42: ='Data Sheet'!D73/'Data Sheet'!D$74 -> 0.045351772 | F42: ='Data Sheet'!E73/'Data Sheet'!E$74 -> 0.040136719 | G42: ='Data Sheet'!F73/'Data Sheet'!F$74 -> 0.032254541 | H42: ='Data Sheet'!G73/'Data Sheet'!G$74 -> 0.071831033 | I42: ='Data Sheet'!H73/'Data Sheet'!H$74 -> 0.082608057 | J42: ='Data Sheet'!I73/'Data Sheet'!I$74 -> 0.067819795 | ... L42: ='Data Sheet'!K73/'Data Sheet'!K$74 -> 0.22234779
B43: ='Data Sheet'!A67 -> Receivables | C43: ='Data Sheet'!B67/'Data Sheet'!B$74 -> 0.0066086118 | D43: ='Data Sheet'!C67/'Data Sheet'!C$74 -> 0.0071393107 | E43: ='Data Sheet'!D67/'Data Sheet'!D$74 -> 0.0071411844 | F43: ='Data Sheet'!E67/'Data Sheet'!E$74 -> 0.0074024114 | G43: ='Data Sheet'!F67/'Data Sheet'!F$74 -> 0.0069688314 | H43: ='Data Sheet'!G67/'Data Sheet'!G$74 -> 0.010863674 | I43: ='Data Sheet'!H67/'Data Sheet'!H$74 -> 0.018713952 | J43: ='Data Sheet'!I67/'Data Sheet'!I$74 -> 0.019216945 | ... L43: ='Data Sheet'!K67/'Data Sheet'!K$74 -> 0.020226382
B44: ='Data Sheet'!A68 -> Inventory | C44: ='Data Sheet'!B68/'Data Sheet'!B$74 -> 0.062439639 | D44: ='Data Sheet'!C68/'Data Sheet'!C$74 -> 0.047923551 | E44: ='Data Sheet'!D68/'Data Sheet'!D$74 -> 0.041444073 | F44: ='Data Sheet'!E68/'Data Sheet'!E$74 -> 0.055623909 | G44: ='Data Sheet'!F68/'Data Sheet'!F$74 -> 0.045972921 | H44: ='Data Sheet'!G68/'Data Sheet'!G$74 -> 0.060074416 | I44: ='Data Sheet'!H68/'Data Sheet'!H$74 -> 0.070161829 | J44: ='Data Sheet'!I68/'Data Sheet'!I$74 -> 0.066593602 | ... L44: ='Data Sheet'!K68/'Data Sheet'!K$74 -> 0.057544948
B45: ='Data Sheet'!A69 -> Cash & Bank | C45: ='Data Sheet'!B69/'Data Sheet'!B$74 -> 0.0099554364 | D45: ='Data Sheet'!C69/'Data Sheet'!C$74 -> 0.0035753622 | E45: ='Data Sheet'!D69/'Data Sheet'!D$74 -> 0.12728111 | F45: ='Data Sheet'!E69/'Data Sheet'!E$74 -> 0.260414 | G45: ='Data Sheet'!F69/'Data Sheet'!F$74 -> 0.23700051 | H45: ='Data Sheet'!G69/'Data Sheet'!G$74 -> 0.40047505 | I45: ='Data Sheet'!H69/'Data Sheet'!H$74 -> 0.16868022 | J45: ='Data Sheet'!I69/'Data Sheet'!I$74 -> 0.03987886 | ... L45: ='Data Sheet'!K69/'Data Sheet'!K$74 -> 0.009678591

Sheet WACC
D2: =data!C23 -> Eicher Motors Limited is an Indian multinational automotive company that manufactures motorcycles and commercial vehicles, headquartered in New Delhi. Eicher is the parent company of Royal Enfield, a manufacturer of middleweight motorcycles. It also manufactures Eicher branded trucks and buses, under a joint venture with Volvo Group.
B9: ="Weighted Average Cost Of Capital - "&'Data Sheet'!B1 -> Weighted Average Cost Of Capital - EICHER MOTORS LTD
B10: all figures are in INR unless stated Otherwise
B12: peer comps
G14: debt/ | H14: debt/
B15: Name of the company | C15: Country | D15: Total Debt | E15: Total Equity | F15: Tax Rate 1 | G15: Equity | H15: Capital | I15: Leaverd Beta | J15: Unleavread Beta
B16: =O17 -> Eicher Motors | C16: India | D16: =IFERROR(P17,0) -> 7164.5 | E16: =IFERROR(Q17,0) -> 196493.51 | F16: 0.3 | G16: =D16/E16 -> 0.036461764 | H16: =D16/(D16+E16) -> 0.035179073 | I16: 1.0724979 | J16: =I16/(1+(1-F16)*G16) -> 1.0458056 | N16: S.No. | O16: Name | P16: CMP Rs. | Q16: Mar Cap Rs.Cr.
B17: =O18 -> Maruti Suzuki | C17: India | D17: =IFERROR(P18,0) -> 15240.95 | E17: =IFERROR(Q18,0) -> 479179.33 | F17: 0.3 | G17: =D17/E17 -> 0.031806359 | H17: =D17/(D17+E17) -> 0.0308259 | I17: 1.02 | J17: =I17/(1+(1-F17)*G17) -> 0.99778487 | N17: 1 | O17: Eicher Motors | P17: 7164.5 | Q17: 196493.51
B18: =O19 -> M & M | C18: India | D18: =IFERROR(P19,0) -> 3394.3 | E18: =IFERROR(Q19,0) -> 422091.07 | F18: 0.3 | G18: =D18/E18 -> 0.0080416295 | H18: =D18/(D18+E18) -> 0.0079774776 | I18: 1.47 | J18: =I18/(1+(1-F18)*G18) -> 1.4617715 | N18: 2 | O18: Maruti Suzuki | P18: 15240.95 | Q18: 479179.33
B19: =O20 -> Bajaj Auto | C19: India | D19: =IFERROR(P20,0) -> 9478.1 | E19: =IFERROR(Q20,0) -> 264916.47 | F19: 0.3 | G19: =D19/E19 -> 0.035777692 | H19: =D19/(D19+E19) -> 0.034541864 | I19: 0.994 | J19: =I19/(1+(1-F19)*G19) -> 0.96971411 | N19: 3 | O19: M & M | P19: 3394.3 | Q19: 422091.07
B20: =O21 -> Hyundai Motor I | C20: India | D20: =IFERROR(P21,0) -> 2173.4 | E20: =IFERROR(Q21,0) -> 176597.7 | F20: 0.3 | G20: =D20/E20 -> 0.012307069 | H20: =D20/(D20+E20) -> 0.012157446 | I20: 1.11 | J20: =I20/(1+(1-F20)*G20) -> 1.1005191 | N20: 4 | O20: Bajaj Auto | P20: 9478.1 | Q20: 264916.47
B21: =O22 -> TVS Motor Co. | C21: India | D21: =IFERROR(P22,0) -> 3565.3 | E21: =IFERROR(Q22,0) -> 169382.81 | F21: 0.3 | G21: =D21/E21 -> 0.021048771 | H21: =D21/(D21+E21) -> 0.020614854 | I21: 1.33 | J21: =I21/(1+(1-F21)*G21) -> 1.3106881 | N21: 5 | O21: Hyundai Motor I | P21: 2173.4 | Q21: 176597.7
N22: 6 | O22: TVS Motor Co. | P22: 3565.3 | Q22: 169382.81
E23: Average | F23: =AVERAGE(F16:F21) -> 0.3 | G23: =AVERAGE(G16:G21) -> 0.024240548 | H23: =AVERAGE(H16:H21) -> 0.023549436 | I23: =AVERAGE(I16:I21) -> 1.166083 | J23: =AVERAGE(J16:J21) -> 1.1477139
E24: Median | F24: =MEDIAN(F16:F21) -> 0.3 | G24: =MEDIAN(G16:G21) -> 0.026427565 | H24: =MEDIAN(H16:H21) -> 0.025720377 | I24: =MEDIAN(I16:I21) -> 1.091249 | J24: =MEDIAN(J16:J21) -> 1.0731623
B28: Cost of debt | G28: Cost of Equity | N28: 6.712
N29: =N28/M31 -> 0.06712
B30: Pre-Tax cost of debt | E30: =N36/N37 -> 0.12113599 | G30: Risk Free rate | J30: =N29 -> 0.06712
B31: Tax Rate | E31: =F23 -> 0.3 | G31: Equity Risk Premimum | J31: =RM!G14-WACC!J30 -> 0.084372308 | M31: 100 | N31: =M31/N28 -> 14.898689
B32: Aftet Tax Cost | E32: =E30*(1-E31) -> 0.08479519 | G32: Leavread Beta 4 | J32: =K40 -> 0.63631569
G33: Cost of Equity | J33: =J30+(J31*J32) -> 0.12080742
B35: Capital Strucutre | G35: leavread Beta
N36: 54
D37: Current | E37: Target | G37: Comps Median Unleavead Beta | J37: =J24 -> 1.0731623 | K37: =J24 -> 1.0731623 | N37: 445.78
B38: Total Debt | C38: =D16 -> 7164.5 | D38: =C38/$C$40 -> 0.035179073 | E38: =H23 -> 0.023549436 | G38: Targetd Tax Debt/Equity | J38: =E38 -> 0.023549436 | K38: =E38 -> 0.023549436
B39: Market Capitalization | C39: =E16 -> 196493.51 | D39: =C39/$C$40 -> 0.96482093 | E39: =E40-E38 -> 0.97645056 | G39: Tax Rate | J39: =F24 -> 0.3 | K39: =F24 -> 0.3
B40: Total Capitalization | C40: =SUM(C38:C39) -> 203658.01 | D40: =D38+D39 -> 1 | E40: 1 | G40: Levered Beta | J40: =J37*(1+1-J38)*J39 -> 0.63631569 | K40: =K37*(1+1-K38)*K39 -> 0.63631569
B42: Debt/Equity | D42: =D38/D39 -> 0.036461764 | E42: =E38/E39 -> 0.024117387
G44: Weighted Average Cost of Capital
I46: Total Cost | J46: Total Weight
B47: 1. Tax Rate considered as Marginal Tax Rate for the country | G47: Debt Capital | I47: =E32 -> 0.08479519 | J47: =J33 -> 0.12080742
B48: 2. Levered Beta is based on 5 year monthly data | G48: Equity Capital | I48: =J33 -> 0.12080742 | J48: =E39 -> 0.97645056
B49: 3. Unlevered Beta = Levered Beta/(1+(1-Tax Rate) x Debt/Equity) | G49: Weighted Average Cost of Capital | J49: =SUMPRODUCT(I47:I48,J47:J48) -> 0.12820637
B50: 4. Levered Beta = Unlevered Beta*(1+(1-Tax Rate) x Debt/Equity)

Sheet Forcasting data 
D1: =data!C23 -> Eicher Motors Limited is an Indian multinational automotive company that manufactures motorcycles and commercial vehicles, headquartered in New Delhi. Eicher is the parent company of Royal Enfield, a manufacturer of middleweight motorcycles. It also manufactures Eicher branded trucks and buses, under a joint venture with Volvo Group.
B9: ="Forcasting Data - "&'Data Sheet'!B1 -> Forcasting Data - EICHER MOTORS LTD
B11: Particulars | C11: =D11-1 -> 2016 | D11: =E11-1 -> 2017 | E11: =F11-1 -> 2018 | F11: =G11-1 -> 2019 | G11: =H11-1 -> 2020 | H11: =I11-1 -> 2021 | I11: =J11-1 -> 2022 | J11: =K11-1 -> 2023 | K11: 2024 | L11: 2025
C12: 42430 | D12: 42795 | E12: 43160 | F12: 43525 | G12: 43891 | H12: 44256 | I12: 44621 | J12: 44986 | K12: 45352 | L12: 45717
B13: Cash from Operating Activity - | C13: 1463 | D13: 1708 | E13: 2482 | F13: 1575 | G13: 1694 | H13: 1691 | I13: 1527 | J13: 2823 | K13: 3724 | L13: 3980
B14: Profit from operations | C14: 1719 | D14: 2196 | E14: 2851 | F14: 2941 | G14: 2236 | H14: 1912 | I14: 2172 | J14: 3527 | K14: 4404 | L14: 4849
B15: Receivables | C15: -22 | D15: -17 | E15: -18 | F15: -18 | G15: 0 | H15: -73 | I15: -147 | J15: -59 | K15: -5 | L15: -176
B16: Inventory | C16: -104 | D16: -28 | E16: -59 | F16: -239 | G16: 61 | H16: -302 | I16: -258 | J16: -146 | K16: -131 | L16: -154
B17: Payables | C17: 241 | D17: 110 | E17: 407 | F17: 62 | G17: -235 | H17: 495 | I17: 283 | J17: 22 | K17: 304 | L17: 440
B18: Loans Advances | C18: -12 | D18: 6 | E18: 0 | F18: -1 | G18: 1 | H18: 0 | I18: 0 | J18: 0 | K18: 0 | L18: 0
B19: Other WC items | C19: 160 | D19: 92 | E19: 109 | F19: -262 | G19: 259 | H19: 115 | I19: -10 | J19: 249 | K19: 220 | L19: 101
B20: Working capital changes | C20: 263 | D20: 163 | E20: 438 | F20: -457 | G20: 86 | H20: 235 | I20: -131 | J20: 66 | K20: 388 | L20: 211
B21: Direct taxes | C21: -519 | D21: -652 | E21: -807 | F21: -908 | G21: -628 | H21: -457 | I21: -514 | J21: -770 | K21: -1068 | L21: -1080
B22: Cash from Investing Activity - | C22: -1001 | D22: -1744 | E22: -2145 | F22: -660 | G22: -1508 | H22: -1625 | I22: -983 | J22: -2397 | K22: -2834 | L22: -2461
B23: Fixed assets purchased | C23: -510 | D23: -548 | E23: -748 | F23: -792 | G23: -546 | H23: -532 | I23: -641 | J23: -682 | K23: -819 | L23: -1039
B24: Fixed assets sold | C24: 1 | D24: 1 | E24: 3 | F24: 2 | G24: 1 | H24: 17 | I24: 2 | J24: 9 | K24: 4 | L24: 11
... B39: Net Cash Flow | C39: -4 | D39: -10 | E39: 75 | F39: 623 | G39: -673 | H39: 51 | I39: -50 | J39: 8 | K39: 45 | L39: 121

Sheet Beta Calculation
D2: =data!C23 -> Eicher Motors Limited is an Indian multinational automotive company that manufactures motorcycles and commercial vehicles, headquartered in New Delhi. Eicher is the parent company of Royal Enfield, a manufacturer of middleweight motorcycles. It also manufactures Eicher branded trucks and buses, under a joint venture with Volvo Group.
B8: ="Beta Calculation - " &'Data Sheet'!B1 -> Beta Calculation - EICHER MOTORS LTD
B9: ='Data Sheet'!B1 -> EICHER MOTORS LTD | F9: Niffty 50 | I9: Beta Drifting
B10: Date | C10: Price | D10: Weekly Retrun | F10: Price | G10: weekly return | M10: beta | N10: =O41 -> 1.0966639
B11: 45690 | C11: 5372.55 | F11: 23559.95
B12: 45697 | C12: 4703.35 | D12: =C12/C11-1 -> -0.1245591 | F12: 22929.25 | G12: =F12/F11-1 -> -0.026770006 | I12: leaverd Raw Beta | K12: =N10 -> 1.0966639
B13: 45704 | C13: 4962.45 | D13: =C13/C12-1 -> 0.055088394 | F13: 22795.9 | G13: =F13/F12-1 -> -0.0058157157 | I13: Raw beta weight | K13: 0.75
B14: 45711 | C14: 4773.6 | D14: =C14/C13-1 -> -0.038055799 | F14: 22124.7 | G14: =F14/F13-1 -> -0.029443891
B15: 45718 | C15: 5100.7 | D15: =C15/C14-1 -> 0.068522708 | F15: 22552.5 | G15: =F15/F14-1 -> 0.019335855 | I15: Market Beta | K15: 1
B16: 45725 | C16: 5015.25 | D16: =C16/C15-1 -> -0.016752603 | F16: 22397.2 | G16: =F16/F15-1 -> -0.0068861545 | I16: Market Beta Weight | K16: 0.25
B17: 45732 | C17: 5305.95 | D17: =C17/C16-1 -> 0.057963212 | F17: 23350.4 | G17: =F17/F16-1 -> 0.042558891
B18: 45739 | C18: 5347.7 | D18: =C18/C17-1 -> 0.007868525 | F18: 23519.35 | G18: =F18/F17-1 -> 0.0072354221
B19: 45746 | C19: 5247.9 | D19: =C19/C18-1 -> -0.018662229 | F19: 22904.45 | G19: =F19/F18-1 -> -0.02614443 | I19: Adujsted Beta | K19: =(K12*K13)+(K15*K16) -> 1.0724979
B20: 45753 | C20: 5350.9 | D20: =C20/C19-1 -> 0.019626898 | F20: 22828.55 | G20: =F20/F19-1 -> -0.0033137665
B21: 45760 | C21: 5678.5 | D21: =C21/C20-1 -> 0.061223346 | F21: 23851.65 | G21: =F21/F20-1 -> 0.044816688
B22: 45767 | C22: 5575.5 | D22: =C22/C21-1 -> -0.018138593 | F22: 24039.35 | G22: =F22/F21-1 -> 0.0078694765
B23: 45774 | C23: 5437.5 | D23: =C23/C22-1 -> -0.024751143 | F23: 24346.7 | G23: =F23/F22-1 -> 0.012785287
B24: 45781 | C24: 5324 | D24: =C24/C23-1 -> -0.020873563 | F24: 24008 | G24: =F24/F23-1 -> -0.013911536 | N24: SUMMARY OUTPUT
B25: 45788 | C25: 5509.5 | D25: =C25/C24-1 -> 0.034842224 | F25: 25019.8 | G25: =F25/F24-1 -> 0.042144285
B26: 45795 | C26: 5400 | D26: =C26/C25-1 -> -0.019874762 | F26: 24853.15 | G26: =F26/F25-1 -> -0.0066607247 | N26: Regression Statistics
B27: 45802 | C27: 5333.5 | D27: =C27/C26-1 -> -0.012314815 | F27: 24750.7 | G27: =F27/F26-1 -> -0.0041222139 | N27: Multiple R | O27: 0.53119241
B28: 45809 | C28: 5394 | D28: =C28/C27-1 -> 0.011343396 | F28: 25003.05 | G28: =F28/F27-1 -> 0.010195671 | N28: R Square | O28: 0.28216538
B29: 45816 | C29: 5319 | D29: =C29/C28-1 -> -0.013904338 | F29: 24718.6 | G29: =F29/F28-1 -> -0.011376612 | N29: Adjusted R Square | O29: 0.26751569
B30: 45823 | C30: 5525 | D30: =C30/C29-1 -> 0.038729084 | F30: 25112.4 | G30: =F30/F29-1 -> 0.015931323 | N30: Standard Error | O30: 0.029910688
B31: 45830 | C31: 5660 | D31: =C31/C30-1 -> 0.024434389 | F31: 25637.8 | G31: =F31/F30-1 -> 0.020921935 | N31: Observations | O31: 51
B32: 45837 | C32: 5629 | D32: =C32/C31-1 -> -0.0054770318 | F32: 25461 | G32: =F32/F31-1 -> -0.0068960675
B33: 45844 | C33: 5612.5 | D33: =C33/C32-1 -> -0.0029312489 | F33: 25149.85 | G33: =F33/F32-1 -> -0.012220651 | N33: ANOVA
B34: 45851 | C34: 5627.5 | D34: =C34/C33-1 -> 0.0026726058 | F34: 24968.4 | G34: =F34/F33-1 -> -0.0072147548 | O34: df | P34: SS | Q34: MS | R34: F | S34: Significance F
B35: 45858 | C35: 5433 | D35: =C35/C34-1 -> -0.034562417 | F35: 24837 | G35: =F35/F34-1 -> -0.005262652 | N35: Regression | O35: 1 | P35: 0.017231703 | Q35: 0.017231703 | R35: 19.260848 | S35: 6.0595237e-05
B36: 45865 | C36: 5528 | D36: =C36/C35-1 -> 0.017485735 | F36: 24565.35 | G36: =F36/F35-1 -> -0.010937311 | N36: Residual | O36: 49 | P36: 0.043837813 | Q36: 0.00089464925
B37: 45872 | C37: 5663 | D37: =C37/C36-1 -> 0.024421129 | F37: 24363.3 | G37: =F37/F36-1 -> -0.0082249998 | N37: Total | O37: 50 | P37: 0.061069517
B38: 45879 | C38: 5764 | D38: =C38/C37-1 -> 0.01783507 | F38: 24631.3 | G38: =F38/F37-1 -> 0.011000152
B39: 45886 | C39: 5924.5 | D39: =C39/C38-1 -> 0.027845246 | F39: 24870.1 | G39: =F39/F38-1 -> 0.0096949816 | O39: Coefficients | P39: Standard Error | Q39: t Stat | R39: P-value | S39: Lower 95% | T39: Upper 95% | U39: Lower 95.0% | V39: Upper 95.0%
B40: 45893 | C40: 6103 | D40: =C40/C39-1 -> 0.030129125 | F40: 24426.85 | G40: =F40/F39-1 -> -0.017822606 | N40: Intercept | O40: 0.0046356036 | P40: 0.0042038401 | Q40: 1.1027069 | R40: 0.27554104 | S40: -0.0038123295 | T40: 0.013083537 | U40: -0.0038123295 | V40: 0.013083537
B41: 45900 | C41: 6580.5 | D41: =C41/C40-1 -> 0.07824021 | F41: 24741 | G41: =F41/F40-1 -> 0.012860848 | N41: X Variable 1 | O41: 1.0966639 | P41: 0.24988251 | Q41: 4.3887183 | R41: 6.0595237e-05 | S41: 0.59450622 | T41: 1.5988216 | U41: 0.59450622 | V41: 1.5988216
B42: 45907 | C42: 6875 | D42: =C42/C41-1 -> 0.044753438 | F42: 25114 | G42: =F42/F41-1 -> 0.015076189
B43: 45914 | C43: 6973.5 | D43: =C43/C42-1 -> 0.014327273 | F43: 25327.05 | G43: =F43/F42-1 -> 0.0084833161
B44: 45921 | C44: 7047 | D44: =C44/C43-1 -> 0.010539901 | F44: 24654.7 | G44: =F44/F43-1 -> -0.026546716
B45: 45928 | C45: 6941 | D45: =C45/C44-1 -> -0.015041862 | F45: 24894.25 | G45: =F45/F44-1 -> 0.0097162002
B46: 45935 | C46: 6965 | D46: =C46/C45-1 -> 0.003457715 | F46: 25285.35 | G46: =F46/F45-1 -> 0.015710455
B47: 45942 | C47: 7042.5 | D47: =C47/C46-1 -> 0.011127064 | F47: 25709.85 | G47: =F47/F46-1 -> 0.016788377
B48: 45949 | C48: 6840 | D48: =C48/C47-1 -> -0.028753994 | F48: 25795.15 | G48: =F48/F47-1 -> 0.0033177945
B49: 45956 | C49: 7007 | D49: =C49/C48-1 -> 0.024415205 | F49: 25722.1 | G49: =F49/F48-1 -> -0.0028319277
B50: 45963 | C50: 6886 | D50: =C50/C49-1 -> -0.017268446 | F50: 25492.3 | G50: =F50/F49-1 -> -0.0089339517
B51: 45970 | C51: 6695 | D51: =C51/C50-1 -> -0.027737438 | F51: 25910.05 | G51: =F51/F50-1 -> 0.016387301
B52: 45977 | C52: 7134.5 | D52: =C52/C51-1 -> 0.065646004 | F52: 26068.15 | G52: =F52/F51-1 -> 0.0061018794
B53: 45984 | C53: 7053.5 | D53: =C53/C52-1 -> -0.011353283 | F53: 26202.95 | G53: =F53/F52-1 -> 0.0051710612
... B62: 46047 | C62: 7147.5 | D62: =C62/C61-1 -> 0.025025097 | F62: 25178.9 | G62: =F62/F61-1 -> 0.005199881

Sheet Data Room
D2: =data!C23 -> Eicher Motors Limited is an Indian multinational automotive company that manufactures motorcycles and commercial vehicles, headquartered in New Delhi. Eicher is the parent company of Royal Enfield, a manufacturer of middleweight motorcycles. It also manufactures Eicher branded trucks and buses, under a joint venture with Volvo Group.
B8: ="Data Room - "&'Data Sheet'!B1 -> Data Room - EICHER MOTORS LTD
B9: Particular | C9: 41609 | D9: 41974 | E9: 42430 | F9: 42795 | G9: 43160 | H9: 43525 | I9: 43891 | J9: 44256 | K9: 44621 | L9: 44986 | M9: 45352 | N9: 45717
B10: Equity Capital | C10: 27 | D10: 27 | E10: 27 | F10: 27 | G10: 27 | H10: 27 | I10: 27 | J10: 27 | K10: 27 | L10: 27 | M10: 27 | N10: 27
B11: Reserves | C11: 2028 | D11: 2489 | E11: 3626 | F11: 5318 | G11: 7003 | H11: 8891 | I11: 9954 | J11: 11411 | K11: 12581 | L11: 14963 | M11: 18018 | N11: 21269
B13: Borrowings -
B14: Long term Borrowings | D14: 0 | E14: 0 | F14: 0 | G14: 0 | H14: 0 | I14: 0 | J14: 0 | K14: 0 | L14: 63 | M14: 163 | N14: 184
B15: Short term Borrowings | D15: 58 | E15: 23 | F15: 112 | G15: 151 | H15: 187 | I15: 144 | J15: 157 | K15: 59 | L15: 133 | M15: 112 | N15: 82
B16: Lease Liabilities | D16: 0 | E16: 0 | F16: 0 | G16: 0 | H16: 0 | I16: 105 | J16: 62 | K16: 49 | L16: 93 | M16: 144 | N16: 192
B18: Other Liabilities -
B19: Non controlling int | D19: 1085 | E19: 0 | F19: 0 | G19: 0 | H19: 0 | I19: 0 | J19: 0 | K19: 0 | L19: 0 | M19: 0 | N19: 0
B20: Trade Payables | D20: 1513 | E20: 723 | F20: 765 | G20: 1172 | H20: 1234 | I20: 1008 | J20: 1513 | K20: 1788 | L20: 1810 | M20: 2090 | N20: 2530
B21: Advance from Customers | D21: 246 | E21: 242 | F21: 292 | G21: 141 | H21: 93 | I21: 61 | J21: 137 | K21: 148 | L21: 126 | M21: 0 | N21: 0
B22: Other liability items | D22: 985 | E22: 298 | F22: 495 | G22: 1029 | H22: 954 | I22: 1151 | J22: 1251 | K22: 1488 | L22: 1982 | M22: 2560 | N22: 2890
B23: Total Liabilities | C23: 5337 | D23: 6403 | E23: 4939 | F23: 7009 | G23: 9522 | H23: 11387 | I23: 12450 | J23: 14559 | K23: 16140 | L23: 19198 | M23: 23115 | N23: 27174
B25: Fixed Assets -
B26: Land | D26: 250 | E26: 86 | F26: 86 | G26: 86 | H26: 86 | I26: 182 | J26: 232 | K26: 230 | L26: 230 | M26: 227 | N26: 226
B27: Building | D27: 406 | E27: 177 | F27: 230 | G27: 484 | H27: 644 | I27: 871 | J27: 866 | K27: 867 | L27: 1051 | M27: 1086 | N27: 1396
B28: Plant Machinery | D28: 1726 | E28: 663 | F28: 795 | G28: 1303 | H28: 1548 | I28: 1928 | J28: 2088 | K28: 2336 | L28: 2598 | M28: 2744 | N28: 3055
B29: Equipments | D29: 121 | E29: 51 | F29: 68 | G29: 110 | H29: 140 | I29: 188 | J29: 204 | K29: 226 | L29: 266 | M29: 231 | N29: 273
B30: Furniture n fittings | D30: 86 | E30: 11 | F30: 14 | G30: 21 | H30: 28 | I30: 34 | J30: 38 | K30: 37 | L30: 39 | M30: 42 | N30: 44
B31: Vehicles | D31: 78 | E31: 19 | F31: 30 | G31: 48 | H31: 64 | I31: 81 | J31: 97 | K31: 122 | L31: 137 | M31: 180 | N31: 224
B32: Intangible Assets | D32: 22 | E32: 0 | F32: 0 | G32: 0 | H32: 0 | I32: 0 | J32: 0 | K32: 0 | L32: 0 | M32: 0 | N32: 0
B33: Other fixed assets | D33: 446 | E33: 53 | F33: 72 | G33: 93 | H33: 258 | I33: 301 | J33: 523 | K33: 588 | L33: 820 | M33: 1177 | N33: 1501
B34: Gross Block | D34: 3137 | E34: 1061 | F34: 1295 | G34: 2144 | H34: 2767 | I34: 3585 | J34: 4049 | K34: 4405 | L34: 5142 | M34: 5687 | N34: 6718
B35: Accumulated Depreciation | D35: 828 | E35: 271 | F35: 422 | G35: 643 | H35: 893 | I35: 1208 | J35: 1616 | K35: 1981 | L35: 2452 | M35: 2772 | N35: 3245
B36: Net Block | D36: =D34-D35 -> 2309 | E36: =E34-E35 -> 790 | F36: =F34-F35 -> 873 | G36: =G34-G35 -> 1501 | H36: =H34-H35 -> 1874 | I36: =I34-I35 -> 2377 | J36: =J34-J35 -> 2433 | K36: =K34-K35 -> 2424 | ... N36: =N34-N35 -> 3473
B38: CWIP | C38: 464 | D38: 419 | E38: 94 | F38: 374 | G38: 333 | H38: 450 | I38: 312 | J38: 314 | K38: 505 | L38: 472 | M38: 555 | N38: 491
B39: Investments | C39: 825 | D39: 1078 | E39: 3388 | F39: 4987 | G39: 5581 | H39: 4923 | I39: 5749 | J39: 3902 | K39: 7721 | L39: 12321 | M39: 13527 | N39: 14791
B41: Other Assets -
B42: Inventories | D42: 646 | E42: 308 | F42: 336 | G42: 395 | H42: 633 | I42: 572 | J42: 875 | K42: 1132 | L42: 1278 | M42: 1410 | N42: 1564
B43: Trade receivables | D43: 562 | E43: 33 | F43: 50 | G43: 68 | H43: 84 | I43: 87 | J43: 158 | K43: 302 | L43: 369 | M43: 374 | N43: 550
B44: Cash Equivalents | D44: 353 | E44: 49 | F44: 25 | G44: 1212 | H44: 2965 | I44: 2951 | J44: 5830 | K44: 2722 | L44: 766 | M44: 146 | N44: 263
B45: Loans n Advances | D45: 88 | E45: 39 | F45: 39 | G45: 64 | H45: 82 | I45: 99 | J45: 594 | K45: 867 | L45: 835 | M45: 680 | N45: 725
B46: Other asset items | D46: 949 | E46: 237 | F46: 326 | G46: 368 | H46: 375 | I46: 303 | J46: 452 | K46: 466 | L46: 467 | M46: 3509 | N46: 5317
B47: Total Assets | C47: 5337 | D47: 6403 | E47: 4939 | F47: 7009 | G47: 9522 | H47: 11387 | I47: 12450 | J47: 14559 | K47: 16140 | L47: 19198 | M47: 23115 | N47: 27174

Sheet Intrisc Value
D2: =data!C23 -> Eicher Motors Limited is an Indian multinational automotive company that manufactures motorcycles and commercial vehicles, headquartered in New Delhi. Eicher is the parent company of Royal Enfield, a manufacturer of middleweight motorcycles. It also manufactures Eicher branded trucks and buses, under a joint venture with Volvo Group.
B9: ="Calculation of Intersic Value - "&'Data Sheet'!B1 -> Calculation of Intersic Value - EICHER MOTORS LTD
A11: # | B11: Calculation of ROIC | E11: 43891 | F11: 44256 | G11: 44621 | H11: 44986 | I11: 45352 | J11: 45717
B13: Current Assests
B14: ='Data Room'!B42 -> Inventories | E14: =IFERROR('Data Room'!I42,0) -> 572 | F14: =IFERROR('Data Room'!J42,0) -> 875 | G14: =IFERROR('Data Room'!K42,0) -> 1132 | H14: =IFERROR('Data Room'!L42,0) -> 1278 | I14: =IFERROR('Data Room'!M42,0) -> 1410 | J14: =IFERROR('Data Room'!N42,0) -> 1564
B15: ='Data Room'!B43 -> Trade receivables | E15: =IFERROR('Data Room'!I43,0) -> 87 | F15: =IFERROR('Data Room'!J43,0) -> 158 | G15: =IFERROR('Data Room'!K43,0) -> 302 | H15: =IFERROR('Data Room'!L43,0) -> 369 | I15: =IFERROR('Data Room'!M43,0) -> 374 | J15: =IFERROR('Data Room'!N43,0) -> 550
B16: ='Data Room'!B44 -> Cash Equivalents | E16: =IFERROR('Data Room'!I44,0) -> 2951 | F16: =IFERROR('Data Room'!J44,0) -> 5830 | G16: =IFERROR('Data Room'!K44,0) -> 2722 | H16: =IFERROR('Data Room'!L44,0) -> 766 | I16: =IFERROR('Data Room'!M44,0) -> 146 | J16: =IFERROR('Data Room'!N44,0) -> 263
B17: ='Data Room'!B45 -> Loans n Advances | E17: =IFERROR('Data Room'!I45,0) -> 99 | F17: =IFERROR('Data Room'!J45,0) -> 594 | G17: =IFERROR('Data Room'!K45,0) -> 867 | H17: =IFERROR('Data Room'!L45,0) -> 835 | I17: =IFERROR('Data Room'!M45,0) -> 680 | J17: =IFERROR('Data Room'!N45,0) -> 725
B18: ='Data Room'!B46 -> Other asset items | E18: =IFERROR('Data Room'!I46,0) -> 303 | F18: =IFERROR('Data Room'!J46,0) -> 452 | G18: =IFERROR('Data Room'!K46,0) -> 466 | H18: =IFERROR('Data Room'!L46,0) -> 467 | I18: =IFERROR('Data Room'!M46,0) -> 3509 | J18: =IFERROR('Data Room'!N46,0) -> 5317
A19: # | B19: Total Current Assest | E19: =SUM(E14:E18) -> 4012 | F19: =SUM(F14:F18) -> 7909 | G19: =SUM(G14:G18) -> 5489 | H19: =SUM(H14:H18) -> 3715 | I19: =SUM(I14:I18) -> 6119 | J19: =SUM(J14:J18) -> 8419
B21: Current liabities
B22: ='Data Room'!B20 -> Trade Payables | E22: =IFERROR('Data Room'!I20,0) -> 1008 | F22: =IFERROR('Data Room'!J20,0) -> 1513 | G22: =IFERROR('Data Room'!K20,0) -> 1788 | H22: =IFERROR('Data Room'!L20,0) -> 1810 | I22: =IFERROR('Data Room'!M20,0) -> 2090 | J22: =IFERROR('Data Room'!N20,0) -> 2530
B23: ='Data Room'!B21 -> Advance from Customers | E23: =IFERROR('Data Room'!I21,0) -> 61 | F23: =IFERROR('Data Room'!J21,0) -> 137 | G23: =IFERROR('Data Room'!K21,0) -> 148 | H23: =IFERROR('Data Room'!L21,0) -> 126 | I23: =IFERROR('Data Room'!M21,0) -> 0 | J23: =IFERROR('Data Room'!N21,0) -> 0
B24: ='Data Room'!B22 -> Other liability items | E24: =IFERROR('Data Room'!I22,0) -> 1151 | F24: =IFERROR('Data Room'!J22,0) -> 1251 | G24: =IFERROR('Data Room'!K22,0) -> 1488 | H24: =IFERROR('Data Room'!L22,0) -> 1982 | I24: =IFERROR('Data Room'!M22,0) -> 2560 | J24: =IFERROR('Data Room'!N22,0) -> 2890
B25: ='Data Room'!B23 -> Total Liabilities | E25: =IFERROR('Data Room'!I23,0) -> 12450 | F25: =IFERROR('Data Room'!J23,0) -> 14559 | G25: =IFERROR('Data Room'!K23,0) -> 16140 | H25: =IFERROR('Data Room'!L23,0) -> 19198 | I25: =IFERROR('Data Room'!M23,0) -> 23115 | J25: =IFERROR('Data Room'!N23,0) -> 27174
B26: Total Current Liabities | E26: =IFERROR(SUM(E22:E25),0) -> 14670 | F26: =IFERROR(SUM(F22:F25),0) -> 17460 | G26: =IFERROR(SUM(G22:G25),0) -> 19564 | H26: =IFERROR(SUM(H22:H25),0) -> 23116 | I26: =IFERROR(SUM(I22:I25),0) -> 27765 | J26: =IFERROR(SUM(J22:J25),0) -> 32594
A28: # | B28: Net Working Capital | E28: =E19-E26 -> -10658 | F28: =F19-F26 -> -9551 | G28: =G19-G26 -> -14075 | H28: =H19-H26 -> -19401 | I28: =I19-I26 -> -21646 | J28: =J19-J26 -> -24175
B30: Non Current Assests
B31: ='Data Room'!B26 -> Land | E31: =IFERROR('Data Room'!I26,0) -> 182 | F31: =IFERROR('Data Room'!J26,0) -> 232 | G31: =IFERROR('Data Room'!K26,0) -> 230 | H31: =IFERROR('Data Room'!L26,0) -> 230 | I31: =IFERROR('Data Room'!M26,0) -> 227 | J31: =IFERROR('Data Room'!N26,0) -> 226
B32: ='Data Room'!B27 -> Building | E32: =IFERROR('Data Room'!I27,0) -> 871 | F32: =IFERROR('Data Room'!J27,0) -> 866 | G32: =IFERROR('Data Room'!K27,0) -> 867 | H32: =IFERROR('Data Room'!L27,0) -> 1051 | I32: =IFERROR('Data Room'!M27,0) -> 1086 | J32: =IFERROR('Data Room'!N27,0) -> 1396
B33: ='Data Room'!B28 -> Plant Machinery | E33: =IFERROR('Data Room'!I28,0) -> 1928 | F33: =IFERROR('Data Room'!J28,0) -> 2088 | G33: =IFERROR('Data Room'!K28,0) -> 2336 | H33: =IFERROR('Data Room'!L28,0) -> 2598 | I33: =IFERROR('Data Room'!M28,0) -> 2744 | J33: =IFERROR('Data Room'!N28,0) -> 3055
B34: ='Data Room'!B29 -> Equipments | E34: =IFERROR('Data Room'!I29,0) -> 188 | F34: =IFERROR('Data Room'!J29,0) -> 204 | G34: =IFERROR('Data Room'!K29,0) -> 226 | H34: =IFERROR('Data Room'!L29,0) -> 266 | I34: =IFERROR('Data Room'!M29,0) -> 231 | J34: =IFERROR('Data Room'!N29,0) -> 273
B35: ='Data Room'!B30 -> Furniture n fittings | E35: =IFERROR('Data Room'!I30,0) -> 34 | F35: =IFERROR('Data Room'!J30,0) -> 38 | G35: =IFERROR('Data Room'!K30,0) -> 37 | H35: =IFERROR('Data Room'!L30,0) -> 39 | I35: =IFERROR('Data Room'!M30,0) -> 42 | J35: =IFERROR('Data Room'!N30,0) -> 44
B36: ='Data Room'!B31 -> Vehicles | E36: =IFERROR('Data Room'!I31,0) -> 81 | F36: =IFERROR('Data Room'!J31,0) -> 97 | G36: =IFERROR('Data Room'!K31,0) -> 122 | H36: =IFERROR('Data Room'!L31,0) -> 137 | I36: =IFERROR('Data Room'!M31,0) -> 180 | J36: =IFERROR('Data Room'!N31,0) -> 224
B37: ='Data Room'!B32 -> Intangible Assets | E37: =IFERROR('Data Room'!I32,0) -> 0 | F37: =IFERROR('Data Room'!J32,0) -> 0 | G37: =IFERROR('Data Room'!K32,0) -> 0 | H37: =IFERROR('Data Room'!L32,0) -> 0 | I37: =IFERROR('Data Room'!M32,0) -> 0 | J37: =IFERROR('Data Room'!N32,0) -> 0
B38: ='Data Room'!B33 -> Other fixed assets | E38: =IFERROR('Data Room'!I33,0) -> 301 | F38: =IFERROR('Data Room'!J33,0) -> 523 | G38: =IFERROR('Data Room'!K33,0) -> 588 | H38: =IFERROR('Data Room'!L33,0) -> 820 | I38: =IFERROR('Data Room'!M33,0) -> 1177 | J38: =IFERROR('Data Room'!N33,0) -> 1501
B40: Gross Block | E40: =IFERROR(SUM(E31:E38),0) -> 3585 | F40: =IFERROR(SUM(F31:F38),0) -> 4048 | G40: =IFERROR(SUM(G31:G38),0) -> 4406 | H40: =IFERROR(SUM(H31:H38),0) -> 5141 | I40: =IFERROR(SUM(I31:I38),0) -> 5687 | J40: =IFERROR(SUM(J31:J38),0) -> 6719
B41: Accumalted Dpn | E41: =-'Data Room'!I35 -> -1208 | F41: =-'Data Room'!J35 -> -1616 | G41: =-'Data Room'!K35 -> -1981 | H41: =-'Data Room'!L35 -> -2452 | I41: =-'Data Room'!M35 -> -2772 | J41: =-'Data Room'!N35 -> -3245
B42: Net non Current Assests | E42: =E40+E41 -> 2377 | F42: =F40+F41 -> 2432 | G42: =G40+G41 -> 2425 | H42: =H40+H41 -> 2689 | I42: =I40+I41 -> 2915 | J42: =J40+J41 -> 3474
A44: # | B44: Invested Capital | E44: =E42+E28 -> -8281 | F44: =F42+F28 -> -7119 | G44: =G42+G28 -> -11650 | H44: =H42+H28 -> -16712 | I44: =I42+I28 -> -18731 | J44: =J42+J28 -> -20701
B45: EBIT | E45: ='Historical IFS'!H33+'Historical IFS'!H27 -> 1126.5464 | F45: ='Historical IFS'!I33+'Historical IFS'!I27 -> 1577.0043 | G45: ='Historical IFS'!J33+'Historical IFS'!J27 -> 2856.2216 | H45: ='Historical IFS'!K33+'Historical IFS'!K27 -> 3534.7008 | I45: ='Historical IFS'!L33+'Historical IFS'!L27 -> 3829.6885 | J45: ='Historical IFS'!M33+'Historical IFS'!M27 -> 62.99
A47: # | B47: ROIC | E47: =E45/E44 -> -0.1360399 | F47: =F45/F44 -> -0.22152048 | G47: =G45/G44 -> -0.24516924 | H47: =H45/H44 -> -0.21150675 | I47: =I45/I44 -> -0.20445724 | J47: =J45/J44 -> -0.0030428482
B49: Calculation or reinvestment rate | E49: 43891 | F49: 44256 | G49: 44621 | H49: 44986 | I49: 45352 | J49: 45717
B51: Net Capex | E51: =-SUM('Forcasting data '!G23:G24) -> 545 | F51: =-SUM('Forcasting data '!H23:H24) -> 515 | G51: =-SUM('Forcasting data '!I23:I24) -> 639 | H51: =-SUM('Forcasting data '!J23:J24) -> 673 | I51: =-SUM('Forcasting data '!K23:K24) -> 815 | J51: =-SUM('Forcasting data '!L23:L24) -> 1028
B52: Change in Working Capital | F52: =F28-E28 -> 1107 | G52: =G28-F28 -> -4524 | H52: =H28-G28 -> -5326 | I52: =I28-H28 -> -2245 | J52: =J28-I28 -> -2529
B54: EBIT | E54: =E45 -> 1126.5464 | F54: =F45 -> 1577.0043 | G54: =G45 -> 2856.2216 | H54: =H45 -> 3534.7008 | I54: =I45 -> 3829.6885 | J54: =J45 -> 62.99
B55: Marginal Tax Rate | E55: 0.25 | F55: 0.25 | G55: 0.25 | H55: 0.25 | I55: 0.25 | J55: 0.25
B56: EBIT(1-T) | E56: =E54*E55 -> 281.63661 | F56: =F54*F55 -> 394.25107 | G56: =G54*G55 -> 714.05541 | H56: =H54*H55 -> 883.6752 | I56: =I54*I55 -> 957.42212 | J56: =J54*J55 -> 15.7475
B58: Reinvestment | F58: =SUM(F51:F52) -> 1622 | G58: =SUM(G51:G52) -> -3885 | H58: =SUM(H51:H52) -> -4653 | I58: =SUM(I51:I52) -> -1430 | J58: =SUM(J51:J52) -> -1501
B60: Re investment rate | F60: =F58/F56 -> 4.1141296 | G60: =G58/G56 -> -5.4407543 | H60: =H58/H56 -> -5.2655093 | I60: =I58/I56 -> -1.4935941 | J60: =J58/J56 -> -95.316717
I62: 4 year Average | J62: =AVERAGE(F60:J60) -> -20.680489
I63: 4 year Median | J63: =MEDIAN(F60:J60) -> -5.2655093
B65: Calculation of growth rate | E65: 43891 | F65: 44256 | G65: 44621 | H65: 44986 | I65: 45352 | J65: 45717
B67: Reinvestment rate | F67: =F60 -> 4.1141296 | G67: =G60 -> -5.4407543 | H67: =H60 -> -5.2655093 | I67: =I60 -> -1.4935941 | J67: =J60 -> -95.316717
B68: Roic | F68: =F47 -> -0.22152048 | G68: =G47 -> -0.24516924 | H68: =H47 -> -0.21150675 | I68: =I47 -> -0.20445724 | J68: =J47 -> -0.0030428482
B70: Intersic Growth | F70: =F67*F68 -> -0.91136396 | G70: =G67*G68 -> 1.3339056 | H70: =H67*H68 -> 1.1136908 | I70: =I67*I68 -> 0.30537611 | J70: =J67*J68 -> 0.2900343
I73: 4 year Average | J73: =AVERAGE(F70:J70) -> 0.42632856
I74: 4 year Median | J74: =MEDIAN(F70:J70) -> 0.30537611

Sheet DCF
D2: =data!C23 -> Eicher Motors Limited is an Indian multinational automotive company that manufactures motorcycles and commercial vehicles, headquartered in New Delhi. Eicher is the parent company of Royal Enfield, a manufacturer of middleweight motorcycles. It also manufactures Eicher branded trucks and buses, under a joint venture with Volvo Group.
B9: ="PV of FCFF - "&'Data Sheet'!B1 -> PV of FCFF - EICHER MOTORS LTD
B11: Calculation of PV of FCFF | D11: ='Intrisc Value'!J11 -> 45717 | E11: =D11+366 -> 46083 | F11: =E11+366 -> 46449 | G11: =F11+366 -> 46815 | H11: =G11+366 -> 47181 | I11: =H11+366 -> 47547
B13: EBIT | D13: =IFERROR('Data Sheet'!K32-'Data Sheet'!K26,0) -> 5987.41 | E13: =D$13*(1+$C$28) -> 7815.822 | F13: =E$13*(1+$C$28) -> 10202.587 | G13: =F$13*(1+$C$28) -> 13318.214 | H13: =G$13*(1+$C$28) -> 17385.278 | I13: =H$13*(1+$C$28) -> 22694.327
B15: Tax Rate | D15: 0.25 | E15: 0.25 | F15: 0.25 | G15: 0.25 | H15: 0.25 | I15: 0.25
B17: EBIT (1-Tax rate) | D17: =D13*(1-D15) -> 4490.5575 | E17: =D17*(1+$C$28) -> 5861.8665 | F17: =E17*(1+$C$28) -> 7651.9405 | G17: =F17*(1+$C$28) -> 9988.6604 | H17: =G17*(1+$C$28) -> 13038.959 | I17: =H17*(1+$C$28) -> 17020.745
B19: Less: Reinvestement rate | D19: =40% -> 0.4 | E19: =40% -> 0.4 | F19: =40% -> 0.4 | G19: =40% -> 0.4 | H19: =40% -> 0.4 | I19: =40% -> 0.4
B21: Free cash flow to firm FCFF | D21: =D17*(1-D19) -> 2694.3345 | E21: =E17*(1-E19) -> 3517.1199 | F21: =F17*(1-F19) -> 4591.1643 | G21: =G17*(1-G19) -> 5993.1962 | H21: =H17*(1-H19) -> 7823.3752 | I21: =I17*(1-I19) -> 10212.447
B23: Mid Year Convention | E23: 0.5 | F23: =E23+1 -> 1.5 | G23: =F23+1 -> 2.5 | H23: =G23+1 -> 3.5 | I23: =H23+1 -> 4.5
B24: Discouting factor | E24: =1/(1+$C$30)^E23 -> 0.94146836 | F24: =1/(1+$C$30)^F23 -> 0.8344824 | G24: =1/(1+$C$30)^G23 -> 0.73965404 | H24: =1/(1+$C$30)^H23 -> 0.65560173 | I24: =1/(1+$C$30)^I23 -> 0.5811009
B26: PV of FCFF | E26: =E21*E24 -> 3311.2571 | F26: =F21*F24 -> 3831.2458 | G26: =G21*G24 -> 4432.8918 | H26: =H21*H24 -> 5129.0183 | I26: =I21*I24 -> 5934.4622
B28: expected growth | C28: ='Intrisc Value'!J74 -> 0.30537611
B29: terminal growth | C29: 0.062
B30: WACC | C30: =WACC!J49 -> 0.12820637
B32: Calcluation of terminal value | E32: senstive analysis
E33: =C38 -> 47104.797 | F33: 0.11 | G33: 0.1282 | H33: 0.13 | I33: 0.14
B34: FcF(n+1) | C34: =I21*C28 -> 3118.6374 | E34: 0.05 | F34: 51977.29 | G34: 39880.274 | H34: 38982.968 | I34: 34651.527
B35: WACC | C35: =C30 -> 0.12820637 | E35: 0.062 | F35: 64971.613 | G35: 47109.327 | H35: 45862.315 | I35: 39982.531
B36: Terminal growth rate | C36: =C29 -> 0.062 | E36: 0.07 | F36: 77965.936 | G36: 53584.835 | H36: 51977.29 | I36: 44551.963
E37: 0.08 | F37: 103954.58 | G37: 64702.021 | H37: 62372.748 | I37: 51977.29
B38: Terminal Value | C38: =C34/(C35-C36) -> 47104.797
B41: Calcluation of Equity Value per share
E42: Share price annalysis
B43: PV of FCFF | C43: =SUM(E26:I26) -> 22638.875 | E43: =C54 -> 7122 | F43: 0.11 | G43: 0.1282 | H43: 0.13 | I43: 0.14
B44: PV of Terminal Value | C44: =C43*I24 -> 13155.471 | E44: 0.05 | F44: 7122 | G44: 7122 | H44: 7122 | I44: 7122
B45: Value of Operting Assests | C45: =SUM(C43,C44) -> 35794.346 | E45: 0.062 | F45: 7122 | G45: 7122 | H45: 7122 | I45: 7122
E46: 0.07 | F46: 7122 | G46: 7122 | H46: 7122 | I46: 7122
B47: Add: Cash | C47: ='Data Sheet'!K69 -> 263.01 | E47: 0.08 | F47: 7122 | G47: 7122 | H47: 7122 | I47: 7122
B48: less: Debt | C48: =SUM('Historical IFS'!L55:L56) -> 5877.92
B49: value of Equity | C49: =C45+C47-C48 -> 30179.436
B50: Number of share | C50: ='Data Sheet'!B6 -> 27.429924
B52: Equity Value Per share | C52: =C49/C50 -> 1100.2377
B54: Share price | C54: 7122
B55: Disciunt/Premimum | C55: =C54/C52-1 -> 5.4731468

Sheet Comps Value
D2: =data!C23 -> Eicher Motors Limited is an Indian multinational automotive company that manufactures motorcycles and commercial vehicles, headquartered in New Delhi. Eicher is the parent company of Royal Enfield, a manufacturer of middleweight motorcycles. It also manufactures Eicher branded trucks and buses, under a joint venture with Volvo Group.
B9: Comparble Company Valuvation
D11: Market data | J11: Market data | N11: Valution
B12: Company | C12: Ticker | D12: Share Price | E12: Shares Outstanding | F12: Equaity Value | G12: Net Debt | H12: Enterprice Value | J12: Revenue | K12: EBIDTA | L12: Net income | N12: EV/Revenue | O12: EV/EBIDTA | P12: P/E
B14: =data!C6 -> Eicher Motors | D14: =data!D6 -> 7209.5 | E14: =data!E6 -> 27.43 | F14: =D14*E14 -> 197756.58 | G14: =data!I6 -> 182.77 | H14: =F14+G14 -> 197939.35 | J14: =data!J6 -> 197939.35 | K14: =data!K6 -> 21427.66 | L14: =data!L6 -> 5774.7544 | N14: =$H14/J14 -> 1 | O14: =$H14/K14 -> 9.2375628 | P14: =F14/L14 -> 34.245021
B15: =data!C3 -> Maruti Suzuki | D15: =data!D3 -> 15059 | E15: =data!E3 -> 31.44 | F15: =D15*E15 -> 473454.96 | G15: =data!I3 -> -453 | H15: =F15+G15 -> 473001.96 | J15: =data!K3 -> 171773.6 | K15: =data!L3 -> 31486.101 | L15: =data!M3 -> 14931.6 | N15: =$H15/J15 -> 2.7536359 | O15: =$H15/K15 -> 15.022564 | P15: =F15/L15 -> 31.708254
B16: =data!C4 -> M & M | D16: =data!D4 -> 3572 | E16: =data!E4 -> 124.35 | F16: =D16*E16 -> 444178.2 | G16: =data!I4 -> 106094.49 | H16: =F16+G16 -> 550272.69 | J16: =data!K4 -> 175704.22 | K16: =data!L4 -> 25564.964 | L16: =data!M4 -> 15506.66 | N16: =$H16/J16 -> 3.1318126 | O16: =$H16/K16 -> 21.524485 | P16: =F16/L16 -> 28.64435
B17: =data!C5 -> Bajaj Auto | D17: =data!D5 -> 9647 | E17: =data!E5 -> 27.95 | F17: =D17*E17 -> 269633.65 | G17: =data!I5 -> 16845.64 | H17: =F17+G17 -> 286479.29 | J17: =data!K5 -> 57718.86 | K17: =data!L5 -> 12178.679 | L17: =data!M5 -> 8884.14 | N17: =$H17/J17 -> 4.9633567 | O17: =$H17/K17 -> 23.523017 | P17: =F17/L17 -> 30.35
B18: =data!C7 -> TVS Motor Co. | D18: =data!D7 -> 3712.7 | E18: =data!E7 -> 47.51 | F18: =D18*E18 -> 176390.38 | G18: =data!I7 -> 27203.05 | H18: =F18+G18 -> 203593.43 | J18: =data!K7 -> 52558.79 | K18: =data!L7 -> 13302.63 | L18: =data!M7 -> 3064.39 | N18: =$H18/J18 -> 3.8736323 | O18: =$H18/K18 -> 15.30475 | P18: =F18/L18 -> 57.561334
B19: =data!C8 -> Hyundai Motor I | D19: =data!D8 -> 2164.3 | E19: =data!E8 -> 81.25 | F19: =D19*E19 -> 175849.38 | G19: =data!I8 -> -7278.79 | H19: =F19+G19 -> 168570.59 | J19: =data!K8 -> 68100.58 | K19: =data!L8 -> 11760.97 | L19: =data!M8 -> 5683.48 | N19: =$H19/J19 -> 2.4753179 | O19: =$H19/K19 -> 14.333051 | P19: =F19/L19 -> 30.940441
B20: =data!C9 -> Tata Motors PVeh | D20: =data!D9 -> 374.15 | E20: =data!E9 -> 368.23 | F20: =D20*E20 -> 137773.25 | G20: =data!I9 -> 26424 | H20: =F20+G20 -> 164197.25 | J20: =data!K9 -> 349637 | K20: =data!L9 -> 20313.91 | L20: =data!M9 -> 85324 | N20: =$H20/J20 -> 0.46962208 | O20: =$H20/K20 -> 8.0829962 | P20: =F20/L20 -> 1.6147069
B21: =data!C10 -> Samvardh. Mothe. | D21: =data!D10 -> 120.99 | E21: =data!E10 -> 1055.44 | F21: =D21*E21 -> 127697.69 | G21: =data!I10 -> 13488.67 | H21: =F21+G21 -> 141186.36 | J21: =data!K10 -> 117367.72 | K21: =data!L10 -> 14588.808 | L21: =data!M10 -> 3551.45 | N21: =$H21/J21 -> 1.2029403 | O21: =$H21/K21 -> 9.6777173 | P21: =F21/L21 -> 35.956493 | S21: `
B22: =data!C11 -> Hero Motocorp | D22: =data!D11 -> 5766 | E22: =data!E11 -> 20.01 | F22: =D22*E22 -> 115377.66 | G22: =data!I11 -> 143.99 | H22: =F22+G22 -> 115521.65 | J22: =data!K11 -> 42175.84 | K22: =data!L11 -> 6195.6309 | L22: =data!M11 -> 5303.76 | N22: =$H22/J22 -> 2.739048 | O22: =$H22/K22 -> 18.645664 | P22: =F22/L22 -> 21.753937
B23: =data!C12 -> Bosch | D23: =data!D12 -> 36275 | E23: =data!E12 -> 2.95 | F23: =D23*E23 -> 107011.25 | G23: =data!I12 -> -398.6 | H23: =F23+G23 -> 106612.65 | J23: =data!K12 -> 18959.7 | K23: =data!L12 -> 5941.97 | L23: =data!M12 -> 2681.5 | N23: =$H23/J23 -> 5.623119 | O23: =$H23/K23 -> 17.942307 | P23: =F23/L23 -> 39.907235
B24: =data!C13 -> Bharat Forge | D24: =data!D13 -> 1573.2 | E24: =data!E13 -> 47.81 | F24: =D24*E24 -> 75214.692 | G24: =data!I13 -> 5366.99 | H24: =F24+G24 -> 80581.682 | J24: =data!K13 -> 15268.83 | K24: =data!L13 -> 4263.0573 | L24: =data!M13 -> 1078.56 | N24: =$H24/J24 -> 5.2775283 | O24: =$H24/K24 -> 18.902322 | P24: =F24/L24 -> 69.736215
B25: =data!C14 -> Uno Minda | D25: =data!D14 -> 1230.8 | E25: =data!E14 -> 57.71 | F25: =D25*E25 -> 71029.468 | G25: =data!I14 -> 2648.12 | H25: =F25+G25 -> 73677.588 | J25: =data!K14 -> 18849.5 | K25: =data!L14 -> 5662.3898 | L25: =data!M14 -> 1221.54 | N25: =$H25/J25 -> 3.908729 | O25: =$H25/K25 -> 13.011748 | P25: =F25/L25 -> 58.147476
B26: =data!C15 -> Schaeffler India | D26: =data!D15 -> 3814.2 | E26: =data!E15 -> 15.63 | F26: =D26*E26 -> 59615.946 | G26: =data!I15 -> -1310.08 | H26: =F26+G26 -> 58305.866 | J26: =data!K15 -> 8834.57 | K26: =data!L15 -> 2830.5962 | L26: =data!M15 -> 1117.62 | N26: =$H26/J26 -> 6.5997401 | O26: =$H26/K26 -> 20.59844 | P26: =F26/L26 -> 53.341875
B27: =data!C16 -> MRF | D27: =data!D16 -> 134970 | E27: =data!E16 -> 0.42 | F27: =D27*E27 -> 56687.4 | G27: =data!I16 -> 3254.73 | H27: =F27+G27 -> 59942.13 | J27: =data!K16 -> 29130.05 | K27: =data!L16 -> 3853.9056 | L27: =data!M16 -> 1853.68 | N27: =$H27/J27 -> 2.0577421 | O27: =$H27/K27 -> 15.553606 | P27: =F27/L27 -> 30.581006
B28: =data!C17 -> Balkrishna Inds | D28: =data!D17 -> 2687.8 | E28: =data!E17 -> 19.33 | F28: =D28*E28 -> 51955.174 | G28: =data!I17 -> 3595.72 | H28: =F28+G28 -> 55550.894 | J28: =data!K17 -> 10642.64 | K28: =data!L17 -> 2244.5328 | L28: =data!M17 -> 1312.19 | N28: =$H28/J28 -> 5.2196536 | O28: =$H28/K28 -> 24.749424 | P28: =F28/L28 -> 39.594246
B30: High | N30: =MAX(N14:N28) -> 6.5997401 | O30: =MAX(O14:O28) -> 24.749424 | P30: =MAX(P14:P28) -> 69.736215
B31: 75 Pecentile | N31: =QUARTILE(N14:N28,3) -> 5.0915051 | O31: =QUARTILE(O14:O28,3) -> 19.750381 | P31: =QUARTILE(P14:P28,3) -> 46.624555
B32: Average | N32: =AVERAGE(N14:N28) -> 3.4197252 | O32: =AVERAGE(O14:O28) -> 16.40731 | P32: =AVERAGE(P14:P28) -> 37.605506
B33: midean | N33: =MEDIAN(N14:N28) -> 3.1318126 | O33: =MEDIAN(O14:O28) -> 15.553606 | P33: =MEDIAN(P14:P28) -> 34.245021
B34: 25 percentile | N34: =QUARTILE(N14:N28,1) -> 2.26653 | O34: =QUARTILE(O14:O28,1) -> 13.672399 | P34: =QUARTILE(P14:P28,1) -> 30.465503
B35: Low | N35: =MIN(N14:N28) -> 0.46962208 | O35: =MIN(O14:O28) -> 8.0829962 | P35: =MIN(P14:P28) -> 1.6147069
B38: Comparble Company Valuvation | N38: EV/Revenue | O38: EV/EBIDTA | P38: P/E
B39: impliedEnterprice Value | N39: =N33*J14 -> 619908.97 | O39: =O33*K14 -> 333277.38 | P39: =P40+P41 -> 6778620.1
B40: Net Debt | N40: =$G$14 -> 182.77 | O40: =$G$14 -> 182.77 | P40: =$G$14 -> 182.77
B41: Implied market Value | N41: =N39-N40 -> 619726.2 | O41: =O39-O40 -> 333094.61 | P41: =P33*J14 -> 6778437.4
B42: shares Outstanding | N42: =$E$14 -> 27.43 | O42: =$E$14 -> 27.43 | P42: =$E$14 -> 27.43
B43: implied value per share | N43: =N41/N42 -> 22593.008 | O43: =O41/O42 -> 12143.442 | P43: =P41/P42 -> 247117.66
N46: =IF(N43>$D$14,"undervalued","overvalued") -> undervalued | O46: =IF(O43>$D$14,"undervalued","overvalued") -> undervalued | P46: =IF(P43>$D$14,"undervalued","overvalued") -> undervalued

Sheet RM
C1: =data!C23 -> Eicher Motors Limited is an Indian multinational automotive company that manufactures motorcycles and commercial vehicles, headquartered in New Delhi. Eicher is the parent company of Royal Enfield, a manufacturer of middleweight motorcycles. It also manufactures Eicher branded trucks and buses, under a joint venture with Volvo Group.
B9: Market Return Nifty 50
B11: Year | C11: Annual
B12: 2000 | C12: -0.1465 | E12: Average Retrun | G12: =AVERAGE(C12:C37) -> 0.15149231
B13: 2001 | C13: -0.1618 | E13: Dividend Yeild | G13: 1.28% 1
B14: 2002 | C14: 0.0325 | E14: Total Market Retrun | G14: =SUM(G12:G13) -> 0.15149231
B15: 2003 | C15: 0.719
B16: 2004 | C16: 0.1068
B17: 2005 | C17: 0.3634
B18: 2006 | C18: 0.3983
B19: 2007 | C19: 0.5477
B20: 2008 | C20: -0.5179
B21: 2009 | C21: 0.7576
B22: 2010 | C22: 0.1795
B23: 2011 | C23: -0.2462
B24: 2012 | C24: 0.277
B25: 2013 | C25: 0.0676
B26: 2014 | C26: 0.3139
... B37: 2025 | C37: 0.1051

Sheet Balance Sheet
A1: ='Profit & Loss'!A1 -> EICHER MOTORS LTD | E1: =UPDATE | J1: SCREENER.IN
A3: Narration | B3: ='Data Sheet'!B56 -> 42460 | C3: ='Data Sheet'!C56 -> 42825 | D3: ='Data Sheet'!D56 -> 43190 | E3: ='Data Sheet'!E56 -> 43555 | F3: ='Data Sheet'!F56 -> 43921 | G3: ='Data Sheet'!G56 -> 44286 | H3: ='Data Sheet'!H56 -> 44651 | I3: ='Data Sheet'!I56 -> 45016 | ... K3: ='Data Sheet'!K56 -> 45747
A4: Equity Share Capital | B4: ='Data Sheet'!B57 -> 27.16 | C4: ='Data Sheet'!C57 -> 27.21 | D4: ='Data Sheet'!D57 -> 27.26 | E4: ='Data Sheet'!E57 -> 27.28 | F4: ='Data Sheet'!F57 -> 27.3 | G4: ='Data Sheet'!G57 -> 27.33 | H4: ='Data Sheet'!H57 -> 27.34 | I4: ='Data Sheet'!I57 -> 27.35 | ... K4: ='Data Sheet'!K57 -> 27.42
A5: Reserves | B5: ='Data Sheet'!B58 -> 3625.93 | C5: ='Data Sheet'!C58 -> 5317.86 | D5: ='Data Sheet'!D58 -> 7002.81 | E5: ='Data Sheet'!E58 -> 8891.44 | F5: ='Data Sheet'!F58 -> 9953.63 | G5: ='Data Sheet'!G58 -> 11410.75 | H5: ='Data Sheet'!H58 -> 12580.66 | I5: ='Data Sheet'!I58 -> 14962.93 | ... K5: ='Data Sheet'!K58 -> 21269.07
A6: Borrowings | B6: ='Data Sheet'!B59 -> 22.57 | C6: ='Data Sheet'!C59 -> 111.85 | D6: ='Data Sheet'!D59 -> 150.84 | E6: ='Data Sheet'!E59 -> 186.76 | F6: ='Data Sheet'!F59 -> 249 | G6: ='Data Sheet'!G59 -> 219.25 | H6: ='Data Sheet'!H59 -> 107.71 | I6: ='Data Sheet'!I59 -> 288.41 | ... K6: ='Data Sheet'!K59 -> 458.13
A7: Other Liabilities | B7: ='Data Sheet'!B60 -> 1263.35 | C7: ='Data Sheet'!C60 -> 1552.16 | D7: ='Data Sheet'!D60 -> 2341.32 | E7: ='Data Sheet'!E60 -> 2281.35 | F7: ='Data Sheet'!F60 -> 2219.79 | G7: ='Data Sheet'!G60 -> 2901.28 | H7: ='Data Sheet'!H60 -> 3424.12 | I7: ='Data Sheet'!I60 -> 3918.95 | ... K7: ='Data Sheet'!K60 -> 5419.79
A8: Total | B8: ='Data Sheet'!B61 -> 4939.01 | C8: ='Data Sheet'!C61 -> 7009.08 | D8: ='Data Sheet'!D61 -> 9522.23 | E8: ='Data Sheet'!E61 -> 11386.83 | F8: ='Data Sheet'!F61 -> 12449.72 | G8: ='Data Sheet'!G61 -> 14558.61 | H8: ='Data Sheet'!H61 -> 16139.83 | I8: ='Data Sheet'!I61 -> 19197.64 | ... K8: ='Data Sheet'!K61 -> 27174.41
A10: Net Block | B10: ='Data Sheet'!B62 -> 789.59 | C10: ='Data Sheet'!C62 -> 872.78 | D10: ='Data Sheet'!D62 -> 1501.69 | E10: ='Data Sheet'!E62 -> 1874.58 | F10: ='Data Sheet'!F62 -> 2377.52 | G10: ='Data Sheet'!G62 -> 2433.3 | H10: ='Data Sheet'!H62 -> 2424.28 | I10: ='Data Sheet'!I62 -> 2689.99 | ... K10: ='Data Sheet'!K62 -> 3473.47
A11: Capital Work in Progress | B11: ='Data Sheet'!B63 -> 94.48 | C11: ='Data Sheet'!C63 -> 373.77 | D11: ='Data Sheet'!D63 -> 333.21 | E11: ='Data Sheet'!E63 -> 449.74 | F11: ='Data Sheet'!F63 -> 312.17 | G11: ='Data Sheet'!G63 -> 314.29 | H11: ='Data Sheet'!H63 -> 504.78 | I11: ='Data Sheet'!I63 -> 472.07 | ... K11: ='Data Sheet'!K63 -> 491.47
A12: Investments | B12: ='Data Sheet'!B64 -> 3388.24 | C12: ='Data Sheet'!C64 -> 4987.13 | D12: ='Data Sheet'!D64 -> 5580.84 | E12: ='Data Sheet'!E64 -> 4922.52 | F12: ='Data Sheet'!F64 -> 5748.77 | G12: ='Data Sheet'!G64 -> 3902.14 | H12: ='Data Sheet'!H64 -> 7720.58 | I12: ='Data Sheet'!I64 -> 12320.66 | ... K12: ='Data Sheet'!K64 -> 14790.9
A13: Other Assets | B13: ='Data Sheet'!B65 -> 666.7 | C13: ='Data Sheet'!C65 -> 775.4 | D13: ='Data Sheet'!D65 -> 2106.49 | E13: ='Data Sheet'!E65 -> 4139.99 | F13: ='Data Sheet'!F65 -> 4011.26 | G13: ='Data Sheet'!G65 -> 7908.88 | H13: ='Data Sheet'!H65 -> 5490.19 | I13: ='Data Sheet'!I65 -> 3714.92 | ... K13: ='Data Sheet'!K65 -> 8418.57
A14: Total | B14: ='Data Sheet'!B66 -> 4939.01 | C14: ='Data Sheet'!C66 -> 7009.08 | D14: ='Data Sheet'!D66 -> 9522.23 | E14: ='Data Sheet'!E66 -> 11386.83 | F14: ='Data Sheet'!F66 -> 12449.72 | G14: ='Data Sheet'!G66 -> 14558.61 | H14: ='Data Sheet'!H66 -> 16139.83 | I14: ='Data Sheet'!I66 -> 19197.64 | ... K14: ='Data Sheet'!K66 -> 27174.41
A16: Working Capital | B16: =B13-B7 -> -596.65 | C16: =C13-C7 -> -776.76 | D16: =D13-D7 -> -234.83 | E16: =E13-E7 -> 1858.64 | F16: =F13-F7 -> 1791.47 | G16: =G13-G7 -> 5007.6 | H16: =H13-H7 -> 2066.07 | I16: =I13-I7 -> -204.03 | ... K16: =K13-K7 -> 2998.78
A17: Debtors | B17: ='Data Sheet'!B67 -> 32.64 | C17: ='Data Sheet'!C67 -> 50.04 | D17: ='Data Sheet'!D67 -> 68 | E17: ='Data Sheet'!E67 -> 84.29 | F17: ='Data Sheet'!F67 -> 86.76 | G17: ='Data Sheet'!G67 -> 158.16 | H17: ='Data Sheet'!H67 -> 302.04 | I17: ='Data Sheet'!I67 -> 368.92 | ... K17: ='Data Sheet'!K67 -> 549.64
A18: Inventory | B18: ='Data Sheet'!B68 -> 308.39 | C18: ='Data Sheet'!C68 -> 335.9 | D18: ='Data Sheet'!D68 -> 394.64 | E18: ='Data Sheet'!E68 -> 633.38 | F18: ='Data Sheet'!F68 -> 572.35 | G18: ='Data Sheet'!G68 -> 874.6 | H18: ='Data Sheet'!H68 -> 1132.4 | I18: ='Data Sheet'!I68 -> 1278.44 | ... K18: ='Data Sheet'!K68 -> 1563.75
A20: Debtor Days | B20: =IF('Profit & Loss'!B4>0,'Balance Sheet'!B17/('Profit & Loss'!B4/365),0) -> 1.9298092 | C20: =IF('Profit & Loss'!C4>0,'Balance Sheet'!C17/('Profit & Loss'!C4/365),0) -> 2.5968527 | D20: =IF('Profit & Loss'!D4>0,'Balance Sheet'!D17/('Profit & Loss'!D4/365),0) -> 2.7685567 | E20: =IF('Profit & Loss'!E4>0,'Balance Sheet'!E17/('Profit & Loss'!E4/365),0) -> 3.1403145 | F20: =IF('Profit & Loss'!F4>0,'Balance Sheet'!F17/('Profit & Loss'!F4/365),0) -> 3.4595645 | G20: =IF('Profit & Loss'!G4>0,'Balance Sheet'!G17/('Profit & Loss'!G4/365),0) -> 6.6199636 | H20: =IF('Profit & Loss'!H4>0,'Balance Sheet'!H17/('Profit & Loss'!H4/365),0) -> 10.705615 | I20: =IF('Profit & Loss'!I4>0,'Balance Sheet'!I17/('Profit & Loss'!I4/365),0) -> 9.3237863 | ... K20: =IF('Profit & Loss'!K4>0,'Balance Sheet'!K17/('Profit & Loss'!K4/365),0) -> 10.631419
A21: Inventory Turnover | B21: =IF('Balance Sheet'!B18>0,'Profit & Loss'!B4/'Balance Sheet'!B18,0) -> 20.018353 | C21: =IF('Balance Sheet'!C18>0,'Profit & Loss'!C4/'Balance Sheet'!C18,0) -> 20.938851 | D21: =IF('Balance Sheet'!D18>0,'Profit & Loss'!D4/'Balance Sheet'!D18,0) -> 22.716805 | E21: =IF('Balance Sheet'!E18>0,'Profit & Loss'!E4/'Balance Sheet'!E18,0) -> 15.467902 | F21: =IF('Balance Sheet'!F18>0,'Profit & Loss'!F4/'Balance Sheet'!F18,0) -> 15.992976 | G21: =IF('Balance Sheet'!G18>0,'Profit & Loss'!G4/'Balance Sheet'!G18,0) -> 9.9706723 | H21: =IF('Balance Sheet'!H18>0,'Profit & Loss'!H4/'Balance Sheet'!H18,0) -> 9.0938096 | I21: =IF('Balance Sheet'!I18>0,'Profit & Loss'!I4/'Balance Sheet'!I18,0) -> 11.296721 | ... K21: =IF('Balance Sheet'!K18>0,'Profit & Loss'!K4/'Balance Sheet'!K18,0) -> 12.06737
A23: Return on Equity | B23: =IF(SUM('Balance Sheet'!B4:B5)>0,'Profit & Loss'!B12/SUM('Balance Sheet'!B4:B5),"") -> 0.36627622 | C23: =IF(SUM('Balance Sheet'!C4:C5)>0,'Profit & Loss'!C12/SUM('Balance Sheet'!C4:C5),"") -> 0.31189114 | D23: =IF(SUM('Balance Sheet'!D4:D5)>0,'Profit & Loss'!D12/SUM('Balance Sheet'!D4:D5),"") -> 0.2787554 | E23: =IF(SUM('Balance Sheet'!E4:E5)>0,'Profit & Loss'!E12/SUM('Balance Sheet'!E4:E5),"") -> 0.24697827 | F23: =IF(SUM('Balance Sheet'!F4:F5)>0,'Profit & Loss'!F12/SUM('Balance Sheet'!F4:F5),"") -> 0.18309316 | G23: =IF(SUM('Balance Sheet'!G4:G5)>0,'Profit & Loss'!G12/SUM('Balance Sheet'!G4:G5),"") -> 0.1177549 | H23: =IF(SUM('Balance Sheet'!H4:H5)>0,'Profit & Loss'!H12/SUM('Balance Sheet'!H4:H5),"") -> 0.13297906 | I23: =IF(SUM('Balance Sheet'!I4:I5)>0,'Profit & Loss'!I12/SUM('Balance Sheet'!I4:I5),"") -> 0.19438863 | ... K23: =IF(SUM('Balance Sheet'!K4:K5)>0,'Profit & Loss'!K12/SUM('Balance Sheet'!K4:K5),"") -> 0.22231081
A24: Return on Capital Emp | C24: =IF((B4+B5+B6+C4+C5+C6)>0,('Profit & Loss'!C10+'Profit & Loss'!C9)*2/(B4+B5+B6+C4+C5+C6),"") -> 0.53368052 | D24: =IF((C4+C5+C6+D4+D5+D6)>0,('Profit & Loss'!D10+'Profit & Loss'!D9)*2/(C4+C5+C6+D4+D5+D6),"") -> 0.49391233 | E24: =IF((D4+D5+D6+E4+E5+E6)>0,('Profit & Loss'!E10+'Profit & Loss'!E9)*2/(D4+D5+D6+E4+E5+E6),"") -> 0.40581369 | F24: =IF((E4+E5+E6+F4+F5+F6)>0,('Profit & Loss'!F10+'Profit & Loss'!F9)*2/(E4+E5+E6+F4+F5+F6),"") -> 0.24553604 | G24: =IF((F4+F5+F6+G4+G5+G6)>0,('Profit & Loss'!G10+'Profit & Loss'!G9)*2/(F4+F5+F6+G4+G5+G6),"") -> 0.16583529 | H24: =IF((G4+G5+G6+H4+H5+H6)>0,('Profit & Loss'!H10+'Profit & Loss'!H9)*2/(G4+G5+G6+H4+H5+H6),"") -> 0.18227435 | I24: =IF((H4+H5+H6+I4+I5+I6)>0,('Profit & Loss'!I10+'Profit & Loss'!I9)*2/(H4+H5+H6+I4+I5+I6),"") -> 0.27345826 | J24: =IF((I4+I5+I6+J4+J5+J6)>0,('Profit & Loss'!J10+'Profit & Loss'!J9)*2/(I4+I5+I6+J4+J5+J6),"") -> 0.31134145 | K24: =IF((J4+J5+J6+K4+K5+K6)>0,('Profit & Loss'!K10+'Profit & Loss'!K9)*2/(J4+J5+J6+K4+K5+K6),"") -> 0.297736

Sheet Profit & Loss
A1: ='Data Sheet'!B1 -> EICHER MOTORS LTD | H1: =UPDATE
A3: Narration | B3: ='Data Sheet'!B16 -> 42460 | C3: ='Data Sheet'!C16 -> 42825 | D3: ='Data Sheet'!D16 -> 43190 | E3: ='Data Sheet'!E16 -> 43555 | F3: ='Data Sheet'!F16 -> 43921 | G3: ='Data Sheet'!G16 -> 44286 | H3: ='Data Sheet'!H16 -> 44651 | I3: ='Data Sheet'!I16 -> 45016 | ... K3: ='Data Sheet'!K16 -> 45747
A4: Sales | B4: ='Data Sheet'!B17 -> 6173.46 | C4: ='Data Sheet'!C17 -> 7033.36 | D4: ='Data Sheet'!D17 -> 8964.96 | E4: ='Data Sheet'!E17 -> 9797.06 | F4: ='Data Sheet'!F17 -> 9153.58 | G4: ='Data Sheet'!G17 -> 8720.35 | H4: ='Data Sheet'!H17 -> 10297.83 | I4: ='Data Sheet'!I17 -> 14442.18 | ... K4: ='Data Sheet'!K17 -> 18870.35
A5: Expenses | B5: =SUM('Data Sheet'!B18,'Data Sheet'!B20:B24, -1*'Data Sheet'!B19) -> 4483.73 | C5: =SUM('Data Sheet'!C18,'Data Sheet'!C20:C24, -1*'Data Sheet'!C19) -> 4859.05 | D5: =SUM('Data Sheet'!D18,'Data Sheet'!D20:D24, -1*'Data Sheet'!D19) -> 6156.33 | E5: =SUM('Data Sheet'!E18,'Data Sheet'!E20:E24, -1*'Data Sheet'!E19) -> 6892.82 | F5: =SUM('Data Sheet'!F18,'Data Sheet'!F20:F24, -1*'Data Sheet'!F19) -> 6970.69 | G5: =SUM('Data Sheet'!G18,'Data Sheet'!G20:G24, -1*'Data Sheet'!G19) -> 6937.12 | H5: =SUM('Data Sheet'!H18,'Data Sheet'!H20:H24, -1*'Data Sheet'!H19) -> 8120.26 | I5: =SUM('Data Sheet'!I18,'Data Sheet'!I20:I24, -1*'Data Sheet'!I19) -> 10996.46 | ... K5: =SUM('Data Sheet'!K18,'Data Sheet'!K20:K24, -1*'Data Sheet'!K19) -> 14147.78
A6: Operating Profit | B6: =B4-B5 -> 1689.73 | C6: =C4-C5 -> 2174.31 | D6: =D4-D5 -> 2808.63 | E6: =E4-E5 -> 2904.24 | F6: =F4-F5 -> 2182.89 | G6: =G4-G5 -> 1783.23 | H6: =H4-H5 -> 2177.57 | I6: =I4-I5 -> 3445.72 | ... K6: =K4-K5 -> 4722.57
A7: Other Income | B7: ='Data Sheet'!B25 -> 325.91 | C7: ='Data Sheet'!C25 -> 416.44 | D7: ='Data Sheet'!D25 -> 535.66 | E7: ='Data Sheet'!E25 -> 700.66 | F7: ='Data Sheet'!F25 -> 572.42 | G7: ='Data Sheet'!G25 -> 482.34 | H7: ='Data Sheet'!H25 -> 495.65 | I7: ='Data Sheet'!I25 -> 908.14 | ... K7: ='Data Sheet'!K25 -> 1994.17
A8: Depreciation | B8: ='Data Sheet'!B26 -> 136.6 | C8: ='Data Sheet'!C26 -> 153.81 | D8: ='Data Sheet'!D26 -> 223.3 | E8: ='Data Sheet'!E26 -> 300.28 | F8: ='Data Sheet'!F26 -> 381.54 | G8: ='Data Sheet'!G26 -> 450.73 | H8: ='Data Sheet'!H26 -> 451.93 | I8: ='Data Sheet'!I26 -> 526.21 | ... K8: ='Data Sheet'!K26 -> 729.33
A9: Interest | B9: ='Data Sheet'!B27 -> 2.12 | C9: ='Data Sheet'!C27 -> 3.56 | D9: ='Data Sheet'!D27 -> 5.34 | E9: ='Data Sheet'!E27 -> 7.33 | F9: ='Data Sheet'!F27 -> 18.88 | G9: ='Data Sheet'!G27 -> 16.45 | H9: ='Data Sheet'!H27 -> 18.78 | I9: ='Data Sheet'!I27 -> 28.02 | ... K9: ='Data Sheet'!K27 -> 54.34
A10: Profit before tax | B10: ='Data Sheet'!B28 -> 1876.92 | C10: ='Data Sheet'!C28 -> 2433.38 | D10: ='Data Sheet'!D28 -> 3115.65 | E10: ='Data Sheet'!E28 -> 3297.29 | F10: ='Data Sheet'!F28 -> 2354.89 | G10: ='Data Sheet'!G28 -> 1798.39 | H10: ='Data Sheet'!H28 -> 2202.51 | I10: ='Data Sheet'!I28 -> 3799.63 | ... K10: ='Data Sheet'!K28 -> 5933.07
A11: Tax | B11: ='Data Sheet'!B29 -> 538.88 | C11: ='Data Sheet'!C29 -> 720.3 | D11: ='Data Sheet'!D29 -> 935.93 | E11: ='Data Sheet'!E29 -> 1077.04 | F11: ='Data Sheet'!F29 -> 527.45 | G11: ='Data Sheet'!G29 -> 451.5 | H11: ='Data Sheet'!H29 -> 525.91 | I11: ='Data Sheet'!I29 -> 885.69 | ... K11: ='Data Sheet'!K29 -> 1198.63
A12: Net profit | B12: ='Data Sheet'!B30 -> 1338.04 | C12: ='Data Sheet'!C30 -> 1667.08 | D12: ='Data Sheet'!D30 -> 1959.67 | E12: ='Data Sheet'!E30 -> 2202.73 | F12: ='Data Sheet'!F30 -> 1827.44 | G12: ='Data Sheet'!G30 -> 1346.89 | H12: ='Data Sheet'!H30 -> 1676.6 | I12: ='Data Sheet'!I30 -> 2913.94 | ... K12: ='Data Sheet'!K30 -> 4734.44
A13: EPS | B13: =IF('Data Sheet'!B93>0,B12/'Data Sheet'!B93,0) -> 49.265096 | C13: =IF('Data Sheet'!C93>0,C12/'Data Sheet'!C93,0) -> 61.267181 | D13: =IF('Data Sheet'!D93>0,D12/'Data Sheet'!D93,0) -> 71.888114 | E13: =IF('Data Sheet'!E93>0,E12/'Data Sheet'!E93,0) -> 80.745235 | F13: =IF('Data Sheet'!F93>0,F12/'Data Sheet'!F93,0) -> 66.914683 | G13: =IF('Data Sheet'!G93>0,G12/'Data Sheet'!G93,0) -> 49.282473 | H13: =IF('Data Sheet'!H93>0,H12/'Data Sheet'!H93,0) -> 61.324067 | I13: =IF('Data Sheet'!I93>0,I12/'Data Sheet'!I93,0) -> 106.5426 | ... K13: =IF('Data Sheet'!K93>0,K12/'Data Sheet'!K93,0) -> 172.66375
A14: Price to earning | B14: =IF(B15>0,B15/B13,"") -> 38.933447 | C14: =IF(C15>0,C15/C13,"") -> 41.763795 | D14: =IF(D15>0,D15/D13,"") -> 39.467859 | E14: =IF(E15>0,E15/E13,"") -> 25.44757 | F14: =IF(F15>0,F15/F13,"") -> 19.571041 | G14: =IF(G15>0,G15/G13,"") -> 52.837242 | H14: =IF(H15>0,H15/H13,"") -> 40.068282 | I14: =IF(I15>0,I15/I13,"") -> 27.677662 | ... K14: =IF(K15>0,K15/K13,"") -> 30.971759
A15: Price | B15: ='Data Sheet'!B90 -> 1918.06 | C15: ='Data Sheet'!C90 -> 2558.75 | D15: ='Data Sheet'!D90 -> 2837.27 | E15: ='Data Sheet'!E90 -> 2054.77 | F15: ='Data Sheet'!F90 -> 1309.59 | G15: ='Data Sheet'!G90 -> 2603.95 | H15: ='Data Sheet'!H90 -> 2457.15 | I15: ='Data Sheet'!I90 -> 2948.85 | ... K15: ='Data Sheet'!K90 -> 5347.7
A17: RATIOS:
A18: Dividend Payout | B18: =IF('Data Sheet'!B30>0, 'Data Sheet'!B31/'Data Sheet'!B30, 0) -> 0.20298347 | C18: =IF('Data Sheet'!C30>0, 'Data Sheet'!C31/'Data Sheet'!C30, 0) -> 0.16321952 | D18: =IF('Data Sheet'!D30>0, 'Data Sheet'!D31/'Data Sheet'!D30, 0) -> 0.15301556 | E18: =IF('Data Sheet'!E30>0, 'Data Sheet'!E31/'Data Sheet'!E30, 0) -> 0.1548079 | F18: =IF('Data Sheet'!F30>0, 'Data Sheet'!F31/'Data Sheet'!F30, 0) -> 0.18673664 | G18: =IF('Data Sheet'!G30>0, 'Data Sheet'!G31/'Data Sheet'!G30, 0) -> 0.34495022 | H18: =IF('Data Sheet'!H30>0, 'Data Sheet'!H31/'Data Sheet'!H30, 0) -> 0.34244304 | I18: =IF('Data Sheet'!I30>0, 'Data Sheet'!I31/'Data Sheet'!I30, 0) -> 0.34727894 | ... K18: =IF('Data Sheet'!K30>0, 'Data Sheet'!K31/'Data Sheet'!K30, 0) -> 0.40541226
A19: OPM | B19: =IF(B6>0,B6/B4,0) -> 0.27370875 | C19: =IF(C6>0,C6/C4,0) -> 0.30914243 | D19: =IF(D6>0,D6/D4,0) -> 0.31328974 | E19: =IF(E6>0,E6/E4,0) -> 0.29643995 | F19: =IF(F6>0,F6/F4,0) -> 0.23847391 | G19: =IF(G6>0,G6/G4,0) -> 0.20449065 | H19: =IF(H6>0,H6/H4,0) -> 0.21145911 | I19: =IF(I6>0,I6/I4,0) -> 0.23858725 | ... K19: =IF(K6>0,K6/K4,0) -> 0.25026404
G22: TRENDS: | H22: 10 YEARS | I22: 7 YEARS | J22: 5 YEARS | K22: 3 YEARS
G23: Sales Growth | H23: =IF(B4=0,"",POWER($K4/B4,1/9)-1) -> 0.13218348 | I23: =IF(D4=0,"",POWER($K4/D4,1/7)-1) -> 0.11218221 | J23: =IF(F4=0,"",POWER($K4/F4,1/5)-1) -> 0.15568052 | K23: =IF(H4=0,"",POWER($K4/H4, 1/3)-1) -> 0.22370879
G24: OPM | H24: =IF(SUM(B4:$K$4)=0,"",SUMPRODUCT(B19:$K$19,B4:$K$4)/SUM(B4:$K$4)) -> 0.2565555 | I24: =IF(SUM(E4:$K$4)=0,"",SUMPRODUCT(E19:$K$19,E4:$K$4)/SUM(E4:$K$4)) -> 0.2453461 | J24: =IF(SUM(G4:$K$4)=0,"",SUMPRODUCT(G19:$K$19,G4:$K$4)/SUM(G4:$K$4)) -> 0.23899084 | K24: =IF(SUM(I4:$K$4)=0, "", SUMPRODUCT(I19:$K$19,I4:$K$4)/SUM(I4:$K$4)) -> 0.25071382
G25: Price to Earning | H25: =IF(ISERROR(AVERAGEIF(B14:$L14,">0")),"",AVERAGEIF(B14:$L14,">0")) -> 34.424382 | I25: =IF(ISERROR(AVERAGEIF(E14:$L14,">0")),"",AVERAGEIF(E14:$L14,">0")) -> 32.011246 | J25: =IF(ISERROR(AVERAGEIF(G14:$L14,">0")),"",AVERAGEIF(G14:$L14,">0")) -> 35.812022 | K25: =IF(ISERROR(AVERAGEIF(I14:$L14,">0")),"",AVERAGEIF(I14:$L14,">0")) -> 28.718195
A28: EBIDTA Margin(%) | B28: =B6/B4 -> 0.27370875 | C28: =C6/C4 -> 0.30914243 | D28: =D6/D4 -> 0.31328974 | E28: =E6/E4 -> 0.29643995 | F28: =F6/F4 -> 0.23847391 | G28: =G6/G4 -> 0.20449065 | H28: =H6/H4 -> 0.21145911 | I28: =I6/I4 -> 0.23858725 | ... K28: =K6/K4 -> 0.25026404
A29: EBIT Margin() | B29: =IFERROR((B6-B8)/B4,0) -> 0.25158177 | C29: =IFERROR((C6-C8)/C4,0) -> 0.28727379 | D29: =IFERROR((D6-D8)/D4,0) -> 0.28838165 | E29: =IFERROR((E6-E8)/E4,0) -> 0.26578994 | F29: =IFERROR((F6-F8)/F4,0) -> 0.19679186 | G29: =IFERROR((G6-G8)/G4,0) -> 0.1528035 | H29: =IFERROR((H6-H8)/H4,0) -> 0.16757317 | I29: =IFERROR((I6-I8)/I4,0) -> 0.20215161 | ... K29: =IFERROR((K6-K8)/K4,0) -> 0.21161452
A32: dived pay ratio | B32: =IFERROR(B13*B18,0) -> 10 | C32: =IFERROR(C13*C18,0) -> 10 | D32: =IFERROR(D13*D18,0) -> 11 | E32: =IFERROR(E13*E18,0) -> 12.5 | F32: =IFERROR(F13*F18,0) -> 12.495423 | G32: =IFERROR(G13*G18,0) -> 17 | H32: =IFERROR(H13*H18,0) -> 21 | I32: =IFERROR(I13*I18,0) -> 37 | ... K32: =IFERROR(K13*K18,0) -> 70
A33: divedend gorwth rate | D33: =D32/C32-1 -> 0.1 | E33: =E32/D32-1 -> 0.13636364 | F33: =F32/E32-1 -> -0.00036616624 | G33: =G32/F32-1 -> 0.36049817 | H33: =H32/G32-1 -> 0.23529412 | I33: =I32/H32-1 -> 0.76190476 | J33: =J32/I32-1 -> 0.37837838 | K33: =K32/J32-1 -> 0.37254902
A35: market captialzation | B35: ='Data Sheet'!B93*'Data Sheet'!B90 -> 52094.51 | C35: ='Data Sheet'!C93*'Data Sheet'!C90 -> 69623.588 | D35: ='Data Sheet'!D93*'Data Sheet'!D90 -> 77343.98 | E35: ='Data Sheet'!E93*'Data Sheet'!E90 -> 56054.126 | F35: ='Data Sheet'!F93*'Data Sheet'!F90 -> 35764.903 | G35: ='Data Sheet'!G93*'Data Sheet'!G90 -> 71165.953 | H35: ='Data Sheet'!H93*'Data Sheet'!H90 -> 67178.481 | I35: ='Data Sheet'!I93*'Data Sheet'!I90 -> 80651.048 | ... K35: ='Data Sheet'!K93*'Data Sheet'!K90 -> 146633.93
A36: debt | B36: ='Data Sheet'!B59 -> 22.57 | C36: ='Data Sheet'!C59 -> 111.85 | D36: ='Data Sheet'!D59 -> 150.84 | E36: ='Data Sheet'!E59 -> 186.76 | F36: ='Data Sheet'!F59 -> 249 | G36: ='Data Sheet'!G59 -> 219.25 | H36: ='Data Sheet'!H59 -> 107.71 | I36: ='Data Sheet'!I59 -> 288.41 | ... K36: ='Data Sheet'!K59 -> 458.13
A37: cash | B37: ='Data Sheet'!B69 -> 49.17 | C37: ='Data Sheet'!C69 -> 25.06 | D37: ='Data Sheet'!D69 -> 1212 | E37: ='Data Sheet'!E69 -> 2965.29 | F37: ='Data Sheet'!F69 -> 2950.59 | G37: ='Data Sheet'!G69 -> 5830.36 | H37: ='Data Sheet'!H69 -> 2722.47 | I37: ='Data Sheet'!I69 -> 765.58 | ... K37: ='Data Sheet'!K69 -> 263.01
A38: ev | B38: =B35+B36-B37 -> 52067.91 | C38: =C35+C36-C37 -> 69710.378 | D38: =D35+D36-D37 -> 76282.82 | E38: =E35+E36-E37 -> 53275.596 | F38: =F35+F36-F37 -> 33063.313 | G38: =G35+G36-G37 -> 65554.843 | H38: =H35+H36-H37 -> 64563.721 | I38: =I35+I36-I37 -> 80173.878 | ... K38: =K35+K36-K37 -> 146829.05
A40: ev/Ebidta | B40: =B38/B6 -> 30.814337 | C40: =C38/C6 -> 32.060919 | D40: =D38/D6 -> 27.160153 | E40: =E38/E6 -> 18.344075 | F40: =F38/F6 -> 15.146578 | G40: =G38/G6 -> 36.761855 | H40: =H38/H6 -> 29.649435 | I40: =I38/I6 -> 23.26767 | ... K40: =K38/K6 -> 31.090922
A41: ev/sales | B41: =B38/B4 -> 8.4341536 | C41: =C38/C4 -> 9.9113905 | D41: =D38/D4 -> 8.5089973 | E41: =E38/E4 -> 5.4379166 | F41: =F38/F4 -> 3.6120636 | G41: =G38/G4 -> 7.5174555 | H41: =H38/H4 -> 6.2696433 | I41: =I38/I4 -> 5.5513695 | ... K41: =K38/K4 -> 7.7809396
A42: p/b | B42: =B35/'Data Sheet'!B95 -> 14.260396 | C42: =C35/'Data Sheet'!C95 -> 13.025758 | D42: =D35/'Data Sheet'!D95 -> 11.001879 | E42: =E35/'Data Sheet'!E95 -> 6.2849967 | F42: =F35/'Data Sheet'!F95 -> 3.5833237 | G42: =G35/'Data Sheet'!G95 -> 6.2218444 | H42: =H35/'Data Sheet'!H95 -> 5.3282425 | I42: =I35/'Data Sheet'!I95 -> 5.3802229 | ... K42: =K35/'Data Sheet'!K95 -> 6.8853569

Sheet Data Sheet
A1: COMPANY NAME | B1: EICHER MOTORS LTD | E1: =IF(B2<>B3, "A NEW VERSION OF THE WORKSHEET IS AVAILABLE", "")
A2: LATEST VERSION | B2: 2.1 | E2: PLEASE DO NOT MAKE ANY CHANGES TO THIS SHEET
A3: CURRENT VERSION | B3: 2.1
A5: META
A6: Number of shares | B6: =IF(B9>0, B9/B8, 0) -> 27.429924
A7: Face Value | B7: 1
A8: Current Price | B8: 6973
A9: Market Capitalization | B9: 191268.86
A15: PROFIT & LOSS
A16: Report Date | B16: 42460 | C16: 42825 | D16: 43190 | E16: 43555 | F16: 43921 | G16: 44286 | H16: 44651 | I16: 45016 | J16: 45382 | K16: 45747
A17: Sales | B17: 6173.46 | C17: 7033.36 | D17: 8964.96 | E17: 9797.06 | F17: 9153.58 | G17: 8720.35 | H17: 10297.83 | I17: 14442.18 | J17: 16535.78 | K17: 18870.35
A18: Raw Material Cost | B18: 3497.73 | C18: 3725.72 | D18: 4679.07 | E18: 5269.64 | F18: 4914.58 | G18: 5319.85 | H18: 6107.28 | I18: 8281.04 | J18: 9187.35 | K18: 10470.09
A19: Change in Inventory | B19: 62.05 | C19: 19.61 | D19: 33.87 | E19: 210.16 | F19: -84.09 | G19: 205.9 | H19: 148.59 | I19: 63.25 | J19: 197.03 | K19: 163.51
A20: Power and Fuel | B20: 46.18 | C20: 46.02 | D20: 52.41 | E20: 66.96 | F20: 62.86 | G20: 52.98 | H20: 55.78 | I20: 72.97 | J20: 80.61 | K20: 89.53
A21: Other Mfr. Exp | B21: 173.76 | C21: 173.09 | D21: 210.76 | E21: 263.49 | F21: 256.58 | G21: 250.85 | H21: 332.41 | I21: 397.21 | J21: 394.36 | K21: 453.77
A22: Employee Cost | B22: 350.21 | C22: 426.28 | D22: 573.68 | E22: 702.44 | F22: 795.78 | G22: 843.23 | H22: 821.02 | I22: 1001.93 | J22: 1235.69 | K22: 1391.23
A23: Selling and admin | B23: 397.4 | C23: 412.25 | D23: 565.66 | E23: 654.82 | F23: 667.16 | G23: 522.52 | H23: 815.51 | I23: 1164.58 | J23: 1293.02 | K23: 1669.63
A24: Other Expenses | B24: 80.5 | C24: 95.3 | D24: 108.62 | E24: 145.63 | F24: 189.64 | G24: 153.59 | H24: 136.85 | I24: 141.98 | J24: 212.41 | K24: 237.04
A25: Other Income | B25: 325.91 | C25: 416.44 | D25: 535.66 | E25: 700.66 | F25: 572.42 | G25: 482.34 | H25: 495.65 | I25: 908.14 | J25: 1521.13 | K25: 1994.17
A26: Depreciation | B26: 136.6 | C26: 153.81 | D26: 223.3 | E26: 300.28 | F26: 381.54 | G26: 450.73 | H26: 451.93 | I26: 526.21 | J26: 597.6 | K26: 729.33
A27: Interest | B27: 2.12 | C27: 3.56 | D27: 5.34 | E27: 7.33 | F27: 18.88 | G27: 16.45 | H27: 18.78 | I27: 28.02 | J27: 50.88 | K27: 54.34
... A31: Dividend Amount | B31: 271.6 | C31: 272.1 | D31: 299.86 | E31: 341 | F31: 341.25 | G31: 464.61 | H31: 574.14 | I31: 1011.95 | J31: 1396.38 | K31: 1919.4
A32: EBIDTA | B32: =B30+B27+B26+B29 -> 2015.64 | C32: =C30+C27+C26+C29 -> 2544.75 | D32: =D30+D27+D26+D29 -> 3124.24 | E32: =E30+E27+E26+E29 -> 3587.38 | F32: =F30+F27+F26+F29 -> 2755.31 | G32: =G30+G27+G26+G29 -> 2265.57 | H32: =H30+H27+H26+H29 -> 2673.22 | I32: =I30+I27+I26+I29 -> 4353.86 | ... K32: =K30+K27+K26+K29 -> 6716.74
A35: GROSS PROFIT | B35: =IFERROR(B17-B18-B19-B20-B21-B22,0) -> 2043.53 | C35: =IFERROR(C17-C18-C19-C20-C21-C22,0) -> 2642.64 | D35: =IFERROR(D17-D18-D19-D20-D21-D22,0) -> 3415.17 | E35: =IFERROR(E17-E18-E19-E20-E21-E22,0) -> 3284.37 | F35: =IFERROR(F17-F18-F19-F20-F21-F22,0) -> 3207.87 | G35: =IFERROR(G17-G18-G19-G20-G21-G22,0) -> 2047.54 | H35: =IFERROR(H17-H18-H19-H20-H21-H22,0) -> 2832.75 | I35: =IFERROR(I17-I18-I19-I20-I21-I22,0) -> 4625.78 | ... K35: =IFERROR(K17-K18-K19-K20-K21-K22,0) -> 6302.22
A36: GPM | B36: =B35/B17 -> 0.33101859 | C36: =C35/C17 -> 0.37572938 | D36: =D35/D17 -> 0.38094648 | E36: =E35/E17 -> 0.33524037 | F36: =F35/F17 -> 0.35044977 | G36: =G35/G17 -> 0.23480021 | H36: =H35/H17 -> 0.27508223 | I36: =I35/I17 -> 0.32029652 | ... K36: =K35/K17 -> 0.33397473
A40: Quarters
A41: Report Date | B41: 45107 | C41: 45199 | D41: 45291 | E41: 45382 | F41: 45473 | G41: 45565 | H41: 45657 | I41: 45747 | J41: 45838 | K41: 45930
A42: Sales | B42: 3986.37 | C42: 4114.53 | D42: 4178.84 | E42: 4256.04 | F42: 4393.05 | G42: 4263.07 | H42: 4973.12 | I42: 5241.11 | J42: 5041.84 | K42: 6171.59
A43: Expenses | B43: 2965.53 | C43: 3027.37 | D43: 3088.57 | E43: 3127.4 | F43: 3227.62 | G43: 3175.35 | H43: 3771.93 | I43: 3983.42 | J43: 3839.06 | K43: 4659.69
A44: Other Income | B44: 343.65 | C44: 375.4 | D44: 367.58 | E44: 436.96 | F44: 456.51 | G44: 467.53 | H44: 452.29 | I44: 628.38 | J44: 603.17 | K44: 485.83
A45: Depreciation | B45: 142.27 | C45: 142.54 | D45: 147.54 | E45: 165.25 | F45: 168.63 | G45: 180.06 | H45: 179.27 | I45: 201.37 | J45: 198.06 | K45: 199.56
A46: Interest | B46: 10.43 | C46: 12.68 | D46: 12.43 | E46: 15.34 | F46: 12.27 | G46: 13.14 | H46: 13.39 | I46: 15.54 | J46: 14.9 | K46: 19.16
A47: Profit before tax | B47: 1211.79 | C47: 1307.34 | D47: 1297.88 | E47: 1385.01 | F47: 1441.04 | G47: 1362.05 | H47: 1460.82 | I47: 1669.16 | J47: 1592.99 | K47: 1779.01
A48: Tax | B48: 293.45 | C48: 291.09 | D48: 301.91 | E48: 314.56 | F48: 339.58 | G48: 261.72 | H48: 290.32 | I48: 307.01 | J48: 387.77 | K48: 409.56
A49: Net profit | B49: 918.34 | C49: 1016.25 | D49: 995.97 | E49: 1070.45 | F49: 1101.46 | G49: 1100.33 | H49: 1170.5 | I49: 1362.15 | J49: 1205.22 | K49: 1369.45
A50: Operating Profit | B50: 1020.84 | C50: 1087.16 | D50: 1090.27 | E50: 1128.64 | F50: 1165.43 | G50: 1087.72 | H50: 1201.19 | I50: 1257.69 | J50: 1202.78 | K50: 1511.9
A55: BALANCE SHEET
A56: Report Date | B56: 42460 | C56: 42825 | D56: 43190 | E56: 43555 | F56: 43921 | G56: 44286 | H56: 44651 | I56: 45016 | J56: 45382 | K56: 45747
A57: Equity Share Capital | B57: 27.16 | C57: 27.21 | D57: 27.26 | E57: 27.28 | F57: 27.3 | G57: 27.33 | H57: 27.34 | I57: 27.35 | J57: 27.38 | K57: 27.42
A58: Reserves | B58: 3625.93 | C58: 5317.86 | D58: 7002.81 | E58: 8891.44 | F58: 9953.63 | G58: 11410.75 | H58: 12580.66 | I58: 14962.93 | J58: 18018.15 | K58: 21269.07
A59: Borrowings | B59: 22.57 | C59: 111.85 | D59: 150.84 | E59: 186.76 | F59: 249 | G59: 219.25 | H59: 107.71 | I59: 288.41 | J59: 419.44 | K59: 458.13
A60: Other Liabilities | B60: 1263.35 | C60: 1552.16 | D60: 2341.32 | E60: 2281.35 | F60: 2219.79 | G60: 2901.28 | H60: 3424.12 | I60: 3918.95 | J60: 4650.16 | K60: 5419.79
A61: Total | B61: 4939.01 | C61: 7009.08 | D61: 9522.23 | E61: 11386.83 | F61: 12449.72 | G61: 14558.61 | H61: 16139.83 | I61: 19197.64 | J61: 23115.13 | K61: 27174.41
A62: Net Block | B62: 789.59 | C62: 872.78 | D62: 1501.69 | E62: 1874.58 | F62: 2377.52 | G62: 2433.3 | H62: 2424.28 | I62: 2689.99 | J62: 2914.38 | K62: 3473.47
A63: Capital Work in Progress | B63: 94.48 | C63: 373.77 | D63: 333.21 | E63: 449.74 | F63: 312.17 | G63: 314.29 | H63: 504.78 | I63: 472.07 | J63: 555.1 | K63: 491.47
A64: Investments | B64: 3388.24 | C64: 4987.13 | D64: 5580.84 | E64: 4922.52 | F64: 5748.77 | G64: 3902.14 | H64: 7720.58 | I64: 12320.66 | J64: 13526.96 | K64: 14790.9
A65: Other Assets | B65: 666.7 | C65: 775.4 | D65: 2106.49 | E65: 4139.99 | F65: 4011.26 | G65: 7908.88 | H65: 5490.19 | I65: 3714.92 | J65: 6118.69 | K65: 8418.57
A66: Total | B66: 4939.01 | C66: 7009.08 | D66: 9522.23 | E66: 11386.83 | F66: 12449.72 | G66: 14558.61 | H66: 16139.83 | I66: 19197.64 | J66: 23115.13 | K66: 27174.41
A67: Receivables | B67: 32.64 | C67: 50.04 | D67: 68 | E67: 84.29 | F67: 86.76 | G67: 158.16 | H67: 302.04 | I67: 368.92 | J67: 373.78 | K67: 549.64
... A70: No. of Equity Shares | B70: 27161183 | C70: 27210249 | D70: 27255549 | E70: 27282570 | F70: 27304570 | G70: 273335922 | H70: 273423102 | I70: 273481570 | J70: 273805630 | K70: 274164080
A71: New Bonus Shares
A72: Face value | C72: 10 | D72: 10 | E72: 10 | F72: 10 | G72: 1 | H72: 1 | I72: 1 | J72: 1 | K72: 1
A73: other assest | B73: =B65-SUM(B67:B69) -> 276.5 | C73: =C65-SUM(C67:C69) -> 364.4 | D73: =D65-SUM(D67:D69) -> 431.85 | E73: =E65-SUM(E67:E69) -> 457.03 | F73: =F65-SUM(F67:F69) -> 401.56 | G73: =G65-SUM(G67:G69) -> 1045.76 | H73: =H65-SUM(H67:H69) -> 1333.28 | I73: =I65-SUM(I67:I69) -> 1301.98 | ... K73: =K65-SUM(K67:K69) -> 6042.17
A74: Total assest | B74: =B66 -> 4939.01 | C74: =C66 -> 7009.08 | D74: =D66 -> 9522.23 | E74: =E66 -> 11386.83 | F74: =F66 -> 12449.72 | G74: =G66 -> 14558.61 | H74: =H66 -> 16139.83 | I74: =I66 -> 19197.64 | ... K74: =K66 -> 27174.41
B76: {=B62:B64+B67:B69+B73} -> 1098.73
B77: 679.37
B78: 3713.91
B79: =SUM(B76:B78) -> 5492.01
A80: CASH FLOW:
A81: Report Date | B81: 42460 | C81: 42825 | D81: 43190 | E81: 43555 | F81: 43921 | G81: 44286 | H81: 44651 | I81: 45016 | J81: 45382 | K81: 45747
A82: Cash from Operating Activity | B82: 1463.08 | C82: 1707.97 | D82: 2482.25 | E82: 1575.47 | F82: 1694.12 | G82: 1690.97 | H82: 1527.04 | I82: 2822.66 | J82: 3723.71 | K82: 3979.92
A83: Cash from Investing Activity | B83: -1001.4 | C83: -1743.58 | D83: -2145.02 | E83: -659.88 | F83: -1508.41 | G83: -1625.3 | H83: -983.25 | I83: -2396.8 | J83: -2833.93 | K83: -2460.68
A84: Cash from Financing Activity | B84: -465.52 | C84: 25.29 | D84: -262.01 | E84: -292.3 | F84: -858.25 | G84: -14.76 | H84: -593.36 | I84: -417.44 | J84: -844.36 | K84: -1398.67
A85: Net Cash Flow | B85: -3.84 | C85: -10.32 | D85: 75.22 | E85: 623.29 | F85: -672.54 | G85: 50.91 | H85: -49.57 | I85: 8.42 | J85: 45.42 | K85: 120.57
A90: PRICE: | B90: 1918.06 | C90: 2558.75 | D90: 2837.27 | E90: 2054.77 | F90: 1309.59 | G90: 2603.95 | H90: 2457.15 | I90: 2948.85 | J90: 4019.3 | K90: 5347.7
A92: DERIVED:
A93: Adjusted Equity Shares in Cr | B93: 27.16 | C93: 27.21 | D93: 27.26 | E93: 27.28 | F93: 27.31 | G93: 27.33 | H93: 27.34 | I93: 27.35 | J93: 27.38 | K93: 27.42
A95: P/b | B95: =SUM(B57:B58) -> 3653.09 | C95: =SUM(C57:C58) -> 5345.07 | D95: =SUM(D57:D58) -> 7030.07 | E95: =SUM(E57:E58) -> 8918.72 | F95: =SUM(F57:F58) -> 9980.93 | G95: =SUM(G57:G58) -> 11438.08 | H95: =SUM(H57:H58) -> 12608 | I95: =SUM(I57:I58) -> 14990.28 | ... K95: =SUM(K57:K58) -> 21296.49

Sheet data
R1: Date | S1: Price | T1: Valoume | U1: Date | V1: 1000000
B2: S.No. | C2: Name | D2: CMP Rs. | E2: No. Eq. Shares Cr. | F2: Current market cap | G2: Debt Rs.Cr. | H2: Cash End Rs.Cr. | I2: net debt | J2: EV | K2: Sales Rs.Cr. | L2: EBIDTA | M2: NP 12M Rs.Cr. | R2: 43831 | S2: 2207.58 | T2: 1090000 | U2: 43831
B3: 1 | C3: Maruti Suzuki | D3: 15059 | E3: 31.44 | F3: =D3*E3 -> 473454.96 | G3: 99.9 | H3: 552.9 | I3: =G3-H3 -> -453 | J3: =F3+G3-H3 -> 473001.96 | K3: 171773.6 | L3: 31486.101 | M3: 14931.6 | O3: Date | P3: Price | R3: 43832 | S3: 2160.09 | T3: 2290000 | U3: 43832
B4: 2 | C4: M & M | D4: 3572 | E4: 124.35 | F4: =D4*E4 -> 444178.2 | G4: 126709.33 | H4: 20614.84 | I4: =G4-H4 -> 106094.49 | J4: =F4+G4-H4 -> 550272.69 | K4: 175704.22 | L4: 25564.964 | M4: 15506.66 | O4: 39461 | P4: 38.27 | R4: 43833 | S4: 2118.93 | T4: 1570000 | U4: 43833
B5: 3 | C5: Bajaj Auto | D5: 9647 | E5: 27.95 | F5: =D5*E5 -> 269633.65 | G5: 19693.24 | H5: 2847.6 | I5: =G5-H5 -> 16845.64 | J5: =F5+G5-H5 -> 286479.29 | K5: 57718.86 | L5: 12178.679 | M5: 8884.14 | O5: 39462 | P5: 37.73 | R5: 43836 | S5: 2086.05 | T5: 1260000 | U5: 43836
B6: 4 | C6: Eicher Motors | D6: 7209.5 | E6: 27.43 | F6: =D6*E6 -> 197756.58 | G6: 445.78 | H6: 263.01 | I6: =G6-H6 -> 182.77 | J6: =F6+G6-H6 -> 197939.35 | K6: 21427.66 | L6: 5774.7544 | M6: 5107.32 | O6: 39463 | P6: 36.5 | R6: 43837 | S6: 2080.38 | T6: 1370000 | U6: 43837
B7: 5 | C7: TVS Motor Co. | D7: 3712.7 | E7: 47.51 | F7: =D7*E7 -> 176390.38 | G7: 31589.29 | H7: 4386.24 | I7: =G7-H7 -> 27203.05 | J7: =F7+G7-H7 -> 203593.43 | K7: 52558.79 | L7: 13302.63 | M7: 3064.39 | O7: 39464 | P7: 37.05 | R7: 43838 | S7: 1989.22 | T7: 2890000 | U7: 43838
B8: 6 | C8: Hyundai Motor I | D8: 2164.3 | E8: 81.25 | F8: =D8*E8 -> 175849.38 | G8: 856.56 | H8: 8135.35 | I8: =G8-H8 -> -7278.79 | J8: =F8+G8-H8 -> 168570.59 | K8: 68100.58 | L8: 11760.97 | M8: 5683.48 | O8: 39465 | P8: 35.89 | R8: 43839 | S8: 2032.89 | T8: 2590000 | U8: 43839
B9: 7 | C9: Tata Motors PVeh | D9: 374.15 | E9: 368.23 | F9: =D9*E9 -> 137773.25 | G9: 67258 | H9: 40834 | I9: =G9-H9 -> 26424 | J9: =F9+G9-H9 -> 164197.25 | K9: 349637 | L9: 20313.91 | M9: 85324 | O9: 39468 | P9: 30.89 | R9: 43840 | S9: 2043.28 | T9: 2170000 | U9: 43840
B10: 8 | C10: Samvardh. Mothe. | D10: 120.99 | E10: 1055.44 | F10: =D10*E10 -> 127697.69 | G10: 19777.47 | H10: 6288.8 | I10: =G10-H10 -> 13488.67 | J10: =F10+G10-H10 -> 141186.36 | K10: 117367.72 | L10: 14588.808 | M10: 3551.45 | O10: 39469 | P10: 26.12 | R10: 43843 | S10: 2028 | T10: 1320000 | U10: 43843
B11: 9 | C11: Hero Motocorp | D11: 5766 | E11: 20.01 | F11: =D11*E11 -> 115377.66 | G11: 718.07 | H11: 574.08 | I11: =G11-H11 -> 143.99 | J11: =F11+G11-H11 -> 115521.65 | K11: 42175.84 | L11: 6195.6309 | M11: 5303.76 | O11: 39470 | P11: 28.94 | R11: 43844 | S11: 2048.97 | T11: 1160000 | U11: 43844
B12: 10 | C12: Bosch | D12: 36275 | E12: 2.95 | F12: =D12*E12 -> 107011.25 | G12: 109.1 | H12: 507.7 | I12: =G12-H12 -> -398.6 | J12: =F12+G12-H12 -> 106612.65 | K12: 18959.7 | L12: 5941.97 | M12: 2681.5 | O12: 39471 | P12: 25.95 | R12: 43845 | S12: 2062.48 | T12: 1080000 | U12: 43845
B13: 11 | C13: Bharat Forge | D13: 1573.2 | E13: 47.81 | F13: =D13*E13 -> 75214.692 | G13: 6658.37 | H13: 1291.38 | I13: =G13-H13 -> 5366.99 | J13: =F13+G13-H13 -> 80581.682 | K13: 15268.83 | L13: 4263.0573 | M13: 1078.56 | O13: 39472 | P13: 29.91 | R13: 43846 | S13: 2153.62 | T13: 2920000 | U13: 43846
B14: 12 | C14: Uno Minda | D14: 1230.8 | E14: 57.71 | F14: =D14*E14 -> 71029.468 | G14: 2851.71 | H14: 203.59 | I14: =G14-H14 -> 2648.12 | J14: =F14+G14-H14 -> 73677.588 | K14: 18849.5 | L14: 5662.3898 | M14: 1221.54 | O14: 39475 | P14: 28.7 | R14: 43847 | S14: 2129.22 | T14: 1830000 | U14: 43847
B15: 13 | C15: Schaeffler India | D15: 3814.2 | E15: 15.63 | F15: =D15*E15 -> 59615.946 | G15: 39.41 | H15: 1349.49 | I15: =G15-H15 -> -1310.08 | J15: =F15+G15-H15 -> 58305.866 | K15: 8834.57 | L15: 2830.5962 | M15: 1117.62 | O15: 39476 | P15: 28.3 | R15: 43850 | S15: 2136.51 | T15: 1010000 | U15: 43850
... B17: 15 | C17: Balkrishna Inds | D17: 2687.8 | E17: 19.33 | F17: =D17*E17 -> 51955.174 | G17: 3681.97 | H17: 86.25 | I17: =G17-H17 -> 3595.72 | J17: =F17+G17-H17 -> 55550.894 | K17: 10642.64 | L17: 2244.5328 | M17: 1312.19 | O17: 39478 | P17: 27.86 | R17: 43852 | S17: 2110 | T17: 786810 | U17: 43852
O18: 39479 | P18: 29.62 | R18: 43853 | S18: 2091.57 | T18: 1060000 | U18: 43853
O19: 39482 | P19: 30.89 | R19: 43854 | S19: 2093.08 | T19: 770750 | U19: 43854
O20: 39483 | P20: 31.42 | R20: 43857 | S20: 2109.52 | T20: 971080 | U20: 43857
L21: 100 | O21: 39484 | P21: 30.14 | R21: 43858 | S21: 2108.66 | T21: 972770 | U21: 43858
O22: 39485 | P22: 29.17 | R22: 43859 | S22: 2019.22 | T22: 2870000 | U22: 43859
B23: Company detials | C23: Eicher Motors Limited is an Indian multinational automotive company that manufactures motorcycles and commercial vehicles, headquartered in New Delhi. Eicher is the parent company of Royal Enfield, a manufacturer of middleweight motorcycles. It also manufactures Eicher branded trucks and buses, under a joint venture with Volvo Group. | K23: 10000000 | L23: 8022 | O23: 39486 | P23: 28.12 | R23: 43860 | S23: 2034.03 | T23: 1390000 | U23: 43860
O24: 39489 | P24: 25.91 | R24: 43861 | S24: 2028.93 | T24: 1020000 | U24: 43861
I25: Shareholder's name | J25: No of Shares (in Cr) | K25: Shareholding (%) | L25: Market value(in Cr) | O25: 39490 | P25: 26.74 | R25: 43862 | S25: 2005.92 | T25: 1010000 | U25: 43862
I26: THE SIMRAN SIDDHARTHA TARA BENEFIT TRUST (Name of trustees are mentioned in Note-4) | J26: 12.030648 | K26: 0.4386 | L26: =J26*$L$23 -> 96509.858 | O26: 39491 | P26: 27.05 | R26: 43864 | S26: 1988.35 | T26: 1490000 | U26: 43864
I27: Sbi Nifty 50 Etf | J27: 0.8167427 | K27: 0.0298 | L27: =J27*$L$23 -> 6551.9099 | O27: 39492 | P27: 27.6 | R27: 43865 | S27: 1951.27 | T27: 1500000 | U27: 43865
I28: Hdfc Trustee Company Limited-Hdfc Flexi Cap Fund | J28: 0.6861231 | K28: 0.025 | L28: =J28*$L$23 -> 5504.0795 | O28: 39493 | P28: 27.82 | R28: 43866 | S28: 1948.7 | T28: 1280000 | U28: 43866
I29: THE BRINDA LAL TRUST (Mrs Anita Lal Mr. Vikram Lal & Mr. Ravi Prakash) | J29: 0.485707 | K29: 0.0177 | L29: =J29*$L$23 -> 3896.3416 | O29: 39496 | P29: 28.03 | R29: 43867 | S29: 2039.12 | T29: 3950000 | U29: 43867
I30: New World Fund Inc | J30: 0.421887 | K30: 0.0154 | L30: =J30*$L$23 -> 3384.3775 | O30: 39497 | P30: 28.71 | R30: 43868 | S30: 1973.63 | T30: 2220000 | U30: 43868
I31: Uti Nifty 50 Etf | J31: 0.3671085 | K31: 0.0134 | L31: =J31*$L$23 -> 2944.9444 | O31: 39498 | P31: 28.54 | R31: 43871 | S31: 1905.72 | T31: 2440000 | U31: 43871
I32: Government Of Singapore | J32: 0.3233263 | K32: 0.0118 | L32: =J32*$L$23 -> 2593.7236 | O32: 39499 | P32: 28.61 | R32: 43872 | S32: 1900.92 | T32: 1300000 | U32: 43872
I33: Simran Lal | J33: 0.315241 | K33: 0.0115 | L33: =J33*$L$23 -> 2528.8633 | O33: 39500 | P33: 28.04 | R33: 43873 | S33: 1927.79 | T33: 1530000 | U33: 43873
I34: TARA LAL | J34: 0.314994 | K34: 0.0115 | L34: =J34*$L$23 -> 2526.8819 | O34: 39503 | P34: 28.16 | R34: 43874 | S34: 1935.53 | T34: 919630 | U34: 43874
I35: Nps Trust- A/C Sbi Pension Fund Scheme - State Govt | J35: 0.3089972 | K35: 0.0113 | L35: =J35*$L$23 -> 2478.7755 | O35: 39504 | P35: 28.04 | R35: 43875 | S35: 1870.36 | T35: 2320000 | U35: 43875
O36: 39505 | P36: 28.03 | R36: 43878 | S36: 1853.59 | T36: 1290000 | U36: 43878
O37: 39506 | P37: 28.11 | R37: 43879 | S37: 1876.04 | T37: 1810000 | U37: 43879
O38: 39507 | P38: 28.51 | R38: 43880 | S38: 1887.52 | T38: 1320000 | U38: 43880
O39: 39510 | P39: 27.66 | R39: 43881 | S39: 1884.87 | T39: 1250000 | U39: 43881
I40: Promoters | J40: 0.4906 | O40: 39511 | P40: 29.04 | R40: 43885 | S40: 1794.99 | T40: 1930000 | U40: 43885
I41: FIIs | J41: 0.2701 | O41: 39512 | P41: 27.84 | R41: 43886 | S41: 1753.23 | T41: 2570000 | U41: 43886
I42: DIIs | J42: 0.1464 | O42: 39514 | P42: 27.16 | R42: 43887 | S42: 1715.69 | T42: 2150000 | U42: 43887
I43: Public | J43: 0.0919 | O43: 39517 | P43: 27.14 | R43: 43888 | S43: 1705.34 | T43: 2550000 | U43: 43888
I44: Government | J44: 0.001 | O44: 39518 | P44: 27.02 | R44: 43889 | S44: 1660.23 | T44: 3260000 | U44: 43889
O45: 39519 | P45: 26.19 | R45: 43892 | S45: 1701.34 | T45: 3480000 | U45: 43892
O46: 39520 | P46: 26.44 | R46: 43893 | S46: 1788.85 | T46: 2750000 | U46: 43893
O47: 39521 | P47: 26 | R47: 43894 | S47: 1725.42 | T47: 4190000 | U47: 43894
O48: 39524 | P48: 24.02 | R48: 43895 | S48: 1777.54 | T48: 2310000 | U48: 43895
O49: 39525 | P49: 24.53 | R49: 43896 | S49: 1774.36 | T49: 1710000 | U49: 43896
C50: 1. Mr. Siddhartha Lal Executive Chairman (from February 13, 2025) | O50: 39526 | P50: 25.51 | R50: 43899 | S50: 1788.58 | T50: 1930000 | U50: 43899
C51: Managing Director (upto February 12, 2025) | O51: 39531 | P51: 23.54 | R51: 43901 | S51: 1775.36 | T51: 2220000 | U51: 43901
C52: 358.4 5.3 | O52: 39532 | P52: 24.19 | R52: 43902 | S52: 1687.78 | T52: 3640000 | U52: 43902
C53: 2. Mr. S Sandilya Chairman - Non-Executive Independent Director (upto | O53: 39533 | P53: 24.16 | R53: 43903 | S53: 1767.21 | T53: 2790000 | U53: 43903
C54: February 12, 2025) | O54: 39534 | P54: 23.78 | R54: 43906 | S54: 1649.37 | T54: 1920000 | U54: 43906
C55: 9.1 N.A.** | O55: 39535 | P55: 24.18 | R55: 43907 | S55: 1706.11 | T55: 1680000 | U55: 43907
C56: 3. Mr. Govindarajan | O56: 39538 | P56: 24.99 | R56: 43908 | S56: 1595.41 | T56: 1590000 | U56: 43908
C57: Balakrishnan | O57: 39539 | P57: 24.91 | R57: 43909 | S57: 1504.64 | T57: 1610000 | U57: 43909
C58: Managing Director (from February 13, 2025) | O58: 39540 | P58: 24.95 | R58: 43910 | S58: 1567.85 | T58: 2110000 | U58: 43910
C59: Whole Time Director (upto February 12, 2025) | O59: 39541 | P59: 24.71 | R59: 43913 | S59: 1370.59 | T59: 1440000 | U59: 43913
C60: 211.8 20.6# | O60: 39542 | P60: 24.41 | R60: 43914 | S60: 1420.85 | T60: 1130000 | U60: 43914
O61: 39545 | P61: 24.5 | R61: 43915 | S61: 1451.66 | T61: 761180 | U61: 43915
O62: 39546 | P62: 24.61 | R62: 43916 | S62: 1475.8 | T62: 2050000 | U62: 43916
O63: 39547 | P63: 24.5 | R63: 43917 | S63: 1431.98 | T63: 1110000 | U63: 43917
O64: 39548 | P64: 25.84 | R64: 43920 | S64: 1333.31 | T64: 2260000 | U64: 43920
O65: 39549 | P65: 26.55 | R65: 43921 | S65: 1309.59 | T65: 1670000 | U65: 43921
O66: 39553 | P66: 27 | R66: 43922 | S66: 1300.16 | T66: 1390000 | U66: 43922
O67: 39554 | P67: 27.39 | R67: 43924 | S67: 1268.01 | T67: 1810000 | U67: 43924
O68: 39555 | P68: 28.07 | R68: 43928 | S68: 1309.61 | T68: 2410000 | U68: 43928
O69: 39559 | P69: 27.7 | R69: 43929 | S69: 1315.85 | T69: 2800000 | U69: 43929
O70: 39560 | P70: 27.75 | R70: 43930 | S70: 1374.23 | T70: 3620000 | U70: 43930
O71: 39561 | P71: 27.36 | R71: 43934 | S71: 1340.06 | T71: 1270000 | U71: 43934
O72: 39562 | P72: 27.52 | R72: 43936 | S72: 1331.49 | T72: 2760000 | U72: 43936
... O1523: 41695 | P1523: 491.62 | R1523: 46066 | S1523: 8065 | T1523: 967940 | U1523: 46066
O1524: 41696 | P1524: 501.26
O1525: 41698 | P1525: 514.03
O1526: 41701 | P1526: 518.71
O1527: 41702 | P1527: 542.61
O1528: 41703 | P1528: 559.91
O1529: 41704 | P1529: 551.03
O1530: 41705 | P1530: 543.41
O1531: 41708 | P1531: 556
O1532: 41709 | P1532: 550.44
O1533: 41710 | P1533: 549.4
O1534: 41711 | P1534: 554.75
O1535: 41712 | P1535: 557.13
... O4483: 46066 | P4483: 8065

Sheet Footabal annalysis
B8: Footabal annalysis
C10: Open Low | D10: Low | E10: Open High | F10: High
B11: COMPS
B12: DCF Bear
B13: DCF Base
B14: DCF Bull
B15: 52W H/L
